Workbook
Name Slicer_City_Clean: #N/A
Name Slicer_Industry_Category: #N/A
Name Slicer_Year: #N/A

Sheet Raw Data
A1: Sr No | B1: Date dd/mm/yyyy | C1: Startup Name | D1: Industry Vertical | E1: SubVertical | F1: City Location | G1: Investors Name | H1: InvestmentnType | I1: Amount in USD | J1: Remarks
A2: 1 | B2: 43839 | C2: BYJU’S | D2: E-Tech | E2: E-learning | F2: Bengaluru | G2: Tiger Global Management | H2: Private Equity Round | I2: 200000000
A3: 2 | B3: 43843 | C3: Shuttl | D3: Transportation | E3: App based shuttle service | F3: Gurgaon | G3: Susquehanna Growth Equity | H3: Series C | I3: 8048394
A4: 3 | B4: 43839 | C4: Mamaearth | D4: E-commerce | E4: Retailer of baby and toddler products | F4: Bengaluru | G4: Sequoia Capital India | H4: Series B | I4: 18358860
A5: 4 | B5: 43832 | C5: https://www.wealthbucket.in/ | D5: FinTech | E5: Online Investment | F5: New Delhi | G5: Vinod Khatumal | H5: Pre-series A | I5: 3000000
A6: 5 | B6: 43832 | C6: Fashor | D6: Fashion and Apparel | E6: Embroiled Clothes For Women | F6: Mumbai | G6: Sprout Venture Partners | H6: Seed Round | I6: 1800000
A7: 6 | B7: 43843 | C7: Pando | D7: Logistics | E7: Open-market, freight management platform | F7: Chennai | G7: Chiratae Ventures | H7: Series A | I7: 9000000
A8: 7 | B8: 43840 | C8: Zomato | D8: Hospitality | E8: Online Food Delivery Platform | F8: Gurgaon | G8: Ant Financial | H8: Private Equity Round | I8: 150000000
A9: 8 | B9: 43811 | C9: Ecozen | D9: Technology | E9: Agritech | F9: Pune | G9: Sathguru Catalyzer Advisors | H9: Series A | I9: 6000000
A10: 9 | B10: 43805 | C10: CarDekho | D10: E-Commerce | E10: Automobile | F10: Gurgaon | G10: Ping An Global Voyager Fund | H10: Series D | I10: 70000000
A11: 10 | B11: 43802 | C11: Dhruva Space | D11: Aerospace | E11: Satellite Communication | F11: Bengaluru | G11: Mumbai Angels, Ravikanth Reddy | H11: Seed | I11: 50000000
A12: 11 | B12: 43812 | C12: Rivigo | D12: Technology | E12: Logistics Services and Solutions | F12: Gurgaon | G12: SAIF Partners, Spring Canter Investment Ltd. | H12: Series F | I12: 20000000
A13: 12 | B13: 43816 | C13: Healthians | D13: B2B-focused foodtech startup | E13: Food Solutions For Corporate | F13: Bengaluru | G13: Paytm, NPTK, Sabre Partners and Neoplux | H13: Series C | I13: 12000000
A14: 13 | B14: 43815 | C14: Licious | D14: E-Commerce | E14: Online Meat And Seafood Ordering Startup | F14: Bengaluru | G14: Vertex Growth Fund | H14: Series E | I14: 30000000
A15: 14 | B15: 43815 | C15: InCred | D15: Finance | E15: Non-Banking Financial Company | F15: Mumbai | H15: Debt Funding | I15: 5900000
A16: 15 | B16: 43813 | C16: Trell | D16: Video | E16: Experience Discovery Platform | F16: Bengaluru | G16: Ruizheng Investment | H16: Seed Round | I16: 2000000
A17: 16 | B17: 43810 | C17: Rein Games | D17: Gaming | E17: Real money based gaming startup | F17: Noida | G17: Manipal Education and Medical Group (MEMG) | H17: Seed Round | I17: 50000000
A18: 17 | B18: 43819 | C18: Lenskart.com | D18: E-Commerce | E18: Online Eyewear Shopping Portal | F18: Faridabad | G18: SoftBank Vision Fund | H18: Series G | I18: 231000000
A19: 18 | B19: 43782 | C19: Freshworks | D19: Software | E19: Business and customer engagement tools | F19: San Francisco | G19: Sequoia, CapitalG, Accel | H19: Series H | I19: 150000000
A20: 19 | B20: 43783 | C20: Misters | D20: Health and wellness | E20: Men's Health and Wellness brand | F20: Gurgaon | G20: Sauce.vc, Rainforest Ventures | H20: Series B | I20: 486000
A21: 20 | B21: 43782 | C21: Sunstone Eduversity Pvt. Ltd | D21: Education | E21: Elearning | F21: Gurgaon | G21: Prime Venture Partners, LetsVenture, PS1 Venture and GlobalLogic co-founder Rajul Garg | H21: Seed | I21: 1500000
A22: 21 | B22: 43786 | C22: Burger Singh | D22: Food and Beverage | E22: Indian Burger Brand | F22: Gurgaon | G22: RB Investments | H22: Venture | I22: undisclosed
A23: 22 | B23: 43787 | C23: Healthians | D23: Health and Wellness | E23: Healthcare services | F23: Gurgaon | G23: DG Daiwa Ventures, DG Incubation | H23: Series B | I23: 12000000
A24: 23 | B24: 43784 | C24: Ninjacart | D24: B2B Marketing | E24: Agritech | F24: Bengaluru | G24: Trifecta Capital Advisors | H24: Debt Funding | I24: 26000000
A25: 24 | B25: 43789 | C25: Aye Finance | D25: FinTech | E25: Financial Services To MSMEs | F25: Gurgaon | G25: FinTech | H25: Debt Funding | I25: 17411265
A26: 25 | B26: 43781 | C26: SuperGaming | D26: Video Games | E26: Social gaming platform | F26: Pune | G26: Dream Incubator | H26: Seed Funding | I26: 1300000
A27: 26 | B27: 43789 | C27: Clumio | D27: SaaS | E27: Recovery software | F27: San Jose, | G27: Altimeter Capital, Sutter Hill Ventures | H27: Series C | I27: 135000000
A28: 27 | B28: 43780 | C28: eBikeGo | D28: Last Mile Transportation | E28: Electric bike rental | F28: Amritsar | G28: Startup Buddy | H28: Seed | I28: 300000
A29: 28 | B29: 43788 | C29: Digital Mall Asia | D29: E-Commerce | E29: Virtual e-commerce platform | F29: Delhi | G29: Amour Infrastructure | H29: Seed Funding | I29: 220000000
A30: 29 | B30: 43787 | C30: Medikabazaar | D30: Healthcare | E30: B2B platform for medical supplies | F30: Mumbai | G30: Ackermans & van Haaren, HealthQuad, Rebright Partners, Toppan Printing | H30: Series B | I30: 15800000
A31: 30 | B31: 43784 | C31: Vogo Automotive | D31: Last Mile Transportation | E31: Scooter sharing app | F31: Kormangala | G31: Matrix Partners, Stellaris Venture Partners, Kalaari Capital | H31: Series B | I31: 283000000
A32: 31 | B32: 43788 | C32: Furtados School of Music | D32: Education | E32: Music Education | F32: Tulangan | G32: IAN Fund and DSG Consumer Partners | I32: 200000000
A33: 32 | B33: 43794 | C33: Paytm | D33: FinTech | E33: Mobile Wallet | F33: Noida | G33: Vijay Shekhar Sharma | H33: Funding Round | I33: 1000000000
A34: 33 | B34: 43742 | C34: Dunzo | D34: Customer Service | E34: Delivery Service | F34: Bengaluru | G34: Lightbox | H34: Series D | I34: 45000000
A35: 34 | B35: 43740 | C35: Udaan | D35: B2B | E35: Business development | F35: Bengaluru | G35: Altimeter Capital, DST Global | H35: Series D | I35: 585000000
A36: 35 | B36: 43759 | C36: The Man Company | D36: Consumer Goods | E36: Beauty and Grooming | F36: Gurgaon | G36: Ayushmann Khurana | H36: Corporate Round | I36: unknown
A37: 36 | B37: 43713 | C37: FPL Technologies | D37: FinTech | E37: Financial Services | F37: Pune | G37: Matrix Partners India, Sequoia India | H37: Maiden Round | I37: 4500000
A38: 37 | B38: 43712 | C38: Cashflo | D38: FinTech | E38: Invoice discounting platform and SME lending marketplace | F38: Mumbai | G38: SAIF Partners | H38: Series A | I38: 3300000
A39: 38 | B39: 43712 | C39: Digital F5 | D39: Advertising, Marketing | E39: Digital marketing firm | F39: Mumbai | G39: TIW Private Equity | H39: Private Equity Round | I39: 6000000
A40: 39 | B40: 43712 | C40: 3rdFlix | D40: SaaS | E40: Education Technology | F40: Hyderabad | G40: Exfinity Venture Partners | H40: pre-series A | I40: 5000000
A41: 40 | B41: 43712 | C41: 75F | D41: IoT | E41: Building automation system | F41: Burnsville | G41: Breakthrough Energy Ventures | H41: Series A | I41: 18000000
A42: 41 | B42: 43712 | C42: Myelin Foundry | D42: Information Technology | E42: Deep-technology | F42: Bengaluru | G42: Endiya Partners | H42: Seed | I42: 1000000
A43: 42 | B43: 43712 | C43: Atomberg Technology | D43: Consumer Technology | E43: Consumer Electronics, Home Appliances | F43: Mumbai | G43: A91 Partners | H43: Series A | I43: 10000000
A44: 43 | B44: 43712 | C44: GOQii | D44: Health and Wellness | E44: Wearable Fitness Bands | F44: Menlo Park | G44: Bennett Coleman and Company Ltd (BCCL) | H44: Series C | I44: 450000000
A45: 44 | B45: 43711 | C45: Vyapar App | D45: Accounting | E45: Mobile-based Accounting Software | F45: Bengaluru | G45: India Quotient, Axilor Ventures | H45: Series A | I45: 5000000
A46: 45 | B46: 43678 | C46: CarDekho | D46: E-Commerce | E46: Automotive | F46: Gurgaon | G46: SC GG India Mobility Holdings LLC | H46: Series C | I46: 20000000 | J46: nan
A47: 46 | B47: 43678 | C47: Progcap | D47: Finance | E47: Supply Chain Management | F47: New Delhi | G47: Sequoia India | H47: Series A | I47: 5000000 | J47: nan
A48: 47 | B48: 43678 | C48: MyPetrolPump | D48: Retail | E48: Fuel Delivery | F48: Bengaluru | H48: Seed Funding Round | I48: 1600000 | J48: nan
A49: 48 | B49: 43678 | C49: Alteria Capital | D49: Finance | E49: VC Funds | F49: Mumbai | G49: Azim Premji, Binny Bansal | H49: Single Venture | I49: 140000000 | J49: nan
A50: 49 | B50: 43678 | C50: Pine Labs | D50: Information Technology | E50: Last-mile retail transaction technology | F50: Noida | G50: Pine Labs Pte Ltd | H50: Corporate Round | I50: 38080000 | J50: nan
A51: 50 | B51: 43689 | C51: Meesho | D51: E-Commerce | E51: Social Commerce | F51: Bengaluru | G51: Naspers | H51: Series D | I51: 125000000 | J51: nan
A52: 51 | B52: 43690 | C52: Cars24 | D52: E-Commerce | E52: Car Retail | F52: Gurugram | G52: MS Dhoni | H52: Series D | I52: 11000000 | J52: nan
A53: 52 | B53: 43690 | C53: Uniphore | D53: Customer Service Platform | E53: Conversational AI | F53: Palo Alto | G53: March Capital Partners | H53: Series C | I53: 51000000 | J53: nan
A54: 53 | B54: 43700 | C54: Zendrive | D54: Automotive | E54: Road Safety Analytics | F54: San Francisco | G54: XL Innovate | H54: Series B | I54: 37000000 | J54: nan
A55: 54 | B55: 43700 | C55: Lo! Foods | D55: Consumer Goods | E55: Low carb food for Diabetics | F55: Bengaluru | G55: Rashmi Daga (founder, FreshMenu), Raveen Sastry (co-founder, Myntra) and Mitesh Shah (finance chief, BookMyShow) | H55: Seed Round | I55: 500000 | J55: nan
A56: 55 | B56: 43700 | C56: Tala | D56: FinTech | E56: Digital Lending Platform | F56: Santa Monica | G56: RPS Ventures | H56: Series D | I56: 110000000 | J56: nan
A57: 56 | B57: 43699 | C57: INDwealth | D57: FinTech | E57: Wealth Management | F57: Gurgaon | G57: Tiger Global Management | H57: Venture Round | I57: 15000000 | J57: nan
A58: 57 | B58: 43698 | C58: HungerBox | D58: Food and Beverage | E58: B2B Foodtech | F58: Bengaluru | G58: One97 Communications Ltd. | H58: Series C | I58: 6590000 | J58: nan
A59: 58 | B59: 43700 | C59: AdmitKard | D59: EdTech | E59: University Admissions | F59: Noida | G59: Growth DNA | H59: Seed Round | I59: 1000000 | J59: nan
A60: 59 | B60: 43696 | C60: Mishry Reviews | D60: Services | E60: Product Review | F60: Gurgaon | G60: Vir Sanghvi | H60: Series A | I60: Undisclosed | J60: nan
A61: 60 | B61: 43696 | C61: Grofers | D61: E-Commerce | E61: Grocery Delivery | F61: Gurgaon | G61: Softbank Vision Fund | H61: Series F | I61: 70000000 | J61: nan
A62: 61 | B62: 43704 | C62: Rapido Bike Taxi | D62: Transportation | E62: Bike Taxi | F62: Bengaluru | G62: Westbridge Capital | H62: Series B | I62: 3900000000 | J62: nan
A63: 62 | B63: 43648 | C63: RenewBuy | D63: Finance | E63: Auto Insurance | F63: Gurgaon | G63: Lok Capital, IIFL Wealth | H63: Series B | I63: 19000000 | J63: nan
A64: 63 | B64: 43648 | C64: Atlan | D64: Information Technology | E64: Big Data | F64: Singapore | G64: WaterBridge Ventures | H64: Pre-Series A | I64: 2500000 | J64: nan
A65: 64 | B65: 43647 | C65: WizCounsel | D65: Compliance | E65: Consulting | F65: New Delhi | G65: Kapil Dev | H65: Angel | I65: 145000 | J65: nan
A66: 65 | B66: 43649 | C66: Ola Cabs | D66: Transport | E66: Cabs | F66: Kormangala | G66: DIG Investment Ab, Deshe Holdings, Samih Toukan and Hussam Khoury | H66: Series J | I66: 1000000 | J66: nan
A67: 66 | B67: 43647 | C67: Uniphore | D67: Artificial Intelligence | E67: Speech Recognition | F67: Taramani | G67: March Capital Partners | H67: Series C | I67: 38080000 | J67: nan
A68: 67 | B68: 43650 | C68: Daalchini Technologies | D68: Food and Beverage | E68: Digital Vending Machine | F68: New Delhi | G68: Artha Venture | H68: Seed Round | I68: 500000 | J68: nan
A69: 68 | B69: 43656 | C69: "BYJU\\'S" | D69: EdTech | E69: Education | F69: Bengaluru | G69: Qatar Investment Authority | H69: Private Equity Round | I69: 150000000 | J69: nan
A70: 69 | B70: 43657 | C70: Moglix | D70: E-Commerce | E70: Industrial Tools and Equipments | F70: Singapore | G70: Composite Capital Management, Sequoia Capital India, Tiger Global Management | H70: Series D | I70: 60000000 | J70: nan
A71: 70 | B71: 43656 | C71: Ezyhaul | D71: Tech | E71: Logistics | F71: Singapore | G71: Undisclosed | H71: Series B | I71: 16000000 | J71: nan
A72: 71 | B72: 43656 | C72: Indus OS | D72: Tech | E72: Smartphone Operating System | F72: Andheri | G72: Ventureast | H72: Series B | I72: 5750000 | J72: nan
... A77: 76 | B77: 43620 | C77: Bira91 | D77: Food and Beverage | E77: Brewery | F77: New Delhi | G77: Anicut Capital | H77: Debt Funding | I77: 10000000 | J77: nan
A78: 77 | B78: 43619 | C78: FabHotels | D78: E-Commerce | E78: Hospitality | F78: Gurgaon | G78: Goldman Sachs, Accel Partners and Qualcomm | I78: 4889975.5 | J78: nan
A79: 78 | B79: 43619 | C79: Avail Finance | D79: Finance | E79: FinTech | F79: Bengaluru | G79: Matrix Partners | H79: Series A | I79: 9000000 | J79: nan
A80: 79 | B80: 43620 | C80: BharatPe | D80: Finance | E80: FinTech | F80: New Delhi | G80: Insight Partners | H80: Series B | I80: 75000000 | J80: nan
A81: 80 | B81: 43620 | C81: Recykal | D81: Waste Management Service | E81: Optimization | F81: Hyderabad | G81: Triton Investment Advisors, Pidilite Industries director Ajay Parekh | H81: pre-Series A | I81: 26000000 | J81: nan
A82: 81 | B82: 43619 | C82: Agara Labs | D82: Deep-Tech | E82: Artificial Intelligence | F82: Bengaluru | G82: Blume Ventures and RTP Global | H82: pre-Series A | I82: 2500000 | J82: nan
A83: 82 | B83: 43622 | C83: Sistema.bio | D83: Agriculture | E83: Hybrid Reactor Biodigestor | F83: Nairobi | G83: Shell Foundation, DILA CAPITAL, Engie RDE Fund, EcoEnterprise Fund, EDFIMC (ElectriFI), Endeavor Catalyst Fund, CoCapital, Triodos, Alpha Mundi, and Lendahand | I83: 2739034.7 | J83: nan
A84: 83 | B84: 43622 | C84: Chakr Innovation | D84: Energy | E84: Renewable Energy | F84: New Delhi | G84: IAN Fund | H84: Series A | I84: 26000000 | J84: nan
A85: 84 | B85: 43622 | C85: Pratilipi | D85: Digital Media | E85: E-Books | F85: Bengaluru | G85: Qiming Venture Partners | H85: Series B | I85: 15109500 | J85: nan
A86: 85 | B86: 43626 | C86: Bolo App | D86: Digital Media | E86: Video Platform | F86: Bengaluru | G86: Nexus Venture Partners | H86: Seed Funding | I86: 430200 | J86: nan
A87: 86 | B87: 43626 | C87: OkCredit | D87: FinTech | E87: Financial Services | F87: Haryana | G87: Tiger Global Management | H87: Series A | I87: 15500000 | J87: nan
A88: 87 | B88: 43622 | C88: Biz2Credit | D88: FinTech | E88: Online Lending Platform | F88: New York | G88: WestBridge Capital | H88: Series B | I88: 52000000 | J88: nan
A89: 88 | B89: 43624 | C89: Vogo Automotive Pvt. Ltd. | D89: Transportation | E89: Dockless Scooter Rental Company | F89: Karnataka | G89: Alteria Capital | H89: Debt Funding | I89: 3584000 | J89: nan
A90: 89 | B90: 43620 | C90: Leegality | D90: Services | E90: Digital Documentation | F90: Mumbai/Bengaluru | G90: Mumbai Angels | H90: Series A | I90: 3400000 | J90: nan
A91: 90 | B91: 43591 | C91: Ola Electric | D91: Transport | E91: Cabs | F91: Bengaluru | G91: Tata Sons | H91: Series A | I91: undisclosed | J91: nan
A92: 91 | B92: 43591 | C92: Saahas Zero Waste | D92: Waste Management Service | E92: Optimization | F92: Bengaluru | G92: C4D Partners | H92: Venture - Series Unknown | I92: 868600 | J92: nan
A93: 92 | B93: 43590 | C93: StyleDotMe | D93: E-commerce | E93: Fashion and Shopping | F93: Delhi | G93: Indian Angel Network and other angel investors, Innov8 founder Ritesh Malik, Josh Talks founders Supriya Paul and Shobha Banga, and former Hero Corporate president Rohit Chanana | H93: Bridge Round | I93: undisclosed | J93: nan
A94: 93 | B94: 43586 | C94: BlackBuck | D94: Transport | E94: Logistics | F94: Bengaluru | G94: Goldman Sachs Investment Partners and Silicon Valley-based Accel, Wellington, Sequoia Capital, B Capital, LightStreet, Sands Capital and International Finance Corporation, | H94: Series D | I94: 150000000 | J94: nan
A95: 94 | B95: 43587 | C95: Zenoti | D95: Saas | E95: Beauty and Wellness Industry | F95: Hyderabad | G95: Tiger Global Management | H95: Series C | I95: 50000000 | J95: nan
A96: 95 | B96: 43613 | C96: Ather Energy | D96: Automobile | E96: Electric Vehicle | F96: Bengaluru | G96: Sachin Bansal | H96: Series C | I96: 51000000 | J96: nan
A97: 96 | B97: 43613 | C97: FreshVnF | D97: Agtech | E97: Fresh Agriculture Produces | F97: Mumbai | G97: Equanimity Ventures | H97: Seed Round | I97: 140000000 | J97: nan
A98: 97 | B98: 43615 | C98: GlowRoad | D98: E-commerce | E98: Retail | F98: Bengaluru | G98: Korea Investment Partners, Vertex Ventures | H98: Series B | I98: 11500000 | J98: nan
A99: 98 | B99: 43616 | C99: Bira91 | D99: Food and Beverage | E99: Brewery | F99: New Delhi | G99: Sixth Sense Ventures | H99: Series B | I99: 5600000 | J99: nan
A100: 99 | B100: 43571 | C100: Kuvera | D100: Finance | E100: Wealth Management | F100: Bengaluru | G100: Eight Roads | H100: Series A | I100: 45000000 | J100: nan
A101: 100 | B101: 43567 | C101: Medlife | D101: E-commerce | E101: Online Medicine | F101: Bengaluru | G101: Prasid Uno Family Trust | H101: Private Equity | I101: 17000000 | J101: nan
A102: 101 | B102: 43565 | C102: Kabadiwala | D102: E-commerce | E102: Waste Management | F102: Bhopal | G102: Unilever, Beehive Capital Advisor, ABCOM Investments, Parekh Marine Transport, | H102: Private Equity | I102: 430665 | J102: nan
A103: 102 | B103: 43568 | C103: Tripoto | D103: Social Media | E103: Travel | F103: New Delhi | G103: Orchid India, Hornbill Orchid India Fund, Chiratae Ventures (formerly IDG Ventures), 3one4 Capital, Lasmer NV | H103: Series B | I103: 3591375 | J103: nan
A104: 103 | B104: 43567 | C104: Azah | D104: Health and Wellness | E104: Organic wellness | F104: Gurugram | G104: Unnamed angel investors | H104: Seed Funding | I104: 200000 | J104: nan
...

Sheet Cleaned Data
A1: Sr No | B1: Date | C1: Startup Name | D1: Industry | E1: Sub Industry | F1: City | G1: Investors | H1: Primary Investor | I1: Investor Count | J1: Multiple Investors | K1: Investment Type | L1: Amount USD | M1: Year | N1: Month | O1: Amount Crore INR | P1: Funding Stage Clean | Q1: Industry Category | R1: City Clean
A2: 1 | B2: 43839 | C2: BYJU’S | D2: E-Tech | E2: E-learning | F2: Bengaluru | G2: Tiger Global Management | H2: =IFERROR(TRIM(LEFT(G2,FIND(",",G2)-1)),TRIM(G2)) -> Tiger Global Management | I2: =IF(TRIM(G2)="",0,LEN(G2)-LEN(SUBSTITUTE(G2,",",""))+1) -> 1 | J2: =IF(Table1[[#This Row],[Investor Count]]>1,"Yes","No") -> No | K2: Private Equity Round | L2: 200000000 | M2: =YEAR(B2) -> 2020 | N2: =TEXT(B2,"mmmm") -> January | O2: 1919.41 | P2: =IF(ISBLANK(K2),"Unknown",IF(OR(ISNUMBER(SEARCH("seed",K2)),ISNUMBER(SEARCH("Seed",K2))),"Seed",IF(ISNUMBER(SEARCH("Series A",K2)),"Series A",IF(ISNUMBER(SEARCH("Series B",K2)),"Series B",IF(ISNUMBER(SEARCH("Series C",K2)),"Series C",IF(ISNUMBER(SEARCH("Series D",K2)),"Series D",IF(ISNUMBER(SEARCH("Private Equity",K2)),"Private Equity","Other"))))))) -> Private Equity | Q2: =IF(IFERROR(SEARCH("ecom",D2),0)+IFERROR(SEARCH("commerce",D2),0)+IFERROR(SEARCH("retail",D2),0)>0,"E-Commerce", IF(IFERROR(SEARCH("fintech",D2),0)+IFERROR(SEARCH("finance",D2),0)+IFERROR(SEARCH("financial",D2),0)+IFERROR(SEARCH("lending",D2),0)+IFERROR(SEARCH("payment",D2),0)+IFERROR(SEARCH("banking",D2),0)+IFERROR(SEARCH("insurance",D2),0)>0,"FinTech", IF(IFERROR(SEARCH("tech",D2),0)+IFERROR(SEARCH("software",D2),0)+IFERROR(SEARCH("saas",D2),0)+IFERROR(SEARCH("ai",D2),0)+IFERROR(SEARCH("iot",D2),0)+IFERROR(SEARCH("cloud",D2),0)+IFERROR(SEARCH("data",D2),0)+IFERROR(SEARCH("analytics",D2),0)>0,"Technology", IF(IFERROR(SEARCH("food",D2),0)+IFERROR(SEARCH("restaurant",D2),0)+IFERROR(SEARCH("hospitality",D2),0)+IFERROR(SEARCH("beverage",D2),0)+IFERROR(SEARCH("delivery",D2),0)>0,"Food & Beverage", IF(IFERROR(SEARCH("health",D2),0)+IFERROR(SEARCH("medical",D2),0)+IFERROR(SEARCH("pharma",D2),0)+IFERROR(SEARCH("wellness",D2),0)+IFERROR(SEARCH("fitness",D2),0)>0,"Healthcare", IF(IFERROR(SEARCH("edu",D2),0)+IFERROR(SEARCH("learning",D2),0)+IFERROR(SEARCH("school",D2),0)+IFERROR(SEARCH("e-tech",D2),0)>0,"Education", IF(IFERROR(SEARCH("logistics",D2),0)+IFERROR(SEARCH("transport",D2),0)+IFERROR(SEARCH("delivery",D2),0)+IFERROR(SEARCH("mobility",D2),0)+IFERROR(SEARCH("automobile",D2),0)>0,"Logistics & Transport", IF(IFERROR(SEARCH("travel",D2),0)+IFERROR(SEARCH("hotel",D2),0)+IFERROR(SEARCH("booking",D2),0)+IFERROR(SEARCH("tourism",D2),0)>0,"Travel & Hospitality", IF(IFERROR(SEARCH("fashion",D2),0)+IFERROR(SEARCH("apparel",D2),0)+IFERROR(SEARCH("clothing",D2),0)+IFERROR(SEARCH("jewelry",D2),0)+IFERROR(SEARCH("beauty",D2),0)>0,"Fashion & Lifestyle", IF(IFERROR(SEARCH("media",D2),0)+IFERROR(SEARCH("entertainment",D2),0)+IFERROR(SEARCH("video",D2),0)+IFERROR(SEARCH("gaming",D2),0)+IFERROR(SEARCH("music",D2),0)+IFERROR(SEARCH("social",D2),0)>0,"Media & Entertainment", IF(IFERROR(SEARCH("agri",D2),0)+IFERROR(SEARCH("farm",D2),0)+IFERROR(SEARCH("agtech",D2),0)>0,"Agriculture", IF(IFERROR(SEARCH("real estate",D2),0)+IFERROR(SEARCH("property",D2),0)+IFERROR(SEARCH("housing",D2),0)>0,"Real Estate", IF(IFERROR(SEARCH("energy",D2),0)+IFERROR(SEARCH("solar",D2),0)+IFERROR(SEARCH("clean tech",D2),0)+IFERROR(SEARCH("waste",D2),0)>0,"Energy & Environment", IF(IFERROR(SEARCH("hr",D2),0)+IFERROR(SEARCH("recruit",D2),0)+IFERROR(SEARCH("hiring",D2),0)+IFERROR(SEARCH("job",D2),0)>0,"HR & Recruitment", "Others")))))))))))))) -> Technology | R2: =IF(ISNUMBER(SEARCH("bang",F2)),"Bangalore",IF(ISNUMBER(SEARCH("beng",F2)),"Bangalore",IF(ISNUMBER(SEARCH("mumbai",F2)),"Mumbai",IF(ISNUMBER(SEARCH("delhi",F2)),"Delhi-NCR",IF(ISNUMBER(SEARCH("gurgaon",F2)),"Delhi-NCR",IF(ISNUMBER(SEARCH("gurugram",F2)),"Delhi-NCR",IF(ISNUMBER(SEARCH("noida",F2)),"Delhi-NCR",IF(ISNUMBER(SEARCH("faridabad",F2)),"Delhi-NCR",IF(ISNUMBER(SEARCH("chennai",F2)),"Chennai",IF(ISNUMBER(SEARCH("hyderabad",F2)),"Hyderabad",IF(ISNUMBER(SEARCH("pune",F2)),"Pune",IF(ISNUMBER(SEARCH("kolkata",F2)),"Kolkata",IF(ISNUMBER(SEARCH("ahmedabad",F2)),"Ahmedabad",IF(ISNUMBER(SEARCH("jaipur",F2)),"Jaipur",IF(ISNUMBER(SEARCH("coimbatore",F2)),"Coimbatore",IF(ISNUMBER(SEARCH("kochi",F2)),"Kerala Cities",IF(ISNUMBER(SEARCH("cochin",F2)),"Kerala Cities",IF(ISNUMBER(SEARCH("francisco",F2)),"USA",IF(ISNUMBER(SEARCH("new york",F2)),"USA",IF(ISNUMBER(SEARCH("california",F2)),"USA",IF(ISNUMBER(SEARCH("palo alto",F2)),"USA",IF(ISNUMBER(SEARCH("santa",F2)),"USA",IF(ISNUMBER(SEARCH("singapore",F2)),"Singapore",IF(ISNUMBER(SEARCH("london",F2)),"London/UK",IF(F2="","Unknown","Other Cities"))))))))))))))))))))))))) -> Bangalore
A3: 2 | B3: 43843 | C3: Shuttl | D3: Transportation | E3: App based shuttle service | F3: Gurgaon | G3: Susquehanna Growth Equity | H3: =IFERROR(TRIM(LEFT(G3,FIND(",",G3)-1)),TRIM(G3)) -> Susquehanna Growth Equity | I3: =IF(TRIM(G3)="",0,LEN(G3)-LEN(SUBSTITUTE(G3,",",""))+1) -> 1 | J3: =IF(Table1[[#This Row],[Investor Count]]>1,"Yes","No") -> No | K3: Series C | L3: 8048394 | M3: =YEAR(B3) -> 2020 | N3: =TEXT(B3,"mmmm") -> January | O3: 77.24084 | P3: =IF(ISBLANK(K3),"Unknown",IF(OR(ISNUMBER(SEARCH("seed",K3)),ISNUMBER(SEARCH("Seed",K3))),"Seed",IF(ISNUMBER(SEARCH("Series A",K3)),"Series A",IF(ISNUMBER(SEARCH("Series B",K3)),"Series B",IF(ISNUMBER(SEARCH("Series C",K3)),"Series C",IF(ISNUMBER(SEARCH("Series D",K3)),"Series D",IF(ISNUMBER(SEARCH("Private Equity",K3)),"Private Equity","Other"))))))) -> Series C | Q3: =IF(IFERROR(SEARCH("ecom",D3),0)+IFERROR(SEARCH("commerce",D3),0)+IFERROR(SEARCH("retail",D3),0)>0,"E-Commerce", IF(IFERROR(SEARCH("fintech",D3),0)+IFERROR(SEARCH("finance",D3),0)+IFERROR(SEARCH("financial",D3),0)+IFERROR(SEARCH("lending",D3),0)+IFERROR(SEARCH("payment",D3),0)+IFERROR(SEARCH("banking",D3),0)+IFERROR(SEARCH("insurance",D3),0)>0,"FinTech", IF(IFERROR(SEARCH("tech",D3),0)+IFERROR(SEARCH("software",D3),0)+IFERROR(SEARCH("saas",D3),0)+IFERROR(SEARCH("ai",D3),0)+IFERROR(SEARCH("iot",D3),0)+IFERROR(SEARCH("cloud",D3),0)+IFERROR(SEARCH("data",D3),0)+IFERROR(SEARCH("analytics",D3),0)>0,"Technology", IF(IFERROR(SEARCH("food",D3),0)+IFERROR(SEARCH("restaurant",D3),0)+IFERROR(SEARCH("hospitality",D3),0)+IFERROR(SEARCH("beverage",D3),0)+IFERROR(SEARCH("delivery",D3),0)>0,"Food & Beverage", IF(IFERROR(SEARCH("health",D3),0)+IFERROR(SEARCH("medical",D3),0)+IFERROR(SEARCH("pharma",D3),0)+IFERROR(SEARCH("wellness",D3),0)+IFERROR(SEARCH("fitness",D3),0)>0,"Healthcare", IF(IFERROR(SEARCH("edu",D3),0)+IFERROR(SEARCH("learning",D3),0)+IFERROR(SEARCH("school",D3),0)+IFERROR(SEARCH("e-tech",D3),0)>0,"Education", IF(IFERROR(SEARCH("logistics",D3),0)+IFERROR(SEARCH("transport",D3),0)+IFERROR(SEARCH("delivery",D3),0)+IFERROR(SEARCH("mobility",D3),0)+IFERROR(SEARCH("automobile",D3),0)>0,"Logistics & Transport", IF(IFERROR(SEARCH("travel",D3),0)+IFERROR(SEARCH("hotel",D3),0)+IFERROR(SEARCH("booking",D3),0)+IFERROR(SEARCH("tourism",D3),0)>0,"Travel & Hospitality", IF(IFERROR(SEARCH("fashion",D3),0)+IFERROR(SEARCH("apparel",D3),0)+IFERROR(SEARCH("clothing",D3),0)+IFERROR(SEARCH("jewelry",D3),0)+IFERROR(SEARCH("beauty",D3),0)>0,"Fashion & Lifestyle", IF(IFERROR(SEARCH("media",D3),0)+IFERROR(SEARCH("entertainment",D3),0)+IFERROR(SEARCH("video",D3),0)+IFERROR(SEARCH("gaming",D3),0)+IFERROR(SEARCH("music",D3),0)+IFERROR(SEARCH("social",D3),0)>0,"Media & Entertainment", IF(IFERROR(SEARCH("agri",D3),0)+IFERROR(SEARCH("farm",D3),0)+IFERROR(SEARCH("agtech",D3),0)>0,"Agriculture", IF(IFERROR(SEARCH("real estate",D3),0)+IFERROR(SEARCH("property",D3),0)+IFERROR(SEARCH("housing",D3),0)>0,"Real Estate", IF(IFERROR(SEARCH("energy",D3),0)+IFERROR(SEARCH("solar",D3),0)+IFERROR(SEARCH("clean tech",D3),0)+IFERROR(SEARCH("waste",D3),0)>0,"Energy & Environment", IF(IFERROR(SEARCH("hr",D3),0)+IFERROR(SEARCH("recruit",D3),0)+IFERROR(SEARCH("hiring",D3),0)+IFERROR(SEARCH("job",D3),0)>0,"HR & Recruitment", "Others")))))))))))))) -> Logistics & Transport | R3: =IF(ISNUMBER(SEARCH("bang",F3)),"Bangalore",IF(ISNUMBER(SEARCH("beng",F3)),"Bangalore",IF(ISNUMBER(SEARCH("mumbai",F3)),"Mumbai",IF(ISNUMBER(SEARCH("delhi",F3)),"Delhi-NCR",IF(ISNUMBER(SEARCH("gurgaon",F3)),"Delhi-NCR",IF(ISNUMBER(SEARCH("gurugram",F3)),"Delhi-NCR",IF(ISNUMBER(SEARCH("noida",F3)),"Delhi-NCR",IF(ISNUMBER(SEARCH("faridabad",F3)),"Delhi-NCR",IF(ISNUMBER(SEARCH("chennai",F3)),"Chennai",IF(ISNUMBER(SEARCH("hyderabad",F3)),"Hyderabad",IF(ISNUMBER(SEARCH("pune",F3)),"Pune",IF(ISNUMBER(SEARCH("kolkata",F3)),"Kolkata",IF(ISNUMBER(SEARCH("ahmedabad",F3)),"Ahmedabad",IF(ISNUMBER(SEARCH("jaipur",F3)),"Jaipur",IF(ISNUMBER(SEARCH("coimbatore",F3)),"Coimbatore",IF(ISNUMBER(SEARCH("kochi",F3)),"Kerala Cities",IF(ISNUMBER(SEARCH("cochin",F3)),"Kerala Cities",IF(ISNUMBER(SEARCH("francisco",F3)),"USA",IF(ISNUMBER(SEARCH("new york",F3)),"USA",IF(ISNUMBER(SEARCH("california",F3)),"USA",IF(ISNUMBER(SEARCH("palo alto",F3)),"USA",IF(ISNUMBER(SEARCH("santa",F3)),"USA",IF(ISNUMBER(SEARCH("singapore",F3)),"Singapore",IF(ISNUMBER(SEARCH("london",F3)),"London/UK",IF(F3="","Unknown","Other Cities"))))))))))))))))))))))))) -> Delhi-NCR
A4: 3 | B4: 43839 | C4: Mamaearth | D4: Ecommerce | E4: Retailer of baby , toddler products | F4: Bengaluru | G4: Sequoia Capital India | H4: =IFERROR(TRIM(LEFT(G4,FIND(",",G4)-1)),TRIM(G4)) -> Sequoia Capital India | I4: =IF(TRIM(G4)="",0,LEN(G4)-LEN(SUBSTITUTE(G4,",",""))+1) -> 1 | J4: =IF(Table1[[#This Row],[Investor Count]]>1,"Yes","No") -> No | K4: Series B | L4: 18358860 | M4: =YEAR(B4) -> 2020 | N4: =TEXT(B4,"mmmm") -> January | O4: 176.1909 | P4: =IF(ISBLANK(K4),"Unknown",IF(OR(ISNUMBER(SEARCH("seed",K4)),ISNUMBER(SEARCH("Seed",K4))),"Seed",IF(ISNUMBER(SEARCH("Series A",K4)),"Series A",IF(ISNUMBER(SEARCH("Series B",K4)),"Series B",IF(ISNUMBER(SEARCH("Series C",K4)),"Series C",IF(ISNUMBER(SEARCH("Series D",K4)),"Series D",IF(ISNUMBER(SEARCH("Private Equity",K4)),"Private Equity","Other"))))))) -> Series B | Q4: =IF(IFERROR(SEARCH("ecom",D4),0)+IFERROR(SEARCH("commerce",D4),0)+IFERROR(SEARCH("retail",D4),0)>0,"E-Commerce", IF(IFERROR(SEARCH("fintech",D4),0)+IFERROR(SEARCH("finance",D4),0)+IFERROR(SEARCH("financial",D4),0)+IFERROR(SEARCH("lending",D4),0)+IFERROR(SEARCH("payment",D4),0)+IFERROR(SEARCH("banking",D4),0)+IFERROR(SEARCH("insurance",D4),0)>0,"FinTech", IF(IFERROR(SEARCH("tech",D4),0)+IFERROR(SEARCH("software",D4),0)+IFERROR(SEARCH("saas",D4),0)+IFERROR(SEARCH("ai",D4),0)+IFERROR(SEARCH("iot",D4),0)+IFERROR(SEARCH("cloud",D4),0)+IFERROR(SEARCH("data",D4),0)+IFERROR(SEARCH("analytics",D4),0)>0,"Technology", IF(IFERROR(SEARCH("food",D4),0)+IFERROR(SEARCH("restaurant",D4),0)+IFERROR(SEARCH("hospitality",D4),0)+IFERROR(SEARCH("beverage",D4),0)+IFERROR(SEARCH("delivery",D4),0)>0,"Food & Beverage", IF(IFERROR(SEARCH("health",D4),0)+IFERROR(SEARCH("medical",D4),0)+IFERROR(SEARCH("pharma",D4),0)+IFERROR(SEARCH("wellness",D4),0)+IFERROR(SEARCH("fitness",D4),0)>0,"Healthcare", IF(IFERROR(SEARCH("edu",D4),0)+IFERROR(SEARCH("learning",D4),0)+IFERROR(SEARCH("school",D4),0)+IFERROR(SEARCH("e-tech",D4),0)>0,"Education", IF(IFERROR(SEARCH("logistics",D4),0)+IFERROR(SEARCH("transport",D4),0)+IFERROR(SEARCH("delivery",D4),0)+IFERROR(SEARCH("mobility",D4),0)+IFERROR(SEARCH("automobile",D4),0)>0,"Logistics & Transport", IF(IFERROR(SEARCH("travel",D4),0)+IFERROR(SEARCH("hotel",D4),0)+IFERROR(SEARCH("booking",D4),0)+IFERROR(SEARCH("tourism",D4),0)>0,"Travel & Hospitality", IF(IFERROR(SEARCH("fashion",D4),0)+IFERROR(SEARCH("apparel",D4),0)+IFERROR(SEARCH("clothing",D4),0)+IFERROR(SEARCH("jewelry",D4),0)+IFERROR(SEARCH("beauty",D4),0)>0,"Fashion & Lifestyle", IF(IFERROR(SEARCH("media",D4),0)+IFERROR(SEARCH("entertainment",D4),0)+IFERROR(SEARCH("video",D4),0)+IFERROR(SEARCH("gaming",D4),0)+IFERROR(SEARCH("music",D4),0)+IFERROR(SEARCH("social",D4),0)>0,"Media & Entertainment", IF(IFERROR(SEARCH("agri",D4),0)+IFERROR(SEARCH("farm",D4),0)+IFERROR(SEARCH("agtech",D4),0)>0,"Agriculture", IF(IFERROR(SEARCH("real estate",D4),0)+IFERROR(SEARCH("property",D4),0)+IFERROR(SEARCH("housing",D4),0)>0,"Real Estate", IF(IFERROR(SEARCH("energy",D4),0)+IFERROR(SEARCH("solar",D4),0)+IFERROR(SEARCH("clean tech",D4),0)+IFERROR(SEARCH("waste",D4),0)>0,"Energy & Environment", IF(IFERROR(SEARCH("hr",D4),0)+IFERROR(SEARCH("recruit",D4),0)+IFERROR(SEARCH("hiring",D4),0)+IFERROR(SEARCH("job",D4),0)>0,"HR & Recruitment", "Others")))))))))))))) -> E-Commerce | R4: =IF(ISNUMBER(SEARCH("bang",F4)),"Bangalore",IF(ISNUMBER(SEARCH("beng",F4)),"Bangalore",IF(ISNUMBER(SEARCH("mumbai",F4)),"Mumbai",IF(ISNUMBER(SEARCH("delhi",F4)),"Delhi-NCR",IF(ISNUMBER(SEARCH("gurgaon",F4)),"Delhi-NCR",IF(ISNUMBER(SEARCH("gurugram",F4)),"Delhi-NCR",IF(ISNUMBER(SEARCH("noida",F4)),"Delhi-NCR",IF(ISNUMBER(SEARCH("faridabad",F4)),"Delhi-NCR",IF(ISNUMBER(SEARCH("chennai",F4)),"Chennai",IF(ISNUMBER(SEARCH("hyderabad",F4)),"Hyderabad",IF(ISNUMBER(SEARCH("pune",F4)),"Pune",IF(ISNUMBER(SEARCH("kolkata",F4)),"Kolkata",IF(ISNUMBER(SEARCH("ahmedabad",F4)),"Ahmedabad",IF(ISNUMBER(SEARCH("jaipur",F4)),"Jaipur",IF(ISNUMBER(SEARCH("coimbatore",F4)),"Coimbatore",IF(ISNUMBER(SEARCH("kochi",F4)),"Kerala Cities",IF(ISNUMBER(SEARCH("cochin",F4)),"Kerala Cities",IF(ISNUMBER(SEARCH("francisco",F4)),"USA",IF(ISNUMBER(SEARCH("new york",F4)),"USA",IF(ISNUMBER(SEARCH("california",F4)),"USA",IF(ISNUMBER(SEARCH("palo alto",F4)),"USA",IF(ISNUMBER(SEARCH("santa",F4)),"USA",IF(ISNUMBER(SEARCH("singapore",F4)),"Singapore",IF(ISNUMBER(SEARCH("london",F4)),"London/UK",IF(F4="","Unknown","Other Cities"))))))))))))))))))))))))) -> Bangalore
A5: 4 | B5: 43832 | C5: Wealthbucket | D5: FinTech | E5: Online Investment | F5: New Delhi | G5: Vinod Khatumal | H5: =IFERROR(TRIM(LEFT(G5,FIND(",",G5)-1)),TRIM(G5)) -> Vinod Khatumal | I5: =IF(TRIM(G5)="",0,LEN(G5)-LEN(SUBSTITUTE(G5,",",""))+1) -> 1 | J5: =IF(Table1[[#This Row],[Investor Count]]>1,"Yes","No") -> No | K5: Pre-series A | L5: 3000000 | M5: =YEAR(B5) -> 2020 | N5: =TEXT(B5,"mmmm") -> January | O5: 28.79115 | P5: =IF(ISBLANK(K5),"Unknown",IF(OR(ISNUMBER(SEARCH("seed",K5)),ISNUMBER(SEARCH("Seed",K5))),"Seed",IF(ISNUMBER(SEARCH("Series A",K5)),"Series A",IF(ISNUMBER(SEARCH("Series B",K5)),"Series B",IF(ISNUMBER(SEARCH("Series C",K5)),"Series C",IF(ISNUMBER(SEARCH("Series D",K5)),"Series D",IF(ISNUMBER(SEARCH("Private Equity",K5)),"Private Equity","Other"))))))) -> Series A | Q5: =IF(IFERROR(SEARCH("ecom",D5),0)+IFERROR(SEARCH("commerce",D5),0)+IFERROR(SEARCH("retail",D5),0)>0,"E-Commerce", IF(IFERROR(SEARCH("fintech",D5),0)+IFERROR(SEARCH("finance",D5),0)+IFERROR(SEARCH("financial",D5),0)+IFERROR(SEARCH("lending",D5),0)+IFERROR(SEARCH("payment",D5),0)+IFERROR(SEARCH("banking",D5),0)+IFERROR(SEARCH("insurance",D5),0)>0,"FinTech", IF(IFERROR(SEARCH("tech",D5),0)+IFERROR(SEARCH("software",D5),0)+IFERROR(SEARCH("saas",D5),0)+IFERROR(SEARCH("ai",D5),0)+IFERROR(SEARCH("iot",D5),0)+IFERROR(SEARCH("cloud",D5),0)+IFERROR(SEARCH("data",D5),0)+IFERROR(SEARCH("analytics",D5),0)>0,"Technology", IF(IFERROR(SEARCH("food",D5),0)+IFERROR(SEARCH("restaurant",D5),0)+IFERROR(SEARCH("hospitality",D5),0)+IFERROR(SEARCH("beverage",D5),0)+IFERROR(SEARCH("delivery",D5),0)>0,"Food & Beverage", IF(IFERROR(SEARCH("health",D5),0)+IFERROR(SEARCH("medical",D5),0)+IFERROR(SEARCH("pharma",D5),0)+IFERROR(SEARCH("wellness",D5),0)+IFERROR(SEARCH("fitness",D5),0)>0,"Healthcare", IF(IFERROR(SEARCH("edu",D5),0)+IFERROR(SEARCH("learning",D5),0)+IFERROR(SEARCH("school",D5),0)+IFERROR(SEARCH("e-tech",D5),0)>0,"Education", IF(IFERROR(SEARCH("logistics",D5),0)+IFERROR(SEARCH("transport",D5),0)+IFERROR(SEARCH("delivery",D5),0)+IFERROR(SEARCH("mobility",D5),0)+IFERROR(SEARCH("automobile",D5),0)>0,"Logistics & Transport", IF(IFERROR(SEARCH("travel",D5),0)+IFERROR(SEARCH("hotel",D5),0)+IFERROR(SEARCH("booking",D5),0)+IFERROR(SEARCH("tourism",D5),0)>0,"Travel & Hospitality", IF(IFERROR(SEARCH("fashion",D5),0)+IFERROR(SEARCH("apparel",D5),0)+IFERROR(SEARCH("clothing",D5),0)+IFERROR(SEARCH("jewelry",D5),0)+IFERROR(SEARCH("beauty",D5),0)>0,"Fashion & Lifestyle", IF(IFERROR(SEARCH("media",D5),0)+IFERROR(SEARCH("entertainment",D5),0)+IFERROR(SEARCH("video",D5),0)+IFERROR(SEARCH("gaming",D5),0)+IFERROR(SEARCH("music",D5),0)+IFERROR(SEARCH("social",D5),0)>0,"Media & Entertainment", IF(IFERROR(SEARCH("agri",D5),0)+IFERROR(SEARCH("farm",D5),0)+IFERROR(SEARCH("agtech",D5),0)>0,"Agriculture", IF(IFERROR(SEARCH("real estate",D5),0)+IFERROR(SEARCH("property",D5),0)+IFERROR(SEARCH("housing",D5),0)>0,"Real Estate", IF(IFERROR(SEARCH("energy",D5),0)+IFERROR(SEARCH("solar",D5),0)+IFERROR(SEARCH("clean tech",D5),0)+IFERROR(SEARCH("waste",D5),0)>0,"Energy & Environment", IF(IFERROR(SEARCH("hr",D5),0)+IFERROR(SEARCH("recruit",D5),0)+IFERROR(SEARCH("hiring",D5),0)+IFERROR(SEARCH("job",D5),0)>0,"HR & Recruitment", "Others")))))))))))))) -> FinTech | R5: =IF(ISNUMBER(SEARCH("bang",F5)),"Bangalore",IF(ISNUMBER(SEARCH("beng",F5)),"Bangalore",IF(ISNUMBER(SEARCH("mumbai",F5)),"Mumbai",IF(ISNUMBER(SEARCH("delhi",F5)),"Delhi-NCR",IF(ISNUMBER(SEARCH("gurgaon",F5)),"Delhi-NCR",IF(ISNUMBER(SEARCH("gurugram",F5)),"Delhi-NCR",IF(ISNUMBER(SEARCH("noida",F5)),"Delhi-NCR",IF(ISNUMBER(SEARCH("faridabad",F5)),"Delhi-NCR",IF(ISNUMBER(SEARCH("chennai",F5)),"Chennai",IF(ISNUMBER(SEARCH("hyderabad",F5)),"Hyderabad",IF(ISNUMBER(SEARCH("pune",F5)),"Pune",IF(ISNUMBER(SEARCH("kolkata",F5)),"Kolkata",IF(ISNUMBER(SEARCH("ahmedabad",F5)),"Ahmedabad",IF(ISNUMBER(SEARCH("jaipur",F5)),"Jaipur",IF(ISNUMBER(SEARCH("coimbatore",F5)),"Coimbatore",IF(ISNUMBER(SEARCH("kochi",F5)),"Kerala Cities",IF(ISNUMBER(SEARCH("cochin",F5)),"Kerala Cities",IF(ISNUMBER(SEARCH("francisco",F5)),"USA",IF(ISNUMBER(SEARCH("new york",F5)),"USA",IF(ISNUMBER(SEARCH("california",F5)),"USA",IF(ISNUMBER(SEARCH("palo alto",F5)),"USA",IF(ISNUMBER(SEARCH("santa",F5)),"USA",IF(ISNUMBER(SEARCH("singapore",F5)),"Singapore",IF(ISNUMBER(SEARCH("london",F5)),"London/UK",IF(F5="","Unknown","Other Cities"))))))))))))))))))))))))) -> Delhi-NCR
A6: 5 | B6: 43832 | C6: Fashor | D6: Fashion & Apparel | E6: Embroiled Clothes For Women | F6: Mumbai | G6: Sprout Venture Partners | H6: =IFERROR(TRIM(LEFT(G6,FIND(",",G6)-1)),TRIM(G6)) -> Sprout Venture Partners | I6: =IF(TRIM(G6)="",0,LEN(G6)-LEN(SUBSTITUTE(G6,",",""))+1) -> 1 | J6: =IF(Table1[[#This Row],[Investor Count]]>1,"Yes","No") -> No | K6: Seed Round | L6: 1800000 | M6: =YEAR(B6) -> 2020 | N6: =TEXT(B6,"mmmm") -> January | O6: 17.27469 | P6: =IF(ISBLANK(K6),"Unknown",IF(OR(ISNUMBER(SEARCH("seed",K6)),ISNUMBER(SEARCH("Seed",K6))),"Seed",IF(ISNUMBER(SEARCH("Series A",K6)),"Series A",IF(ISNUMBER(SEARCH("Series B",K6)),"Series B",IF(ISNUMBER(SEARCH("Series C",K6)),"Series C",IF(ISNUMBER(SEARCH("Series D",K6)),"Series D",IF(ISNUMBER(SEARCH("Private Equity",K6)),"Private Equity","Other"))))))) -> Seed | Q6: =IF(IFERROR(SEARCH("ecom",D6),0)+IFERROR(SEARCH("commerce",D6),0)+IFERROR(SEARCH("retail",D6),0)>0,"E-Commerce", IF(IFERROR(SEARCH("fintech",D6),0)+IFERROR(SEARCH("finance",D6),0)+IFERROR(SEARCH("financial",D6),0)+IFERROR(SEARCH("lending",D6),0)+IFERROR(SEARCH("payment",D6),0)+IFERROR(SEARCH("banking",D6),0)+IFERROR(SEARCH("insurance",D6),0)>0,"FinTech", IF(IFERROR(SEARCH("tech",D6),0)+IFERROR(SEARCH("software",D6),0)+IFERROR(SEARCH("saas",D6),0)+IFERROR(SEARCH("ai",D6),0)+IFERROR(SEARCH("iot",D6),0)+IFERROR(SEARCH("cloud",D6),0)+IFERROR(SEARCH("data",D6),0)+IFERROR(SEARCH("analytics",D6),0)>0,"Technology", IF(IFERROR(SEARCH("food",D6),0)+IFERROR(SEARCH("restaurant",D6),0)+IFERROR(SEARCH("hospitality",D6),0)+IFERROR(SEARCH("beverage",D6),0)+IFERROR(SEARCH("delivery",D6),0)>0,"Food & Beverage", IF(IFERROR(SEARCH("health",D6),0)+IFERROR(SEARCH("medical",D6),0)+IFERROR(SEARCH("pharma",D6),0)+IFERROR(SEARCH("wellness",D6),0)+IFERROR(SEARCH("fitness",D6),0)>0,"Healthcare", IF(IFERROR(SEARCH("edu",D6),0)+IFERROR(SEARCH("learning",D6),0)+IFERROR(SEARCH("school",D6),0)+IFERROR(SEARCH("e-tech",D6),0)>0,"Education", IF(IFERROR(SEARCH("logistics",D6),0)+IFERROR(SEARCH("transport",D6),0)+IFERROR(SEARCH("delivery",D6),0)+IFERROR(SEARCH("mobility",D6),0)+IFERROR(SEARCH("automobile",D6),0)>0,"Logistics & Transport", IF(IFERROR(SEARCH("travel",D6),0)+IFERROR(SEARCH("hotel",D6),0)+IFERROR(SEARCH("booking",D6),0)+IFERROR(SEARCH("tourism",D6),0)>0,"Travel & Hospitality", IF(IFERROR(SEARCH("fashion",D6),0)+IFERROR(SEARCH("apparel",D6),0)+IFERROR(SEARCH("clothing",D6),0)+IFERROR(SEARCH("jewelry",D6),0)+IFERROR(SEARCH("beauty",D6),0)>0,"Fashion & Lifestyle", IF(IFERROR(SEARCH("media",D6),0)+IFERROR(SEARCH("entertainment",D6),0)+IFERROR(SEARCH("video",D6),0)+IFERROR(SEARCH("gaming",D6),0)+IFERROR(SEARCH("music",D6),0)+IFERROR(SEARCH("social",D6),0)>0,"Media & Entertainment", IF(IFERROR(SEARCH("agri",D6),0)+IFERROR(SEARCH("farm",D6),0)+IFERROR(SEARCH("agtech",D6),0)>0,"Agriculture", IF(IFERROR(SEARCH("real estate",D6),0)+IFERROR(SEARCH("property",D6),0)+IFERROR(SEARCH("housing",D6),0)>0,"Real Estate", IF(IFERROR(SEARCH("energy",D6),0)+IFERROR(SEARCH("solar",D6),0)+IFERROR(SEARCH("clean tech",D6),0)+IFERROR(SEARCH("waste",D6),0)>0,"Energy & Environment", IF(IFERROR(SEARCH("hr",D6),0)+IFERROR(SEARCH("recruit",D6),0)+IFERROR(SEARCH("hiring",D6),0)+IFERROR(SEARCH("job",D6),0)>0,"HR & Recruitment", "Others")))))))))))))) -> Fashion & Lifestyle | R6: =IF(ISNUMBER(SEARCH("bang",F6)),"Bangalore",IF(ISNUMBER(SEARCH("beng",F6)),"Bangalore",IF(ISNUMBER(SEARCH("mumbai",F6)),"Mumbai",IF(ISNUMBER(SEARCH("delhi",F6)),"Delhi-NCR",IF(ISNUMBER(SEARCH("gurgaon",F6)),"Delhi-NCR",IF(ISNUMBER(SEARCH("gurugram",F6)),"Delhi-NCR",IF(ISNUMBER(SEARCH("noida",F6)),"Delhi-NCR",IF(ISNUMBER(SEARCH("faridabad",F6)),"Delhi-NCR",IF(ISNUMBER(SEARCH("chennai",F6)),"Chennai",IF(ISNUMBER(SEARCH("hyderabad",F6)),"Hyderabad",IF(ISNUMBER(SEARCH("pune",F6)),"Pune",IF(ISNUMBER(SEARCH("kolkata",F6)),"Kolkata",IF(ISNUMBER(SEARCH("ahmedabad",F6)),"Ahmedabad",IF(ISNUMBER(SEARCH("jaipur",F6)),"Jaipur",IF(ISNUMBER(SEARCH("coimbatore",F6)),"Coimbatore",IF(ISNUMBER(SEARCH("kochi",F6)),"Kerala Cities",IF(ISNUMBER(SEARCH("cochin",F6)),"Kerala Cities",IF(ISNUMBER(SEARCH("francisco",F6)),"USA",IF(ISNUMBER(SEARCH("new york",F6)),"USA",IF(ISNUMBER(SEARCH("california",F6)),"USA",IF(ISNUMBER(SEARCH("palo alto",F6)),"USA",IF(ISNUMBER(SEARCH("santa",F6)),"USA",IF(ISNUMBER(SEARCH("singapore",F6)),"Singapore",IF(ISNUMBER(SEARCH("london",F6)),"London/UK",IF(F6="","Unknown","Other Cities"))))))))))))))))))))))))) -> Mumbai
A7: 6 | B7: 43843 | C7: Po | D7: Logistics | E7: Open-market, freight management platform | F7: Chennai | G7: Chiratae Ventures | H7: =IFERROR(TRIM(LEFT(G7,FIND(",",G7)-1)),TRIM(G7)) -> Chiratae Ventures | I7: =IF(TRIM(G7)="",0,LEN(G7)-LEN(SUBSTITUTE(G7,",",""))+1) -> 1 | J7: =IF(Table1[[#This Row],[Investor Count]]>1,"Yes","No") -> No | K7: Series A | L7: 9000000 | M7: =YEAR(B7) -> 2020 | N7: =TEXT(B7,"mmmm") -> January | O7: 86.37345 | P7: =IF(ISBLANK(K7),"Unknown",IF(OR(ISNUMBER(SEARCH("seed",K7)),ISNUMBER(SEARCH("Seed",K7))),"Seed",IF(ISNUMBER(SEARCH("Series A",K7)),"Series A",IF(ISNUMBER(SEARCH("Series B",K7)),"Series B",IF(ISNUMBER(SEARCH("Series C",K7)),"Series C",IF(ISNUMBER(SEARCH("Series D",K7)),"Series D",IF(ISNUMBER(SEARCH("Private Equity",K7)),"Private Equity","Other"))))))) -> Series A | Q7: =IF(IFERROR(SEARCH("ecom",D7),0)+IFERROR(SEARCH("commerce",D7),0)+IFERROR(SEARCH("retail",D7),0)>0,"E-Commerce", IF(IFERROR(SEARCH("fintech",D7),0)+IFERROR(SEARCH("finance",D7),0)+IFERROR(SEARCH("financial",D7),0)+IFERROR(SEARCH("lending",D7),0)+IFERROR(SEARCH("payment",D7),0)+IFERROR(SEARCH("banking",D7),0)+IFERROR(SEARCH("insurance",D7),0)>0,"FinTech", IF(IFERROR(SEARCH("tech",D7),0)+IFERROR(SEARCH("software",D7),0)+IFERROR(SEARCH("saas",D7),0)+IFERROR(SEARCH("ai",D7),0)+IFERROR(SEARCH("iot",D7),0)+IFERROR(SEARCH("cloud",D7),0)+IFERROR(SEARCH("data",D7),0)+IFERROR(SEARCH("analytics",D7),0)>0,"Technology", IF(IFERROR(SEARCH("food",D7),0)+IFERROR(SEARCH("restaurant",D7),0)+IFERROR(SEARCH("hospitality",D7),0)+IFERROR(SEARCH("beverage",D7),0)+IFERROR(SEARCH("delivery",D7),0)>0,"Food & Beverage", IF(IFERROR(SEARCH("health",D7),0)+IFERROR(SEARCH("medical",D7),0)+IFERROR(SEARCH("pharma",D7),0)+IFERROR(SEARCH("wellness",D7),0)+IFERROR(SEARCH("fitness",D7),0)>0,"Healthcare", IF(IFERROR(SEARCH("edu",D7),0)+IFERROR(SEARCH("learning",D7),0)+IFERROR(SEARCH("school",D7),0)+IFERROR(SEARCH("e-tech",D7),0)>0,"Education", IF(IFERROR(SEARCH("logistics",D7),0)+IFERROR(SEARCH("transport",D7),0)+IFERROR(SEARCH("delivery",D7),0)+IFERROR(SEARCH("mobility",D7),0)+IFERROR(SEARCH("automobile",D7),0)>0,"Logistics & Transport", IF(IFERROR(SEARCH("travel",D7),0)+IFERROR(SEARCH("hotel",D7),0)+IFERROR(SEARCH("booking",D7),0)+IFERROR(SEARCH("tourism",D7),0)>0,"Travel & Hospitality", IF(IFERROR(SEARCH("fashion",D7),0)+IFERROR(SEARCH("apparel",D7),0)+IFERROR(SEARCH("clothing",D7),0)+IFERROR(SEARCH("jewelry",D7),0)+IFERROR(SEARCH("beauty",D7),0)>0,"Fashion & Lifestyle", IF(IFERROR(SEARCH("media",D7),0)+IFERROR(SEARCH("entertainment",D7),0)+IFERROR(SEARCH("video",D7),0)+IFERROR(SEARCH("gaming",D7),0)+IFERROR(SEARCH("music",D7),0)+IFERROR(SEARCH("social",D7),0)>0,"Media & Entertainment", IF(IFERROR(SEARCH("agri",D7),0)+IFERROR(SEARCH("farm",D7),0)+IFERROR(SEARCH("agtech",D7),0)>0,"Agriculture", IF(IFERROR(SEARCH("real estate",D7),0)+IFERROR(SEARCH("property",D7),0)+IFERROR(SEARCH("housing",D7),0)>0,"Real Estate", IF(IFERROR(SEARCH("energy",D7),0)+IFERROR(SEARCH("solar",D7),0)+IFERROR(SEARCH("clean tech",D7),0)+IFERROR(SEARCH("waste",D7),0)>0,"Energy & Environment", IF(IFERROR(SEARCH("hr",D7),0)+IFERROR(SEARCH("recruit",D7),0)+IFERROR(SEARCH("hiring",D7),0)+IFERROR(SEARCH("job",D7),0)>0,"HR & Recruitment", "Others")))))))))))))) -> Logistics & Transport | R7: =IF(ISNUMBER(SEARCH("bang",F7)),"Bangalore",IF(ISNUMBER(SEARCH("beng",F7)),"Bangalore",IF(ISNUMBER(SEARCH("mumbai",F7)),"Mumbai",IF(ISNUMBER(SEARCH("delhi",F7)),"Delhi-NCR",IF(ISNUMBER(SEARCH("gurgaon",F7)),"Delhi-NCR",IF(ISNUMBER(SEARCH("gurugram",F7)),"Delhi-NCR",IF(ISNUMBER(SEARCH("noida",F7)),"Delhi-NCR",IF(ISNUMBER(SEARCH("faridabad",F7)),"Delhi-NCR",IF(ISNUMBER(SEARCH("chennai",F7)),"Chennai",IF(ISNUMBER(SEARCH("hyderabad",F7)),"Hyderabad",IF(ISNUMBER(SEARCH("pune",F7)),"Pune",IF(ISNUMBER(SEARCH("kolkata",F7)),"Kolkata",IF(ISNUMBER(SEARCH("ahmedabad",F7)),"Ahmedabad",IF(ISNUMBER(SEARCH("jaipur",F7)),"Jaipur",IF(ISNUMBER(SEARCH("coimbatore",F7)),"Coimbatore",IF(ISNUMBER(SEARCH("kochi",F7)),"Kerala Cities",IF(ISNUMBER(SEARCH("cochin",F7)),"Kerala Cities",IF(ISNUMBER(SEARCH("francisco",F7)),"USA",IF(ISNUMBER(SEARCH("new york",F7)),"USA",IF(ISNUMBER(SEARCH("california",F7)),"USA",IF(ISNUMBER(SEARCH("palo alto",F7)),"USA",IF(ISNUMBER(SEARCH("santa",F7)),"USA",IF(ISNUMBER(SEARCH("singapore",F7)),"Singapore",IF(ISNUMBER(SEARCH("london",F7)),"London/UK",IF(F7="","Unknown","Other Cities"))))))))))))))))))))))))) -> Chennai
A8: 7 | B8: 43840 | C8: Zomato | D8: Hospitality | E8: Online Food Delivery Platform | F8: Gurgaon | G8: Ant Financial | H8: =IFERROR(TRIM(LEFT(G8,FIND(",",G8)-1)),TRIM(G8)) -> Ant Financial | I8: =IF(TRIM(G8)="",0,LEN(G8)-LEN(SUBSTITUTE(G8,",",""))+1) -> 1 | J8: =IF(Table1[[#This Row],[Investor Count]]>1,"Yes","No") -> No | K8: Private Equity Round | L8: 150000000 | M8: =YEAR(B8) -> 2020 | N8: =TEXT(B8,"mmmm") -> January | O8: 1439.5575 | P8: =IF(ISBLANK(K8),"Unknown",IF(OR(ISNUMBER(SEARCH("seed",K8)),ISNUMBER(SEARCH("Seed",K8))),"Seed",IF(ISNUMBER(SEARCH("Series A",K8)),"Series A",IF(ISNUMBER(SEARCH("Series B",K8)),"Series B",IF(ISNUMBER(SEARCH("Series C",K8)),"Series C",IF(ISNUMBER(SEARCH("Series D",K8)),"Series D",IF(ISNUMBER(SEARCH("Private Equity",K8)),"Private Equity","Other"))))))) -> Private Equity | Q8: =IF(IFERROR(SEARCH("ecom",D8),0)+IFERROR(SEARCH("commerce",D8),0)+IFERROR(SEARCH("retail",D8),0)>0,"E-Commerce", IF(IFERROR(SEARCH("fintech",D8),0)+IFERROR(SEARCH("finance",D8),0)+IFERROR(SEARCH("financial",D8),0)+IFERROR(SEARCH("lending",D8),0)+IFERROR(SEARCH("payment",D8),0)+IFERROR(SEARCH("banking",D8),0)+IFERROR(SEARCH("insurance",D8),0)>0,"FinTech", IF(IFERROR(SEARCH("tech",D8),0)+IFERROR(SEARCH("software",D8),0)+IFERROR(SEARCH("saas",D8),0)+IFERROR(SEARCH("ai",D8),0)+IFERROR(SEARCH("iot",D8),0)+IFERROR(SEARCH("cloud",D8),0)+IFERROR(SEARCH("data",D8),0)+IFERROR(SEARCH("analytics",D8),0)>0,"Technology", IF(IFERROR(SEARCH("food",D8),0)+IFERROR(SEARCH("restaurant",D8),0)+IFERROR(SEARCH("hospitality",D8),0)+IFERROR(SEARCH("beverage",D8),0)+IFERROR(SEARCH("delivery",D8),0)>0,"Food & Beverage", IF(IFERROR(SEARCH("health",D8),0)+IFERROR(SEARCH("medical",D8),0)+IFERROR(SEARCH("pharma",D8),0)+IFERROR(SEARCH("wellness",D8),0)+IFERROR(SEARCH("fitness",D8),0)>0,"Healthcare", IF(IFERROR(SEARCH("edu",D8),0)+IFERROR(SEARCH("learning",D8),0)+IFERROR(SEARCH("school",D8),0)+IFERROR(SEARCH("e-tech",D8),0)>0,"Education", IF(IFERROR(SEARCH("logistics",D8),0)+IFERROR(SEARCH("transport",D8),0)+IFERROR(SEARCH("delivery",D8),0)+IFERROR(SEARCH("mobility",D8),0)+IFERROR(SEARCH("automobile",D8),0)>0,"Logistics & Transport", IF(IFERROR(SEARCH("travel",D8),0)+IFERROR(SEARCH("hotel",D8),0)+IFERROR(SEARCH("booking",D8),0)+IFERROR(SEARCH("tourism",D8),0)>0,"Travel & Hospitality", IF(IFERROR(SEARCH("fashion",D8),0)+IFERROR(SEARCH("apparel",D8),0)+IFERROR(SEARCH("clothing",D8),0)+IFERROR(SEARCH("jewelry",D8),0)+IFERROR(SEARCH("beauty",D8),0)>0,"Fashion & Lifestyle", IF(IFERROR(SEARCH("media",D8),0)+IFERROR(SEARCH("entertainment",D8),0)+IFERROR(SEARCH("video",D8),0)+IFERROR(SEARCH("gaming",D8),0)+IFERROR(SEARCH("music",D8),0)+IFERROR(SEARCH("social",D8),0)>0,"Media & Entertainment", IF(IFERROR(SEARCH("agri",D8),0)+IFERROR(SEARCH("farm",D8),0)+IFERROR(SEARCH("agtech",D8),0)>0,"Agriculture", IF(IFERROR(SEARCH("real estate",D8),0)+IFERROR(SEARCH("property",D8),0)+IFERROR(SEARCH("housing",D8),0)>0,"Real Estate", IF(IFERROR(SEARCH("energy",D8),0)+IFERROR(SEARCH("solar",D8),0)+IFERROR(SEARCH("clean tech",D8),0)+IFERROR(SEARCH("waste",D8),0)>0,"Energy & Environment", IF(IFERROR(SEARCH("hr",D8),0)+IFERROR(SEARCH("recruit",D8),0)+IFERROR(SEARCH("hiring",D8),0)+IFERROR(SEARCH("job",D8),0)>0,"HR & Recruitment", "Others")))))))))))))) -> Food & Beverage | R8: =IF(ISNUMBER(SEARCH("bang",F8)),"Bangalore",IF(ISNUMBER(SEARCH("beng",F8)),"Bangalore",IF(ISNUMBER(SEARCH("mumbai",F8)),"Mumbai",IF(ISNUMBER(SEARCH("delhi",F8)),"Delhi-NCR",IF(ISNUMBER(SEARCH("gurgaon",F8)),"Delhi-NCR",IF(ISNUMBER(SEARCH("gurugram",F8)),"Delhi-NCR",IF(ISNUMBER(SEARCH("noida",F8)),"Delhi-NCR",IF(ISNUMBER(SEARCH("faridabad",F8)),"Delhi-NCR",IF(ISNUMBER(SEARCH("chennai",F8)),"Chennai",IF(ISNUMBER(SEARCH("hyderabad",F8)),"Hyderabad",IF(ISNUMBER(SEARCH("pune",F8)),"Pune",IF(ISNUMBER(SEARCH("kolkata",F8)),"Kolkata",IF(ISNUMBER(SEARCH("ahmedabad",F8)),"Ahmedabad",IF(ISNUMBER(SEARCH("jaipur",F8)),"Jaipur",IF(ISNUMBER(SEARCH("coimbatore",F8)),"Coimbatore",IF(ISNUMBER(SEARCH("kochi",F8)),"Kerala Cities",IF(ISNUMBER(SEARCH("cochin",F8)),"Kerala Cities",IF(ISNUMBER(SEARCH("francisco",F8)),"USA",IF(ISNUMBER(SEARCH("new york",F8)),"USA",IF(ISNUMBER(SEARCH("california",F8)),"USA",IF(ISNUMBER(SEARCH("palo alto",F8)),"USA",IF(ISNUMBER(SEARCH("santa",F8)),"USA",IF(ISNUMBER(SEARCH("singapore",F8)),"Singapore",IF(ISNUMBER(SEARCH("london",F8)),"London/UK",IF(F8="","Unknown","Other Cities"))))))))))))))))))))))))) -> Delhi-NCR
A9: 8 | B9: 43811 | C9: Ecozen | D9: Technology | E9: Agritech | F9: Pune | G9: Sathguru Catalyzer Advisors | H9: =IFERROR(TRIM(LEFT(G9,FIND(",",G9)-1)),TRIM(G9)) -> Sathguru Catalyzer Advisors | I9: =IF(TRIM(G9)="",0,LEN(G9)-LEN(SUBSTITUTE(G9,",",""))+1) -> 1 | J9: =IF(Table1[[#This Row],[Investor Count]]>1,"Yes","No") -> No | K9: Series A | L9: 6000000 | M9: =YEAR(B9) -> 2019 | N9: =TEXT(B9,"mmmm") -> December | O9: 57.5823 | P9: =IF(ISBLANK(K9),"Unknown",IF(OR(ISNUMBER(SEARCH("seed",K9)),ISNUMBER(SEARCH("Seed",K9))),"Seed",IF(ISNUMBER(SEARCH("Series A",K9)),"Series A",IF(ISNUMBER(SEARCH("Series B",K9)),"Series B",IF(ISNUMBER(SEARCH("Series C",K9)),"Series C",IF(ISNUMBER(SEARCH("Series D",K9)),"Series D",IF(ISNUMBER(SEARCH("Private Equity",K9)),"Private Equity","Other"))))))) -> Series A | Q9: =IF(IFERROR(SEARCH("ecom",D9),0)+IFERROR(SEARCH("commerce",D9),0)+IFERROR(SEARCH("retail",D9),0)>0,"E-Commerce", IF(IFERROR(SEARCH("fintech",D9),0)+IFERROR(SEARCH("finance",D9),0)+IFERROR(SEARCH("financial",D9),0)+IFERROR(SEARCH("lending",D9),0)+IFERROR(SEARCH("payment",D9),0)+IFERROR(SEARCH("banking",D9),0)+IFERROR(SEARCH("insurance",D9),0)>0,"FinTech", IF(IFERROR(SEARCH("tech",D9),0)+IFERROR(SEARCH("software",D9),0)+IFERROR(SEARCH("saas",D9),0)+IFERROR(SEARCH("ai",D9),0)+IFERROR(SEARCH("iot",D9),0)+IFERROR(SEARCH("cloud",D9),0)+IFERROR(SEARCH("data",D9),0)+IFERROR(SEARCH("analytics",D9),0)>0,"Technology", IF(IFERROR(SEARCH("food",D9),0)+IFERROR(SEARCH("restaurant",D9),0)+IFERROR(SEARCH("hospitality",D9),0)+IFERROR(SEARCH("beverage",D9),0)+IFERROR(SEARCH("delivery",D9),0)>0,"Food & Beverage", IF(IFERROR(SEARCH("health",D9),0)+IFERROR(SEARCH("medical",D9),0)+IFERROR(SEARCH("pharma",D9),0)+IFERROR(SEARCH("wellness",D9),0)+IFERROR(SEARCH("fitness",D9),0)>0,"Healthcare", IF(IFERROR(SEARCH("edu",D9),0)+IFERROR(SEARCH("learning",D9),0)+IFERROR(SEARCH("school",D9),0)+IFERROR(SEARCH("e-tech",D9),0)>0,"Education", IF(IFERROR(SEARCH("logistics",D9),0)+IFERROR(SEARCH("transport",D9),0)+IFERROR(SEARCH("delivery",D9),0)+IFERROR(SEARCH("mobility",D9),0)+IFERROR(SEARCH("automobile",D9),0)>0,"Logistics & Transport", IF(IFERROR(SEARCH("travel",D9),0)+IFERROR(SEARCH("hotel",D9),0)+IFERROR(SEARCH("booking",D9),0)+IFERROR(SEARCH("tourism",D9),0)>0,"Travel & Hospitality", IF(IFERROR(SEARCH("fashion",D9),0)+IFERROR(SEARCH("apparel",D9),0)+IFERROR(SEARCH("clothing",D9),0)+IFERROR(SEARCH("jewelry",D9),0)+IFERROR(SEARCH("beauty",D9),0)>0,"Fashion & Lifestyle", IF(IFERROR(SEARCH("media",D9),0)+IFERROR(SEARCH("entertainment",D9),0)+IFERROR(SEARCH("video",D9),0)+IFERROR(SEARCH("gaming",D9),0)+IFERROR(SEARCH("music",D9),0)+IFERROR(SEARCH("social",D9),0)>0,"Media & Entertainment", IF(IFERROR(SEARCH("agri",D9),0)+IFERROR(SEARCH("farm",D9),0)+IFERROR(SEARCH("agtech",D9),0)>0,"Agriculture", IF(IFERROR(SEARCH("real estate",D9),0)+IFERROR(SEARCH("property",D9),0)+IFERROR(SEARCH("housing",D9),0)>0,"Real Estate", IF(IFERROR(SEARCH("energy",D9),0)+IFERROR(SEARCH("solar",D9),0)+IFERROR(SEARCH("clean tech",D9),0)+IFERROR(SEARCH("waste",D9),0)>0,"Energy & Environment", IF(IFERROR(SEARCH("hr",D9),0)+IFERROR(SEARCH("recruit",D9),0)+IFERROR(SEARCH("hiring",D9),0)+IFERROR(SEARCH("job",D9),0)>0,"HR & Recruitment", "Others")))))))))))))) -> Technology | R9: =IF(ISNUMBER(SEARCH("bang",F9)),"Bangalore",IF(ISNUMBER(SEARCH("beng",F9)),"Bangalore",IF(ISNUMBER(SEARCH("mumbai",F9)),"Mumbai",IF(ISNUMBER(SEARCH("delhi",F9)),"Delhi-NCR",IF(ISNUMBER(SEARCH("gurgaon",F9)),"Delhi-NCR",IF(ISNUMBER(SEARCH("gurugram",F9)),"Delhi-NCR",IF(ISNUMBER(SEARCH("noida",F9)),"Delhi-NCR",IF(ISNUMBER(SEARCH("faridabad",F9)),"Delhi-NCR",IF(ISNUMBER(SEARCH("chennai",F9)),"Chennai",IF(ISNUMBER(SEARCH("hyderabad",F9)),"Hyderabad",IF(ISNUMBER(SEARCH("pune",F9)),"Pune",IF(ISNUMBER(SEARCH("kolkata",F9)),"Kolkata",IF(ISNUMBER(SEARCH("ahmedabad",F9)),"Ahmedabad",IF(ISNUMBER(SEARCH("jaipur",F9)),"Jaipur",IF(ISNUMBER(SEARCH("coimbatore",F9)),"Coimbatore",IF(ISNUMBER(SEARCH("kochi",F9)),"Kerala Cities",IF(ISNUMBER(SEARCH("cochin",F9)),"Kerala Cities",IF(ISNUMBER(SEARCH("francisco",F9)),"USA",IF(ISNUMBER(SEARCH("new york",F9)),"USA",IF(ISNUMBER(SEARCH("california",F9)),"USA",IF(ISNUMBER(SEARCH("palo alto",F9)),"USA",IF(ISNUMBER(SEARCH("santa",F9)),"USA",IF(ISNUMBER(SEARCH("singapore",F9)),"Singapore",IF(ISNUMBER(SEARCH("london",F9)),"London/UK",IF(F9="","Unknown","Other Cities"))))))))))))))))))))))))) -> Pune
A10: 9 | B10: 43805 | C10: CarDekho | D10: Ecommerce | E10: Automobile | F10: Gurgaon | G10: Ping An Global Voyager Fund | H10: =IFERROR(TRIM(LEFT(G10,FIND(",",G10)-1)),TRIM(G10)) -> Ping An Global Voyager Fund | I10: =IF(TRIM(G10)="",0,LEN(G10)-LEN(SUBSTITUTE(G10,",",""))+1) -> 1 | J10: =IF(Table1[[#This Row],[Investor Count]]>1,"Yes","No") -> No | K10: Series D | L10: 70000000 | M10: =YEAR(B10) -> 2019 | N10: =TEXT(B10,"mmmm") -> December | O10: 671.7935 | P10: =IF(ISBLANK(K10),"Unknown",IF(OR(ISNUMBER(SEARCH("seed",K10)),ISNUMBER(SEARCH("Seed",K10))),"Seed",IF(ISNUMBER(SEARCH("Series A",K10)),"Series A",IF(ISNUMBER(SEARCH("Series B",K10)),"Series B",IF(ISNUMBER(SEARCH("Series C",K10)),"Series C",IF(ISNUMBER(SEARCH("Series D",K10)),"Series D",IF(ISNUMBER(SEARCH("Private Equity",K10)),"Private Equity","Other"))))))) -> Series D | Q10: =IF(IFERROR(SEARCH("ecom",D10),0)+IFERROR(SEARCH("commerce",D10),0)+IFERROR(SEARCH("retail",D10),0)>0,"E-Commerce", IF(IFERROR(SEARCH("fintech",D10),0)+IFERROR(SEARCH("finance",D10),0)+IFERROR(SEARCH("financial",D10),0)+IFERROR(SEARCH("lending",D10),0)+IFERROR(SEARCH("payment",D10),0)+IFERROR(SEARCH("banking",D10),0)+IFERROR(SEARCH("insurance",D10),0)>0,"FinTech", IF(IFERROR(SEARCH("tech",D10),0)+IFERROR(SEARCH("software",D10),0)+IFERROR(SEARCH("saas",D10),0)+IFERROR(SEARCH("ai",D10),0)+IFERROR(SEARCH("iot",D10),0)+IFERROR(SEARCH("cloud",D10),0)+IFERROR(SEARCH("data",D10),0)+IFERROR(SEARCH("analytics",D10),0)>0,"Technology", IF(IFERROR(SEARCH("food",D10),0)+IFERROR(SEARCH("restaurant",D10),0)+IFERROR(SEARCH("hospitality",D10),0)+IFERROR(SEARCH("beverage",D10),0)+IFERROR(SEARCH("delivery",D10),0)>0,"Food & Beverage", IF(IFERROR(SEARCH("health",D10),0)+IFERROR(SEARCH("medical",D10),0)+IFERROR(SEARCH("pharma",D10),0)+IFERROR(SEARCH("wellness",D10),0)+IFERROR(SEARCH("fitness",D10),0)>0,"Healthcare", IF(IFERROR(SEARCH("edu",D10),0)+IFERROR(SEARCH("learning",D10),0)+IFERROR(SEARCH("school",D10),0)+IFERROR(SEARCH("e-tech",D10),0)>0,"Education", IF(IFERROR(SEARCH("logistics",D10),0)+IFERROR(SEARCH("transport",D10),0)+IFERROR(SEARCH("delivery",D10),0)+IFERROR(SEARCH("mobility",D10),0)+IFERROR(SEARCH("automobile",D10),0)>0,"Logistics & Transport", IF(IFERROR(SEARCH("travel",D10),0)+IFERROR(SEARCH("hotel",D10),0)+IFERROR(SEARCH("booking",D10),0)+IFERROR(SEARCH("tourism",D10),0)>0,"Travel & Hospitality", IF(IFERROR(SEARCH("fashion",D10),0)+IFERROR(SEARCH("apparel",D10),0)+IFERROR(SEARCH("clothing",D10),0)+IFERROR(SEARCH("jewelry",D10),0)+IFERROR(SEARCH("beauty",D10),0)>0,"Fashion & Lifestyle", IF(IFERROR(SEARCH("media",D10),0)+IFERROR(SEARCH("entertainment",D10),0)+IFERROR(SEARCH("video",D10),0)+IFERROR(SEARCH("gaming",D10),0)+IFERROR(SEARCH("music",D10),0)+IFERROR(SEARCH("social",D10),0)>0,"Media & Entertainment", IF(IFERROR(SEARCH("agri",D10),0)+IFERROR(SEARCH("farm",D10),0)+IFERROR(SEARCH("agtech",D10),0)>0,"Agriculture", IF(IFERROR(SEARCH("real estate",D10),0)+IFERROR(SEARCH("property",D10),0)+IFERROR(SEARCH("housing",D10),0)>0,"Real Estate", IF(IFERROR(SEARCH("energy",D10),0)+IFERROR(SEARCH("solar",D10),0)+IFERROR(SEARCH("clean tech",D10),0)+IFERROR(SEARCH("waste",D10),0)>0,"Energy & Environment", IF(IFERROR(SEARCH("hr",D10),0)+IFERROR(SEARCH("recruit",D10),0)+IFERROR(SEARCH("hiring",D10),0)+IFERROR(SEARCH("job",D10),0)>0,"HR & Recruitment", "Others")))))))))))))) -> E-Commerce | R10: =IF(ISNUMBER(SEARCH("bang",F10)),"Bangalore",IF(ISNUMBER(SEARCH("beng",F10)),"Bangalore",IF(ISNUMBER(SEARCH("mumbai",F10)),"Mumbai",IF(ISNUMBER(SEARCH("delhi",F10)),"Delhi-NCR",IF(ISNUMBER(SEARCH("gurgaon",F10)),"Delhi-NCR",IF(ISNUMBER(SEARCH("gurugram",F10)),"Delhi-NCR",IF(ISNUMBER(SEARCH("noida",F10)),"Delhi-NCR",IF(ISNUMBER(SEARCH("faridabad",F10)),"Delhi-NCR",IF(ISNUMBER(SEARCH("chennai",F10)),"Chennai",IF(ISNUMBER(SEARCH("hyderabad",F10)),"Hyderabad",IF(ISNUMBER(SEARCH("pune",F10)),"Pune",IF(ISNUMBER(SEARCH("kolkata",F10)),"Kolkata",IF(ISNUMBER(SEARCH("ahmedabad",F10)),"Ahmedabad",IF(ISNUMBER(SEARCH("jaipur",F10)),"Jaipur",IF(ISNUMBER(SEARCH("coimbatore",F10)),"Coimbatore",IF(ISNUMBER(SEARCH("kochi",F10)),"Kerala Cities",IF(ISNUMBER(SEARCH("cochin",F10)),"Kerala Cities",IF(ISNUMBER(SEARCH("francisco",F10)),"USA",IF(ISNUMBER(SEARCH("new york",F10)),"USA",IF(ISNUMBER(SEARCH("california",F10)),"USA",IF(ISNUMBER(SEARCH("palo alto",F10)),"USA",IF(ISNUMBER(SEARCH("santa",F10)),"USA",IF(ISNUMBER(SEARCH("singapore",F10)),"Singapore",IF(ISNUMBER(SEARCH("london",F10)),"London/UK",IF(F10="","Unknown","Other Cities"))))))))))))))))))))))))) -> Delhi-NCR
A11: 10 | B11: 43802 | C11: Dhruva Space | D11: Aerospace | E11: Satellite Communication | F11: Bengaluru | G11: Mumbai Angels, Ravikanth Reddy | H11: =IFERROR(TRIM(LEFT(G11,FIND(",",G11)-1)),TRIM(G11)) -> Mumbai Angels | I11: =IF(TRIM(G11)="",0,LEN(G11)-LEN(SUBSTITUTE(G11,",",""))+1) -> 2 | J11: =IF(Table1[[#This Row],[Investor Count]]>1,"Yes","No") -> Yes | K11: Seed | L11: 50000000 | M11: =YEAR(B11) -> 2019 | N11: =TEXT(B11,"mmmm") -> December | O11: 479.8525 | P11: =IF(ISBLANK(K11),"Unknown",IF(OR(ISNUMBER(SEARCH("seed",K11)),ISNUMBER(SEARCH("Seed",K11))),"Seed",IF(ISNUMBER(SEARCH("Series A",K11)),"Series A",IF(ISNUMBER(SEARCH("Series B",K11)),"Series B",IF(ISNUMBER(SEARCH("Series C",K11)),"Series C",IF(ISNUMBER(SEARCH("Series D",K11)),"Series D",IF(ISNUMBER(SEARCH("Private Equity",K11)),"Private Equity","Other"))))))) -> Seed | Q11: =IF(IFERROR(SEARCH("ecom",D11),0)+IFERROR(SEARCH("commerce",D11),0)+IFERROR(SEARCH("retail",D11),0)>0,"E-Commerce", IF(IFERROR(SEARCH("fintech",D11),0)+IFERROR(SEARCH("finance",D11),0)+IFERROR(SEARCH("financial",D11),0)+IFERROR(SEARCH("lending",D11),0)+IFERROR(SEARCH("payment",D11),0)+IFERROR(SEARCH("banking",D11),0)+IFERROR(SEARCH("insurance",D11),0)>0,"FinTech", IF(IFERROR(SEARCH("tech",D11),0)+IFERROR(SEARCH("software",D11),0)+IFERROR(SEARCH("saas",D11),0)+IFERROR(SEARCH("ai",D11),0)+IFERROR(SEARCH("iot",D11),0)+IFERROR(SEARCH("cloud",D11),0)+IFERROR(SEARCH("data",D11),0)+IFERROR(SEARCH("analytics",D11),0)>0,"Technology", IF(IFERROR(SEARCH("food",D11),0)+IFERROR(SEARCH("restaurant",D11),0)+IFERROR(SEARCH("hospitality",D11),0)+IFERROR(SEARCH("beverage",D11),0)+IFERROR(SEARCH("delivery",D11),0)>0,"Food & Beverage", IF(IFERROR(SEARCH("health",D11),0)+IFERROR(SEARCH("medical",D11),0)+IFERROR(SEARCH("pharma",D11),0)+IFERROR(SEARCH("wellness",D11),0)+IFERROR(SEARCH("fitness",D11),0)>0,"Healthcare", IF(IFERROR(SEARCH("edu",D11),0)+IFERROR(SEARCH("learning",D11),0)+IFERROR(SEARCH("school",D11),0)+IFERROR(SEARCH("e-tech",D11),0)>0,"Education", IF(IFERROR(SEARCH("logistics",D11),0)+IFERROR(SEARCH("transport",D11),0)+IFERROR(SEARCH("delivery",D11),0)+IFERROR(SEARCH("mobility",D11),0)+IFERROR(SEARCH("automobile",D11),0)>0,"Logistics & Transport", IF(IFERROR(SEARCH("travel",D11),0)+IFERROR(SEARCH("hotel",D11),0)+IFERROR(SEARCH("booking",D11),0)+IFERROR(SEARCH("tourism",D11),0)>0,"Travel & Hospitality", IF(IFERROR(SEARCH("fashion",D11),0)+IFERROR(SEARCH("apparel",D11),0)+IFERROR(SEARCH("clothing",D11),0)+IFERROR(SEARCH("jewelry",D11),0)+IFERROR(SEARCH("beauty",D11),0)>0,"Fashion & Lifestyle", IF(IFERROR(SEARCH("media",D11),0)+IFERROR(SEARCH("entertainment",D11),0)+IFERROR(SEARCH("video",D11),0)+IFERROR(SEARCH("gaming",D11),0)+IFERROR(SEARCH("music",D11),0)+IFERROR(SEARCH("social",D11),0)>0,"Media & Entertainment", IF(IFERROR(SEARCH("agri",D11),0)+IFERROR(SEARCH("farm",D11),0)+IFERROR(SEARCH("agtech",D11),0)>0,"Agriculture", IF(IFERROR(SEARCH("real estate",D11),0)+IFERROR(SEARCH("property",D11),0)+IFERROR(SEARCH("housing",D11),0)>0,"Real Estate", IF(IFERROR(SEARCH("energy",D11),0)+IFERROR(SEARCH("solar",D11),0)+IFERROR(SEARCH("clean tech",D11),0)+IFERROR(SEARCH("waste",D11),0)>0,"Energy & Environment", IF(IFERROR(SEARCH("hr",D11),0)+IFERROR(SEARCH("recruit",D11),0)+IFERROR(SEARCH("hiring",D11),0)+IFERROR(SEARCH("job",D11),0)>0,"HR & Recruitment", "Others")))))))))))))) -> Others | R11: =IF(ISNUMBER(SEARCH("bang",F11)),"Bangalore",IF(ISNUMBER(SEARCH("beng",F11)),"Bangalore",IF(ISNUMBER(SEARCH("mumbai",F11)),"Mumbai",IF(ISNUMBER(SEARCH("delhi",F11)),"Delhi-NCR",IF(ISNUMBER(SEARCH("gurgaon",F11)),"Delhi-NCR",IF(ISNUMBER(SEARCH("gurugram",F11)),"Delhi-NCR",IF(ISNUMBER(SEARCH("noida",F11)),"Delhi-NCR",IF(ISNUMBER(SEARCH("faridabad",F11)),"Delhi-NCR",IF(ISNUMBER(SEARCH("chennai",F11)),"Chennai",IF(ISNUMBER(SEARCH("hyderabad",F11)),"Hyderabad",IF(ISNUMBER(SEARCH("pune",F11)),"Pune",IF(ISNUMBER(SEARCH("kolkata",F11)),"Kolkata",IF(ISNUMBER(SEARCH("ahmedabad",F11)),"Ahmedabad",IF(ISNUMBER(SEARCH("jaipur",F11)),"Jaipur",IF(ISNUMBER(SEARCH("coimbatore",F11)),"Coimbatore",IF(ISNUMBER(SEARCH("kochi",F11)),"Kerala Cities",IF(ISNUMBER(SEARCH("cochin",F11)),"Kerala Cities",IF(ISNUMBER(SEARCH("francisco",F11)),"USA",IF(ISNUMBER(SEARCH("new york",F11)),"USA",IF(ISNUMBER(SEARCH("california",F11)),"USA",IF(ISNUMBER(SEARCH("palo alto",F11)),"USA",IF(ISNUMBER(SEARCH("santa",F11)),"USA",IF(ISNUMBER(SEARCH("singapore",F11)),"Singapore",IF(ISNUMBER(SEARCH("london",F11)),"London/UK",IF(F11="","Unknown","Other Cities"))))))))))))))))))))))))) -> Bangalore
A12: 11 | B12: 43812 | C12: Rivigo | D12: Technology | E12: Logistics Services , Solutions | F12: Gurgaon | G12: Saif Partners, Spring Canter Investment Ltd | H12: =IFERROR(TRIM(LEFT(G12,FIND(",",G12)-1)),TRIM(G12)) -> Saif Partners | I12: =IF(TRIM(G12)="",0,LEN(G12)-LEN(SUBSTITUTE(G12,",",""))+1) -> 2 | J12: =IF(Table1[[#This Row],[Investor Count]]>1,"Yes","No") -> Yes | K12: Series F | L12: 20000000 | M12: =YEAR(B12) -> 2019 | N12: =TEXT(B12,"mmmm") -> December | O12: 191.941 | P12: =IF(ISBLANK(K12),"Unknown",IF(OR(ISNUMBER(SEARCH("seed",K12)),ISNUMBER(SEARCH("Seed",K12))),"Seed",IF(ISNUMBER(SEARCH("Series A",K12)),"Series A",IF(ISNUMBER(SEARCH("Series B",K12)),"Series B",IF(ISNUMBER(SEARCH("Series C",K12)),"Series C",IF(ISNUMBER(SEARCH("Series D",K12)),"Series D",IF(ISNUMBER(SEARCH("Private Equity",K12)),"Private Equity","Other"))))))) -> Other | Q12: =IF(IFERROR(SEARCH("ecom",D12),0)+IFERROR(SEARCH("commerce",D12),0)+IFERROR(SEARCH("retail",D12),0)>0,"E-Commerce", IF(IFERROR(SEARCH("fintech",D12),0)+IFERROR(SEARCH("finance",D12),0)+IFERROR(SEARCH("financial",D12),0)+IFERROR(SEARCH("lending",D12),0)+IFERROR(SEARCH("payment",D12),0)+IFERROR(SEARCH("banking",D12),0)+IFERROR(SEARCH("insurance",D12),0)>0,"FinTech", IF(IFERROR(SEARCH("tech",D12),0)+IFERROR(SEARCH("software",D12),0)+IFERROR(SEARCH("saas",D12),0)+IFERROR(SEARCH("ai",D12),0)+IFERROR(SEARCH("iot",D12),0)+IFERROR(SEARCH("cloud",D12),0)+IFERROR(SEARCH("data",D12),0)+IFERROR(SEARCH("analytics",D12),0)>0,"Technology", IF(IFERROR(SEARCH("food",D12),0)+IFERROR(SEARCH("restaurant",D12),0)+IFERROR(SEARCH("hospitality",D12),0)+IFERROR(SEARCH("beverage",D12),0)+IFERROR(SEARCH("delivery",D12),0)>0,"Food & Beverage", IF(IFERROR(SEARCH("health",D12),0)+IFERROR(SEARCH("medical",D12),0)+IFERROR(SEARCH("pharma",D12),0)+IFERROR(SEARCH("wellness",D12),0)+IFERROR(SEARCH("fitness",D12),0)>0,"Healthcare", IF(IFERROR(SEARCH("edu",D12),0)+IFERROR(SEARCH("learning",D12),0)+IFERROR(SEARCH("school",D12),0)+IFERROR(SEARCH("e-tech",D12),0)>0,"Education", IF(IFERROR(SEARCH("logistics",D12),0)+IFERROR(SEARCH("transport",D12),0)+IFERROR(SEARCH("delivery",D12),0)+IFERROR(SEARCH("mobility",D12),0)+IFERROR(SEARCH("automobile",D12),0)>0,"Logistics & Transport", IF(IFERROR(SEARCH("travel",D12),0)+IFERROR(SEARCH("hotel",D12),0)+IFERROR(SEARCH("booking",D12),0)+IFERROR(SEARCH("tourism",D12),0)>0,"Travel & Hospitality", IF(IFERROR(SEARCH("fashion",D12),0)+IFERROR(SEARCH("apparel",D12),0)+IFERROR(SEARCH("clothing",D12),0)+IFERROR(SEARCH("jewelry",D12),0)+IFERROR(SEARCH("beauty",D12),0)>0,"Fashion & Lifestyle", IF(IFERROR(SEARCH("media",D12),0)+IFERROR(SEARCH("entertainment",D12),0)+IFERROR(SEARCH("video",D12),0)+IFERROR(SEARCH("gaming",D12),0)+IFERROR(SEARCH("music",D12),0)+IFERROR(SEARCH("social",D12),0)>0,"Media & Entertainment", IF(IFERROR(SEARCH("agri",D12),0)+IFERROR(SEARCH("farm",D12),0)+IFERROR(SEARCH("agtech",D12),0)>0,"Agriculture", IF(IFERROR(SEARCH("real estate",D12),0)+IFERROR(SEARCH("property",D12),0)+IFERROR(SEARCH("housing",D12),0)>0,"Real Estate", IF(IFERROR(SEARCH("energy",D12),0)+IFERROR(SEARCH("solar",D12),0)+IFERROR(SEARCH("clean tech",D12),0)+IFERROR(SEARCH("waste",D12),0)>0,"Energy & Environment", IF(IFERROR(SEARCH("hr",D12),0)+IFERROR(SEARCH("recruit",D12),0)+IFERROR(SEARCH("hiring",D12),0)+IFERROR(SEARCH("job",D12),0)>0,"HR & Recruitment", "Others")))))))))))))) -> Technology | R12: =IF(ISNUMBER(SEARCH("bang",F12)),"Bangalore",IF(ISNUMBER(SEARCH("beng",F12)),"Bangalore",IF(ISNUMBER(SEARCH("mumbai",F12)),"Mumbai",IF(ISNUMBER(SEARCH("delhi",F12)),"Delhi-NCR",IF(ISNUMBER(SEARCH("gurgaon",F12)),"Delhi-NCR",IF(ISNUMBER(SEARCH("gurugram",F12)),"Delhi-NCR",IF(ISNUMBER(SEARCH("noida",F12)),"Delhi-NCR",IF(ISNUMBER(SEARCH("faridabad",F12)),"Delhi-NCR",IF(ISNUMBER(SEARCH("chennai",F12)),"Chennai",IF(ISNUMBER(SEARCH("hyderabad",F12)),"Hyderabad",IF(ISNUMBER(SEARCH("pune",F12)),"Pune",IF(ISNUMBER(SEARCH("kolkata",F12)),"Kolkata",IF(ISNUMBER(SEARCH("ahmedabad",F12)),"Ahmedabad",IF(ISNUMBER(SEARCH("jaipur",F12)),"Jaipur",IF(ISNUMBER(SEARCH("coimbatore",F12)),"Coimbatore",IF(ISNUMBER(SEARCH("kochi",F12)),"Kerala Cities",IF(ISNUMBER(SEARCH("cochin",F12)),"Kerala Cities",IF(ISNUMBER(SEARCH("francisco",F12)),"USA",IF(ISNUMBER(SEARCH("new york",F12)),"USA",IF(ISNUMBER(SEARCH("california",F12)),"USA",IF(ISNUMBER(SEARCH("palo alto",F12)),"USA",IF(ISNUMBER(SEARCH("santa",F12)),"USA",IF(ISNUMBER(SEARCH("singapore",F12)),"Singapore",IF(ISNUMBER(SEARCH("london",F12)),"London/UK",IF(F12="","Unknown","Other Cities"))))))))))))))))))))))))) -> Delhi-NCR
A13: 12 | B13: 43816 | C13: Healthians | D13: B2B-focused foodtech startup | E13: Food Solutions For Corporate | F13: Bengaluru | G13: Paytm, Nptk, Sabre Partners , Neoplux | H13: =IFERROR(TRIM(LEFT(G13,FIND(",",G13)-1)),TRIM(G13)) -> Paytm | I13: =IF(TRIM(G13)="",0,LEN(G13)-LEN(SUBSTITUTE(G13,",",""))+1) -> 4 | J13: =IF(Table1[[#This Row],[Investor Count]]>1,"Yes","No") -> Yes | K13: Series C | L13: 12000000 | M13: =YEAR(B13) -> 2019 | N13: =TEXT(B13,"mmmm") -> December | O13: 115.1646 | P13: =IF(ISBLANK(K13),"Unknown",IF(OR(ISNUMBER(SEARCH("seed",K13)),ISNUMBER(SEARCH("Seed",K13))),"Seed",IF(ISNUMBER(SEARCH("Series A",K13)),"Series A",IF(ISNUMBER(SEARCH("Series B",K13)),"Series B",IF(ISNUMBER(SEARCH("Series C",K13)),"Series C",IF(ISNUMBER(SEARCH("Series D",K13)),"Series D",IF(ISNUMBER(SEARCH("Private Equity",K13)),"Private Equity","Other"))))))) -> Series C | Q13: =IF(IFERROR(SEARCH("ecom",D13),0)+IFERROR(SEARCH("commerce",D13),0)+IFERROR(SEARCH("retail",D13),0)>0,"E-Commerce", IF(IFERROR(SEARCH("fintech",D13),0)+IFERROR(SEARCH("finance",D13),0)+IFERROR(SEARCH("financial",D13),0)+IFERROR(SEARCH("lending",D13),0)+IFERROR(SEARCH("payment",D13),0)+IFERROR(SEARCH("banking",D13),0)+IFERROR(SEARCH("insurance",D13),0)>0,"FinTech", IF(IFERROR(SEARCH("tech",D13),0)+IFERROR(SEARCH("software",D13),0)+IFERROR(SEARCH("saas",D13),0)+IFERROR(SEARCH("ai",D13),0)+IFERROR(SEARCH("iot",D13),0)+IFERROR(SEARCH("cloud",D13),0)+IFERROR(SEARCH("data",D13),0)+IFERROR(SEARCH("analytics",D13),0)>0,"Technology", IF(IFERROR(SEARCH("food",D13),0)+IFERROR(SEARCH("restaurant",D13),0)+IFERROR(SEARCH("hospitality",D13),0)+IFERROR(SEARCH("beverage",D13),0)+IFERROR(SEARCH("delivery",D13),0)>0,"Food & Beverage", IF(IFERROR(SEARCH("health",D13),0)+IFERROR(SEARCH("medical",D13),0)+IFERROR(SEARCH("pharma",D13),0)+IFERROR(SEARCH("wellness",D13),0)+IFERROR(SEARCH("fitness",D13),0)>0,"Healthcare", IF(IFERROR(SEARCH("edu",D13),0)+IFERROR(SEARCH("learning",D13),0)+IFERROR(SEARCH("school",D13),0)+IFERROR(SEARCH("e-tech",D13),0)>0,"Education", IF(IFERROR(SEARCH("logistics",D13),0)+IFERROR(SEARCH("transport",D13),0)+IFERROR(SEARCH("delivery",D13),0)+IFERROR(SEARCH("mobility",D13),0)+IFERROR(SEARCH("automobile",D13),0)>0,"Logistics & Transport", IF(IFERROR(SEARCH("travel",D13),0)+IFERROR(SEARCH("hotel",D13),0)+IFERROR(SEARCH("booking",D13),0)+IFERROR(SEARCH("tourism",D13),0)>0,"Travel & Hospitality", IF(IFERROR(SEARCH("fashion",D13),0)+IFERROR(SEARCH("apparel",D13),0)+IFERROR(SEARCH("clothing",D13),0)+IFERROR(SEARCH("jewelry",D13),0)+IFERROR(SEARCH("beauty",D13),0)>0,"Fashion & Lifestyle", IF(IFERROR(SEARCH("media",D13),0)+IFERROR(SEARCH("entertainment",D13),0)+IFERROR(SEARCH("video",D13),0)+IFERROR(SEARCH("gaming",D13),0)+IFERROR(SEARCH("music",D13),0)+IFERROR(SEARCH("social",D13),0)>0,"Media & Entertainment", IF(IFERROR(SEARCH("agri",D13),0)+IFERROR(SEARCH("farm",D13),0)+IFERROR(SEARCH("agtech",D13),0)>0,"Agriculture", IF(IFERROR(SEARCH("real estate",D13),0)+IFERROR(SEARCH("property",D13),0)+IFERROR(SEARCH("housing",D13),0)>0,"Real Estate", IF(IFERROR(SEARCH("energy",D13),0)+IFERROR(SEARCH("solar",D13),0)+IFERROR(SEARCH("clean tech",D13),0)+IFERROR(SEARCH("waste",D13),0)>0,"Energy & Environment", IF(IFERROR(SEARCH("hr",D13),0)+IFERROR(SEARCH("recruit",D13),0)+IFERROR(SEARCH("hiring",D13),0)+IFERROR(SEARCH("job",D13),0)>0,"HR & Recruitment", "Others")))))))))))))) -> Technology | R13: =IF(ISNUMBER(SEARCH("bang",F13)),"Bangalore",IF(ISNUMBER(SEARCH("beng",F13)),"Bangalore",IF(ISNUMBER(SEARCH("mumbai",F13)),"Mumbai",IF(ISNUMBER(SEARCH("delhi",F13)),"Delhi-NCR",IF(ISNUMBER(SEARCH("gurgaon",F13)),"Delhi-NCR",IF(ISNUMBER(SEARCH("gurugram",F13)),"Delhi-NCR",IF(ISNUMBER(SEARCH("noida",F13)),"Delhi-NCR",IF(ISNUMBER(SEARCH("faridabad",F13)),"Delhi-NCR",IF(ISNUMBER(SEARCH("chennai",F13)),"Chennai",IF(ISNUMBER(SEARCH("hyderabad",F13)),"Hyderabad",IF(ISNUMBER(SEARCH("pune",F13)),"Pune",IF(ISNUMBER(SEARCH("kolkata",F13)),"Kolkata",IF(ISNUMBER(SEARCH("ahmedabad",F13)),"Ahmedabad",IF(ISNUMBER(SEARCH("jaipur",F13)),"Jaipur",IF(ISNUMBER(SEARCH("coimbatore",F13)),"Coimbatore",IF(ISNUMBER(SEARCH("kochi",F13)),"Kerala Cities",IF(ISNUMBER(SEARCH("cochin",F13)),"Kerala Cities",IF(ISNUMBER(SEARCH("francisco",F13)),"USA",IF(ISNUMBER(SEARCH("new york",F13)),"USA",IF(ISNUMBER(SEARCH("california",F13)),"USA",IF(ISNUMBER(SEARCH("palo alto",F13)),"USA",IF(ISNUMBER(SEARCH("santa",F13)),"USA",IF(ISNUMBER(SEARCH("singapore",F13)),"Singapore",IF(ISNUMBER(SEARCH("london",F13)),"London/UK",IF(F13="","Unknown","Other Cities"))))))))))))))))))))))))) -> Bangalore
... A21: 20 | B21: 43782 | C21: Sunstone Eduversity Pvt. Ltd | D21: Education | E21: Elearning | F21: Gurgaon | G21: Prime Venture Partners, Letsventure, Ps1 Venture , Globallogic Co-Founder Rajul Garg | H21: =IFERROR(TRIM(LEFT(G21,FIND(",",G21)-1)),TRIM(G21)) -> Prime Venture Partners | I21: =IF(TRIM(G21)="",0,LEN(G21)-LEN(SUBSTITUTE(G21,",",""))+1) -> 4 | J21: =IF(Table1[[#This Row],[Investor Count]]>1,"Yes","No") -> Yes | K21: Seed | L21: 1500000 | M21: =YEAR(B21) -> 2019 | N21: =TEXT(B21,"mmmm") -> November | O21: 14.395575 | P21: =IF(ISBLANK(K21),"Unknown",IF(OR(ISNUMBER(SEARCH("seed",K21)),ISNUMBER(SEARCH("Seed",K21))),"Seed",IF(ISNUMBER(SEARCH("Series A",K21)),"Series A",IF(ISNUMBER(SEARCH("Series B",K21)),"Series B",IF(ISNUMBER(SEARCH("Series C",K21)),"Series C",IF(ISNUMBER(SEARCH("Series D",K21)),"Series D",IF(ISNUMBER(SEARCH("Private Equity",K21)),"Private Equity","Other"))))))) -> Seed | Q21: =IF(IFERROR(SEARCH("ecom",D21),0)+IFERROR(SEARCH("commerce",D21),0)+IFERROR(SEARCH("retail",D21),0)>0,"E-Commerce", IF(IFERROR(SEARCH("fintech",D21),0)+IFERROR(SEARCH("finance",D21),0)+IFERROR(SEARCH("financial",D21),0)+IFERROR(SEARCH("lending",D21),0)+IFERROR(SEARCH("payment",D21),0)+IFERROR(SEARCH("banking",D21),0)+IFERROR(SEARCH("insurance",D21),0)>0,"FinTech", IF(IFERROR(SEARCH("tech",D21),0)+IFERROR(SEARCH("software",D21),0)+IFERROR(SEARCH("saas",D21),0)+IFERROR(SEARCH("ai",D21),0)+IFERROR(SEARCH("iot",D21),0)+IFERROR(SEARCH("cloud",D21),0)+IFERROR(SEARCH("data",D21),0)+IFERROR(SEARCH("analytics",D21),0)>0,"Technology", IF(IFERROR(SEARCH("food",D21),0)+IFERROR(SEARCH("restaurant",D21),0)+IFERROR(SEARCH("hospitality",D21),0)+IFERROR(SEARCH("beverage",D21),0)+IFERROR(SEARCH("delivery",D21),0)>0,"Food & Beverage", IF(IFERROR(SEARCH("health",D21),0)+IFERROR(SEARCH("medical",D21),0)+IFERROR(SEARCH("pharma",D21),0)+IFERROR(SEARCH("wellness",D21),0)+IFERROR(SEARCH("fitness",D21),0)>0,"Healthcare", IF(IFERROR(SEARCH("edu",D21),0)+IFERROR(SEARCH("learning",D21),0)+IFERROR(SEARCH("school",D21),0)+IFERROR(SEARCH("e-tech",D21),0)>0,"Education", IF(IFERROR(SEARCH("logistics",D21),0)+IFERROR(SEARCH("transport",D21),0)+IFERROR(SEARCH("delivery",D21),0)+IFERROR(SEARCH("mobility",D21),0)+IFERROR(SEARCH("automobile",D21),0)>0,"Logistics & Transport", IF(IFERROR(SEARCH("travel",D21),0)+IFERROR(SEARCH("hotel",D21),0)+IFERROR(SEARCH("booking",D21),0)+IFERROR(SEARCH("tourism",D21),0)>0,"Travel & Hospitality", IF(IFERROR(SEARCH("fashion",D21),0)+IFERROR(SEARCH("apparel",D21),0)+IFERROR(SEARCH("clothing",D21),0)+IFERROR(SEARCH("jewelry",D21),0)+IFERROR(SEARCH("beauty",D21),0)>0,"Fashion & Lifestyle", IF(IFERROR(SEARCH("media",D21),0)+IFERROR(SEARCH("entertainment",D21),0)+IFERROR(SEARCH("video",D21),0)+IFERROR(SEARCH("gaming",D21),0)+IFERROR(SEARCH("music",D21),0)+IFERROR(SEARCH("social",D21),0)>0,"Media & Entertainment", IF(IFERROR(SEARCH("agri",D21),0)+IFERROR(SEARCH("farm",D21),0)+IFERROR(SEARCH("agtech",D21),0)>0,"Agriculture", IF(IFERROR(SEARCH("real estate",D21),0)+IFERROR(SEARCH("property",D21),0)+IFERROR(SEARCH("housing",D21),0)>0,"Real Estate", IF(IFERROR(SEARCH("energy",D21),0)+IFERROR(SEARCH("solar",D21),0)+IFERROR(SEARCH("clean tech",D21),0)+IFERROR(SEARCH("waste",D21),0)>0,"Energy & Environment", IF(IFERROR(SEARCH("hr",D21),0)+IFERROR(SEARCH("recruit",D21),0)+IFERROR(SEARCH("hiring",D21),0)+IFERROR(SEARCH("job",D21),0)>0,"HR & Recruitment", "Others")))))))))))))) -> Education | R21: =IF(ISNUMBER(SEARCH("bang",F21)),"Bangalore",IF(ISNUMBER(SEARCH("beng",F21)),"Bangalore",IF(ISNUMBER(SEARCH("mumbai",F21)),"Mumbai",IF(ISNUMBER(SEARCH("delhi",F21)),"Delhi-NCR",IF(ISNUMBER(SEARCH("gurgaon",F21)),"Delhi-NCR",IF(ISNUMBER(SEARCH("gurugram",F21)),"Delhi-NCR",IF(ISNUMBER(SEARCH("noida",F21)),"Delhi-NCR",IF(ISNUMBER(SEARCH("faridabad",F21)),"Delhi-NCR",IF(ISNUMBER(SEARCH("chennai",F21)),"Chennai",IF(ISNUMBER(SEARCH("hyderabad",F21)),"Hyderabad",IF(ISNUMBER(SEARCH("pune",F21)),"Pune",IF(ISNUMBER(SEARCH("kolkata",F21)),"Kolkata",IF(ISNUMBER(SEARCH("ahmedabad",F21)),"Ahmedabad",IF(ISNUMBER(SEARCH("jaipur",F21)),"Jaipur",IF(ISNUMBER(SEARCH("coimbatore",F21)),"Coimbatore",IF(ISNUMBER(SEARCH("kochi",F21)),"Kerala Cities",IF(ISNUMBER(SEARCH("cochin",F21)),"Kerala Cities",IF(ISNUMBER(SEARCH("francisco",F21)),"USA",IF(ISNUMBER(SEARCH("new york",F21)),"USA",IF(ISNUMBER(SEARCH("california",F21)),"USA",IF(ISNUMBER(SEARCH("palo alto",F21)),"USA",IF(ISNUMBER(SEARCH("santa",F21)),"USA",IF(ISNUMBER(SEARCH("singapore",F21)),"Singapore",IF(ISNUMBER(SEARCH("london",F21)),"London/UK",IF(F21="","Unknown","Other Cities"))))))))))))))))))))))))) -> Delhi-NCR
A22: 21 | B22: 43786 | C22: Burger Singh | D22: Food & Beverage | E22: Indian Burger | F22: Gurgaon | G22: Rb Investments | H22: =IFERROR(TRIM(LEFT(G22,FIND(",",G22)-1)),TRIM(G22)) -> Rb Investments | I22: =IF(TRIM(G22)="",0,LEN(G22)-LEN(SUBSTITUTE(G22,",",""))+1) -> 1 | J22: =IF(Table1[[#This Row],[Investor Count]]>1,"Yes","No") -> No | K22: Venture | M22: =YEAR(B22) -> 2019 | N22: =TEXT(B22,"mmmm") -> November | O22: 0 | P22: =IF(ISBLANK(K22),"Unknown",IF(OR(ISNUMBER(SEARCH("seed",K22)),ISNUMBER(SEARCH("Seed",K22))),"Seed",IF(ISNUMBER(SEARCH("Series A",K22)),"Series A",IF(ISNUMBER(SEARCH("Series B",K22)),"Series B",IF(ISNUMBER(SEARCH("Series C",K22)),"Series C",IF(ISNUMBER(SEARCH("Series D",K22)),"Series D",IF(ISNUMBER(SEARCH("Private Equity",K22)),"Private Equity","Other"))))))) -> Other | Q22: =IF(IFERROR(SEARCH("ecom",D22),0)+IFERROR(SEARCH("commerce",D22),0)+IFERROR(SEARCH("retail",D22),0)>0,"E-Commerce", IF(IFERROR(SEARCH("fintech",D22),0)+IFERROR(SEARCH("finance",D22),0)+IFERROR(SEARCH("financial",D22),0)+IFERROR(SEARCH("lending",D22),0)+IFERROR(SEARCH("payment",D22),0)+IFERROR(SEARCH("banking",D22),0)+IFERROR(SEARCH("insurance",D22),0)>0,"FinTech", IF(IFERROR(SEARCH("tech",D22),0)+IFERROR(SEARCH("software",D22),0)+IFERROR(SEARCH("saas",D22),0)+IFERROR(SEARCH("ai",D22),0)+IFERROR(SEARCH("iot",D22),0)+IFERROR(SEARCH("cloud",D22),0)+IFERROR(SEARCH("data",D22),0)+IFERROR(SEARCH("analytics",D22),0)>0,"Technology", IF(IFERROR(SEARCH("food",D22),0)+IFERROR(SEARCH("restaurant",D22),0)+IFERROR(SEARCH("hospitality",D22),0)+IFERROR(SEARCH("beverage",D22),0)+IFERROR(SEARCH("delivery",D22),0)>0,"Food & Beverage", IF(IFERROR(SEARCH("health",D22),0)+IFERROR(SEARCH("medical",D22),0)+IFERROR(SEARCH("pharma",D22),0)+IFERROR(SEARCH("wellness",D22),0)+IFERROR(SEARCH("fitness",D22),0)>0,"Healthcare", IF(IFERROR(SEARCH("edu",D22),0)+IFERROR(SEARCH("learning",D22),0)+IFERROR(SEARCH("school",D22),0)+IFERROR(SEARCH("e-tech",D22),0)>0,"Education", IF(IFERROR(SEARCH("logistics",D22),0)+IFERROR(SEARCH("transport",D22),0)+IFERROR(SEARCH("delivery",D22),0)+IFERROR(SEARCH("mobility",D22),0)+IFERROR(SEARCH("automobile",D22),0)>0,"Logistics & Transport", IF(IFERROR(SEARCH("travel",D22),0)+IFERROR(SEARCH("hotel",D22),0)+IFERROR(SEARCH("booking",D22),0)+IFERROR(SEARCH("tourism",D22),0)>0,"Travel & Hospitality", IF(IFERROR(SEARCH("fashion",D22),0)+IFERROR(SEARCH("apparel",D22),0)+IFERROR(SEARCH("clothing",D22),0)+IFERROR(SEARCH("jewelry",D22),0)+IFERROR(SEARCH("beauty",D22),0)>0,"Fashion & Lifestyle", IF(IFERROR(SEARCH("media",D22),0)+IFERROR(SEARCH("entertainment",D22),0)+IFERROR(SEARCH("video",D22),0)+IFERROR(SEARCH("gaming",D22),0)+IFERROR(SEARCH("music",D22),0)+IFERROR(SEARCH("social",D22),0)>0,"Media & Entertainment", IF(IFERROR(SEARCH("agri",D22),0)+IFERROR(SEARCH("farm",D22),0)+IFERROR(SEARCH("agtech",D22),0)>0,"Agriculture", IF(IFERROR(SEARCH("real estate",D22),0)+IFERROR(SEARCH("property",D22),0)+IFERROR(SEARCH("housing",D22),0)>0,"Real Estate", IF(IFERROR(SEARCH("energy",D22),0)+IFERROR(SEARCH("solar",D22),0)+IFERROR(SEARCH("clean tech",D22),0)+IFERROR(SEARCH("waste",D22),0)>0,"Energy & Environment", IF(IFERROR(SEARCH("hr",D22),0)+IFERROR(SEARCH("recruit",D22),0)+IFERROR(SEARCH("hiring",D22),0)+IFERROR(SEARCH("job",D22),0)>0,"HR & Recruitment", "Others")))))))))))))) -> Food & Beverage | R22: =IF(ISNUMBER(SEARCH("bang",F22)),"Bangalore",IF(ISNUMBER(SEARCH("beng",F22)),"Bangalore",IF(ISNUMBER(SEARCH("mumbai",F22)),"Mumbai",IF(ISNUMBER(SEARCH("delhi",F22)),"Delhi-NCR",IF(ISNUMBER(SEARCH("gurgaon",F22)),"Delhi-NCR",IF(ISNUMBER(SEARCH("gurugram",F22)),"Delhi-NCR",IF(ISNUMBER(SEARCH("noida",F22)),"Delhi-NCR",IF(ISNUMBER(SEARCH("faridabad",F22)),"Delhi-NCR",IF(ISNUMBER(SEARCH("chennai",F22)),"Chennai",IF(ISNUMBER(SEARCH("hyderabad",F22)),"Hyderabad",IF(ISNUMBER(SEARCH("pune",F22)),"Pune",IF(ISNUMBER(SEARCH("kolkata",F22)),"Kolkata",IF(ISNUMBER(SEARCH("ahmedabad",F22)),"Ahmedabad",IF(ISNUMBER(SEARCH("jaipur",F22)),"Jaipur",IF(ISNUMBER(SEARCH("coimbatore",F22)),"Coimbatore",IF(ISNUMBER(SEARCH("kochi",F22)),"Kerala Cities",IF(ISNUMBER(SEARCH("cochin",F22)),"Kerala Cities",IF(ISNUMBER(SEARCH("francisco",F22)),"USA",IF(ISNUMBER(SEARCH("new york",F22)),"USA",IF(ISNUMBER(SEARCH("california",F22)),"USA",IF(ISNUMBER(SEARCH("palo alto",F22)),"USA",IF(ISNUMBER(SEARCH("santa",F22)),"USA",IF(ISNUMBER(SEARCH("singapore",F22)),"Singapore",IF(ISNUMBER(SEARCH("london",F22)),"London/UK",IF(F22="","Unknown","Other Cities"))))))))))))))))))))))))) -> Delhi-NCR
A23: 22 | B23: 43787 | C23: Healthians | D23: Healthcare | E23: Healthcare services | F23: Gurgaon | G23: Dg Daiwa Ventures, Dg Incubation | H23: =IFERROR(TRIM(LEFT(G23,FIND(",",G23)-1)),TRIM(G23)) -> Dg Daiwa Ventures | I23: =IF(TRIM(G23)="",0,LEN(G23)-LEN(SUBSTITUTE(G23,",",""))+1) -> 2 | J23: =IF(Table1[[#This Row],[Investor Count]]>1,"Yes","No") -> Yes | K23: Series B | L23: 12000000 | M23: =YEAR(B23) -> 2019 | N23: =TEXT(B23,"mmmm") -> November | O23: 115.1646 | P23: =IF(ISBLANK(K23),"Unknown",IF(OR(ISNUMBER(SEARCH("seed",K23)),ISNUMBER(SEARCH("Seed",K23))),"Seed",IF(ISNUMBER(SEARCH("Series A",K23)),"Series A",IF(ISNUMBER(SEARCH("Series B",K23)),"Series B",IF(ISNUMBER(SEARCH("Series C",K23)),"Series C",IF(ISNUMBER(SEARCH("Series D",K23)),"Series D",IF(ISNUMBER(SEARCH("Private Equity",K23)),"Private Equity","Other"))))))) -> Series B | Q23: =IF(IFERROR(SEARCH("ecom",D23),0)+IFERROR(SEARCH("commerce",D23),0)+IFERROR(SEARCH("retail",D23),0)>0,"E-Commerce", IF(IFERROR(SEARCH("fintech",D23),0)+IFERROR(SEARCH("finance",D23),0)+IFERROR(SEARCH("financial",D23),0)+IFERROR(SEARCH("lending",D23),0)+IFERROR(SEARCH("payment",D23),0)+IFERROR(SEARCH("banking",D23),0)+IFERROR(SEARCH("insurance",D23),0)>0,"FinTech", IF(IFERROR(SEARCH("tech",D23),0)+IFERROR(SEARCH("software",D23),0)+IFERROR(SEARCH("saas",D23),0)+IFERROR(SEARCH("ai",D23),0)+IFERROR(SEARCH("iot",D23),0)+IFERROR(SEARCH("cloud",D23),0)+IFERROR(SEARCH("data",D23),0)+IFERROR(SEARCH("analytics",D23),0)>0,"Technology", IF(IFERROR(SEARCH("food",D23),0)+IFERROR(SEARCH("restaurant",D23),0)+IFERROR(SEARCH("hospitality",D23),0)+IFERROR(SEARCH("beverage",D23),0)+IFERROR(SEARCH("delivery",D23),0)>0,"Food & Beverage", IF(IFERROR(SEARCH("health",D23),0)+IFERROR(SEARCH("medical",D23),0)+IFERROR(SEARCH("pharma",D23),0)+IFERROR(SEARCH("wellness",D23),0)+IFERROR(SEARCH("fitness",D23),0)>0,"Healthcare", IF(IFERROR(SEARCH("edu",D23),0)+IFERROR(SEARCH("learning",D23),0)+IFERROR(SEARCH("school",D23),0)+IFERROR(SEARCH("e-tech",D23),0)>0,"Education", IF(IFERROR(SEARCH("logistics",D23),0)+IFERROR(SEARCH("transport",D23),0)+IFERROR(SEARCH("delivery",D23),0)+IFERROR(SEARCH("mobility",D23),0)+IFERROR(SEARCH("automobile",D23),0)>0,"Logistics & Transport", IF(IFERROR(SEARCH("travel",D23),0)+IFERROR(SEARCH("hotel",D23),0)+IFERROR(SEARCH("booking",D23),0)+IFERROR(SEARCH("tourism",D23),0)>0,"Travel & Hospitality", IF(IFERROR(SEARCH("fashion",D23),0)+IFERROR(SEARCH("apparel",D23),0)+IFERROR(SEARCH("clothing",D23),0)+IFERROR(SEARCH("jewelry",D23),0)+IFERROR(SEARCH("beauty",D23),0)>0,"Fashion & Lifestyle", IF(IFERROR(SEARCH("media",D23),0)+IFERROR(SEARCH("entertainment",D23),0)+IFERROR(SEARCH("video",D23),0)+IFERROR(SEARCH("gaming",D23),0)+IFERROR(SEARCH("music",D23),0)+IFERROR(SEARCH("social",D23),0)>0,"Media & Entertainment", IF(IFERROR(SEARCH("agri",D23),0)+IFERROR(SEARCH("farm",D23),0)+IFERROR(SEARCH("agtech",D23),0)>0,"Agriculture", IF(IFERROR(SEARCH("real estate",D23),0)+IFERROR(SEARCH("property",D23),0)+IFERROR(SEARCH("housing",D23),0)>0,"Real Estate", IF(IFERROR(SEARCH("energy",D23),0)+IFERROR(SEARCH("solar",D23),0)+IFERROR(SEARCH("clean tech",D23),0)+IFERROR(SEARCH("waste",D23),0)>0,"Energy & Environment", IF(IFERROR(SEARCH("hr",D23),0)+IFERROR(SEARCH("recruit",D23),0)+IFERROR(SEARCH("hiring",D23),0)+IFERROR(SEARCH("job",D23),0)>0,"HR & Recruitment", "Others")))))))))))))) -> Healthcare | R23: =IF(ISNUMBER(SEARCH("bang",F23)),"Bangalore",IF(ISNUMBER(SEARCH("beng",F23)),"Bangalore",IF(ISNUMBER(SEARCH("mumbai",F23)),"Mumbai",IF(ISNUMBER(SEARCH("delhi",F23)),"Delhi-NCR",IF(ISNUMBER(SEARCH("gurgaon",F23)),"Delhi-NCR",IF(ISNUMBER(SEARCH("gurugram",F23)),"Delhi-NCR",IF(ISNUMBER(SEARCH("noida",F23)),"Delhi-NCR",IF(ISNUMBER(SEARCH("faridabad",F23)),"Delhi-NCR",IF(ISNUMBER(SEARCH("chennai",F23)),"Chennai",IF(ISNUMBER(SEARCH("hyderabad",F23)),"Hyderabad",IF(ISNUMBER(SEARCH("pune",F23)),"Pune",IF(ISNUMBER(SEARCH("kolkata",F23)),"Kolkata",IF(ISNUMBER(SEARCH("ahmedabad",F23)),"Ahmedabad",IF(ISNUMBER(SEARCH("jaipur",F23)),"Jaipur",IF(ISNUMBER(SEARCH("coimbatore",F23)),"Coimbatore",IF(ISNUMBER(SEARCH("kochi",F23)),"Kerala Cities",IF(ISNUMBER(SEARCH("cochin",F23)),"Kerala Cities",IF(ISNUMBER(SEARCH("francisco",F23)),"USA",IF(ISNUMBER(SEARCH("new york",F23)),"USA",IF(ISNUMBER(SEARCH("california",F23)),"USA",IF(ISNUMBER(SEARCH("palo alto",F23)),"USA",IF(ISNUMBER(SEARCH("santa",F23)),"USA",IF(ISNUMBER(SEARCH("singapore",F23)),"Singapore",IF(ISNUMBER(SEARCH("london",F23)),"London/UK",IF(F23="","Unknown","Other Cities"))))))))))))))))))))))))) -> Delhi-NCR
A24: 23 | B24: 43784 | C24: Ninjacart | D24: B2B Marketing | E24: Agritech | F24: Bengaluru | G24: Trifecta Capital Advisors | H24: =IFERROR(TRIM(LEFT(G24,FIND(",",G24)-1)),TRIM(G24)) -> Trifecta Capital Advisors | I24: =IF(TRIM(G24)="",0,LEN(G24)-LEN(SUBSTITUTE(G24,",",""))+1) -> 1 | J24: =IF(Table1[[#This Row],[Investor Count]]>1,"Yes","No") -> No | K24: Debt Funding | L24: 26000000 | M24: =YEAR(B24) -> 2019 | N24: =TEXT(B24,"mmmm") -> November | O24: 249.5233 | P24: =IF(ISBLANK(K24),"Unknown",IF(OR(ISNUMBER(SEARCH("seed",K24)),ISNUMBER(SEARCH("Seed",K24))),"Seed",IF(ISNUMBER(SEARCH("Series A",K24)),"Series A",IF(ISNUMBER(SEARCH("Series B",K24)),"Series B",IF(ISNUMBER(SEARCH("Series C",K24)),"Series C",IF(ISNUMBER(SEARCH("Series D",K24)),"Series D",IF(ISNUMBER(SEARCH("Private Equity",K24)),"Private Equity","Other"))))))) -> Other | Q24: =IF(IFERROR(SEARCH("ecom",D24),0)+IFERROR(SEARCH("commerce",D24),0)+IFERROR(SEARCH("retail",D24),0)>0,"E-Commerce", IF(IFERROR(SEARCH("fintech",D24),0)+IFERROR(SEARCH("finance",D24),0)+IFERROR(SEARCH("financial",D24),0)+IFERROR(SEARCH("lending",D24),0)+IFERROR(SEARCH("payment",D24),0)+IFERROR(SEARCH("banking",D24),0)+IFERROR(SEARCH("insurance",D24),0)>0,"FinTech", IF(IFERROR(SEARCH("tech",D24),0)+IFERROR(SEARCH("software",D24),0)+IFERROR(SEARCH("saas",D24),0)+IFERROR(SEARCH("ai",D24),0)+IFERROR(SEARCH("iot",D24),0)+IFERROR(SEARCH("cloud",D24),0)+IFERROR(SEARCH("data",D24),0)+IFERROR(SEARCH("analytics",D24),0)>0,"Technology", IF(IFERROR(SEARCH("food",D24),0)+IFERROR(SEARCH("restaurant",D24),0)+IFERROR(SEARCH("hospitality",D24),0)+IFERROR(SEARCH("beverage",D24),0)+IFERROR(SEARCH("delivery",D24),0)>0,"Food & Beverage", IF(IFERROR(SEARCH("health",D24),0)+IFERROR(SEARCH("medical",D24),0)+IFERROR(SEARCH("pharma",D24),0)+IFERROR(SEARCH("wellness",D24),0)+IFERROR(SEARCH("fitness",D24),0)>0,"Healthcare", IF(IFERROR(SEARCH("edu",D24),0)+IFERROR(SEARCH("learning",D24),0)+IFERROR(SEARCH("school",D24),0)+IFERROR(SEARCH("e-tech",D24),0)>0,"Education", IF(IFERROR(SEARCH("logistics",D24),0)+IFERROR(SEARCH("transport",D24),0)+IFERROR(SEARCH("delivery",D24),0)+IFERROR(SEARCH("mobility",D24),0)+IFERROR(SEARCH("automobile",D24),0)>0,"Logistics & Transport", IF(IFERROR(SEARCH("travel",D24),0)+IFERROR(SEARCH("hotel",D24),0)+IFERROR(SEARCH("booking",D24),0)+IFERROR(SEARCH("tourism",D24),0)>0,"Travel & Hospitality", IF(IFERROR(SEARCH("fashion",D24),0)+IFERROR(SEARCH("apparel",D24),0)+IFERROR(SEARCH("clothing",D24),0)+IFERROR(SEARCH("jewelry",D24),0)+IFERROR(SEARCH("beauty",D24),0)>0,"Fashion & Lifestyle", IF(IFERROR(SEARCH("media",D24),0)+IFERROR(SEARCH("entertainment",D24),0)+IFERROR(SEARCH("video",D24),0)+IFERROR(SEARCH("gaming",D24),0)+IFERROR(SEARCH("music",D24),0)+IFERROR(SEARCH("social",D24),0)>0,"Media & Entertainment", IF(IFERROR(SEARCH("agri",D24),0)+IFERROR(SEARCH("farm",D24),0)+IFERROR(SEARCH("agtech",D24),0)>0,"Agriculture", IF(IFERROR(SEARCH("real estate",D24),0)+IFERROR(SEARCH("property",D24),0)+IFERROR(SEARCH("housing",D24),0)>0,"Real Estate", IF(IFERROR(SEARCH("energy",D24),0)+IFERROR(SEARCH("solar",D24),0)+IFERROR(SEARCH("clean tech",D24),0)+IFERROR(SEARCH("waste",D24),0)>0,"Energy & Environment", IF(IFERROR(SEARCH("hr",D24),0)+IFERROR(SEARCH("recruit",D24),0)+IFERROR(SEARCH("hiring",D24),0)+IFERROR(SEARCH("job",D24),0)>0,"HR & Recruitment", "Others")))))))))))))) -> Others | R24: =IF(ISNUMBER(SEARCH("bang",F24)),"Bangalore",IF(ISNUMBER(SEARCH("beng",F24)),"Bangalore",IF(ISNUMBER(SEARCH("mumbai",F24)),"Mumbai",IF(ISNUMBER(SEARCH("delhi",F24)),"Delhi-NCR",IF(ISNUMBER(SEARCH("gurgaon",F24)),"Delhi-NCR",IF(ISNUMBER(SEARCH("gurugram",F24)),"Delhi-NCR",IF(ISNUMBER(SEARCH("noida",F24)),"Delhi-NCR",IF(ISNUMBER(SEARCH("faridabad",F24)),"Delhi-NCR",IF(ISNUMBER(SEARCH("chennai",F24)),"Chennai",IF(ISNUMBER(SEARCH("hyderabad",F24)),"Hyderabad",IF(ISNUMBER(SEARCH("pune",F24)),"Pune",IF(ISNUMBER(SEARCH("kolkata",F24)),"Kolkata",IF(ISNUMBER(SEARCH("ahmedabad",F24)),"Ahmedabad",IF(ISNUMBER(SEARCH("jaipur",F24)),"Jaipur",IF(ISNUMBER(SEARCH("coimbatore",F24)),"Coimbatore",IF(ISNUMBER(SEARCH("kochi",F24)),"Kerala Cities",IF(ISNUMBER(SEARCH("cochin",F24)),"Kerala Cities",IF(ISNUMBER(SEARCH("francisco",F24)),"USA",IF(ISNUMBER(SEARCH("new york",F24)),"USA",IF(ISNUMBER(SEARCH("california",F24)),"USA",IF(ISNUMBER(SEARCH("palo alto",F24)),"USA",IF(ISNUMBER(SEARCH("santa",F24)),"USA",IF(ISNUMBER(SEARCH("singapore",F24)),"Singapore",IF(ISNUMBER(SEARCH("london",F24)),"London/UK",IF(F24="","Unknown","Other Cities"))))))))))))))))))))))))) -> Bangalore
A25: 24 | B25: 43789 | C25: Aye Finance | D25: FinTech | E25: Financial Services To MSMEs | F25: Gurgaon | G25: Fintech | H25: =IFERROR(TRIM(LEFT(G25,FIND(",",G25)-1)),TRIM(G25)) -> Fintech | I25: =IF(TRIM(G25)="",0,LEN(G25)-LEN(SUBSTITUTE(G25,",",""))+1) -> 1 | J25: =IF(Table1[[#This Row],[Investor Count]]>1,"Yes","No") -> No | K25: Debt Funding | L25: 17411265 | M25: =YEAR(B25) -> 2019 | N25: =TEXT(B25,"mmmm") -> November | O25: 167.09678 | P25: =IF(ISBLANK(K25),"Unknown",IF(OR(ISNUMBER(SEARCH("seed",K25)),ISNUMBER(SEARCH("Seed",K25))),"Seed",IF(ISNUMBER(SEARCH("Series A",K25)),"Series A",IF(ISNUMBER(SEARCH("Series B",K25)),"Series B",IF(ISNUMBER(SEARCH("Series C",K25)),"Series C",IF(ISNUMBER(SEARCH("Series D",K25)),"Series D",IF(ISNUMBER(SEARCH("Private Equity",K25)),"Private Equity","Other"))))))) -> Other | Q25: =IF(IFERROR(SEARCH("ecom",D25),0)+IFERROR(SEARCH("commerce",D25),0)+IFERROR(SEARCH("retail",D25),0)>0,"E-Commerce", IF(IFERROR(SEARCH("fintech",D25),0)+IFERROR(SEARCH("finance",D25),0)+IFERROR(SEARCH("financial",D25),0)+IFERROR(SEARCH("lending",D25),0)+IFERROR(SEARCH("payment",D25),0)+IFERROR(SEARCH("banking",D25),0)+IFERROR(SEARCH("insurance",D25),0)>0,"FinTech", IF(IFERROR(SEARCH("tech",D25),0)+IFERROR(SEARCH("software",D25),0)+IFERROR(SEARCH("saas",D25),0)+IFERROR(SEARCH("ai",D25),0)+IFERROR(SEARCH("iot",D25),0)+IFERROR(SEARCH("cloud",D25),0)+IFERROR(SEARCH("data",D25),0)+IFERROR(SEARCH("analytics",D25),0)>0,"Technology", IF(IFERROR(SEARCH("food",D25),0)+IFERROR(SEARCH("restaurant",D25),0)+IFERROR(SEARCH("hospitality",D25),0)+IFERROR(SEARCH("beverage",D25),0)+IFERROR(SEARCH("delivery",D25),0)>0,"Food & Beverage", IF(IFERROR(SEARCH("health",D25),0)+IFERROR(SEARCH("medical",D25),0)+IFERROR(SEARCH("pharma",D25),0)+IFERROR(SEARCH("wellness",D25),0)+IFERROR(SEARCH("fitness",D25),0)>0,"Healthcare", IF(IFERROR(SEARCH("edu",D25),0)+IFERROR(SEARCH("learning",D25),0)+IFERROR(SEARCH("school",D25),0)+IFERROR(SEARCH("e-tech",D25),0)>0,"Education", IF(IFERROR(SEARCH("logistics",D25),0)+IFERROR(SEARCH("transport",D25),0)+IFERROR(SEARCH("delivery",D25),0)+IFERROR(SEARCH("mobility",D25),0)+IFERROR(SEARCH("automobile",D25),0)>0,"Logistics & Transport", IF(IFERROR(SEARCH("travel",D25),0)+IFERROR(SEARCH("hotel",D25),0)+IFERROR(SEARCH("booking",D25),0)+IFERROR(SEARCH("tourism",D25),0)>0,"Travel & Hospitality", IF(IFERROR(SEARCH("fashion",D25),0)+IFERROR(SEARCH("apparel",D25),0)+IFERROR(SEARCH("clothing",D25),0)+IFERROR(SEARCH("jewelry",D25),0)+IFERROR(SEARCH("beauty",D25),0)>0,"Fashion & Lifestyle", IF(IFERROR(SEARCH("media",D25),0)+IFERROR(SEARCH("entertainment",D25),0)+IFERROR(SEARCH("video",D25),0)+IFERROR(SEARCH("gaming",D25),0)+IFERROR(SEARCH("music",D25),0)+IFERROR(SEARCH("social",D25),0)>0,"Media & Entertainment", IF(IFERROR(SEARCH("agri",D25),0)+IFERROR(SEARCH("farm",D25),0)+IFERROR(SEARCH("agtech",D25),0)>0,"Agriculture", IF(IFERROR(SEARCH("real estate",D25),0)+IFERROR(SEARCH("property",D25),0)+IFERROR(SEARCH("housing",D25),0)>0,"Real Estate", IF(IFERROR(SEARCH("energy",D25),0)+IFERROR(SEARCH("solar",D25),0)+IFERROR(SEARCH("clean tech",D25),0)+IFERROR(SEARCH("waste",D25),0)>0,"Energy & Environment", IF(IFERROR(SEARCH("hr",D25),0)+IFERROR(SEARCH("recruit",D25),0)+IFERROR(SEARCH("hiring",D25),0)+IFERROR(SEARCH("job",D25),0)>0,"HR & Recruitment", "Others")))))))))))))) -> FinTech | R25: =IF(ISNUMBER(SEARCH("bang",F25)),"Bangalore",IF(ISNUMBER(SEARCH("beng",F25)),"Bangalore",IF(ISNUMBER(SEARCH("mumbai",F25)),"Mumbai",IF(ISNUMBER(SEARCH("delhi",F25)),"Delhi-NCR",IF(ISNUMBER(SEARCH("gurgaon",F25)),"Delhi-NCR",IF(ISNUMBER(SEARCH("gurugram",F25)),"Delhi-NCR",IF(ISNUMBER(SEARCH("noida",F25)),"Delhi-NCR",IF(ISNUMBER(SEARCH("faridabad",F25)),"Delhi-NCR",IF(ISNUMBER(SEARCH("chennai",F25)),"Chennai",IF(ISNUMBER(SEARCH("hyderabad",F25)),"Hyderabad",IF(ISNUMBER(SEARCH("pune",F25)),"Pune",IF(ISNUMBER(SEARCH("kolkata",F25)),"Kolkata",IF(ISNUMBER(SEARCH("ahmedabad",F25)),"Ahmedabad",IF(ISNUMBER(SEARCH("jaipur",F25)),"Jaipur",IF(ISNUMBER(SEARCH("coimbatore",F25)),"Coimbatore",IF(ISNUMBER(SEARCH("kochi",F25)),"Kerala Cities",IF(ISNUMBER(SEARCH("cochin",F25)),"Kerala Cities",IF(ISNUMBER(SEARCH("francisco",F25)),"USA",IF(ISNUMBER(SEARCH("new york",F25)),"USA",IF(ISNUMBER(SEARCH("california",F25)),"USA",IF(ISNUMBER(SEARCH("palo alto",F25)),"USA",IF(ISNUMBER(SEARCH("santa",F25)),"USA",IF(ISNUMBER(SEARCH("singapore",F25)),"Singapore",IF(ISNUMBER(SEARCH("london",F25)),"London/UK",IF(F25="","Unknown","Other Cities"))))))))))))))))))))))))) -> Delhi-NCR
A26: 25 | B26: 43781 | C26: SuperGaming | D26: Video Games | E26: Social gaming platform | F26: Pune | G26: Dream Incubator | H26: =IFERROR(TRIM(LEFT(G26,FIND(",",G26)-1)),TRIM(G26)) -> Dream Incubator | I26: =IF(TRIM(G26)="",0,LEN(G26)-LEN(SUBSTITUTE(G26,",",""))+1) -> 1 | J26: =IF(Table1[[#This Row],[Investor Count]]>1,"Yes","No") -> No | K26: Seed Funding | L26: 1300000 | M26: =YEAR(B26) -> 2019 | N26: =TEXT(B26,"mmmm") -> November | O26: 12.476165 | P26: =IF(ISBLANK(K26),"Unknown",IF(OR(ISNUMBER(SEARCH("seed",K26)),ISNUMBER(SEARCH("Seed",K26))),"Seed",IF(ISNUMBER(SEARCH("Series A",K26)),"Series A",IF(ISNUMBER(SEARCH("Series B",K26)),"Series B",IF(ISNUMBER(SEARCH("Series C",K26)),"Series C",IF(ISNUMBER(SEARCH("Series D",K26)),"Series D",IF(ISNUMBER(SEARCH("Private Equity",K26)),"Private Equity","Other"))))))) -> Seed | Q26: =IF(IFERROR(SEARCH("ecom",D26),0)+IFERROR(SEARCH("commerce",D26),0)+IFERROR(SEARCH("retail",D26),0)>0,"E-Commerce", IF(IFERROR(SEARCH("fintech",D26),0)+IFERROR(SEARCH("finance",D26),0)+IFERROR(SEARCH("financial",D26),0)+IFERROR(SEARCH("lending",D26),0)+IFERROR(SEARCH("payment",D26),0)+IFERROR(SEARCH("banking",D26),0)+IFERROR(SEARCH("insurance",D26),0)>0,"FinTech", IF(IFERROR(SEARCH("tech",D26),0)+IFERROR(SEARCH("software",D26),0)+IFERROR(SEARCH("saas",D26),0)+IFERROR(SEARCH("ai",D26),0)+IFERROR(SEARCH("iot",D26),0)+IFERROR(SEARCH("cloud",D26),0)+IFERROR(SEARCH("data",D26),0)+IFERROR(SEARCH("analytics",D26),0)>0,"Technology", IF(IFERROR(SEARCH("food",D26),0)+IFERROR(SEARCH("restaurant",D26),0)+IFERROR(SEARCH("hospitality",D26),0)+IFERROR(SEARCH("beverage",D26),0)+IFERROR(SEARCH("delivery",D26),0)>0,"Food & Beverage", IF(IFERROR(SEARCH("health",D26),0)+IFERROR(SEARCH("medical",D26),0)+IFERROR(SEARCH("pharma",D26),0)+IFERROR(SEARCH("wellness",D26),0)+IFERROR(SEARCH("fitness",D26),0)>0,"Healthcare", IF(IFERROR(SEARCH("edu",D26),0)+IFERROR(SEARCH("learning",D26),0)+IFERROR(SEARCH("school",D26),0)+IFERROR(SEARCH("e-tech",D26),0)>0,"Education", IF(IFERROR(SEARCH("logistics",D26),0)+IFERROR(SEARCH("transport",D26),0)+IFERROR(SEARCH("delivery",D26),0)+IFERROR(SEARCH("mobility",D26),0)+IFERROR(SEARCH("automobile",D26),0)>0,"Logistics & Transport", IF(IFERROR(SEARCH("travel",D26),0)+IFERROR(SEARCH("hotel",D26),0)+IFERROR(SEARCH("booking",D26),0)+IFERROR(SEARCH("tourism",D26),0)>0,"Travel & Hospitality", IF(IFERROR(SEARCH("fashion",D26),0)+IFERROR(SEARCH("apparel",D26),0)+IFERROR(SEARCH("clothing",D26),0)+IFERROR(SEARCH("jewelry",D26),0)+IFERROR(SEARCH("beauty",D26),0)>0,"Fashion & Lifestyle", IF(IFERROR(SEARCH("media",D26),0)+IFERROR(SEARCH("entertainment",D26),0)+IFERROR(SEARCH("video",D26),0)+IFERROR(SEARCH("gaming",D26),0)+IFERROR(SEARCH("music",D26),0)+IFERROR(SEARCH("social",D26),0)>0,"Media & Entertainment", IF(IFERROR(SEARCH("agri",D26),0)+IFERROR(SEARCH("farm",D26),0)+IFERROR(SEARCH("agtech",D26),0)>0,"Agriculture", IF(IFERROR(SEARCH("real estate",D26),0)+IFERROR(SEARCH("property",D26),0)+IFERROR(SEARCH("housing",D26),0)>0,"Real Estate", IF(IFERROR(SEARCH("energy",D26),0)+IFERROR(SEARCH("solar",D26),0)+IFERROR(SEARCH("clean tech",D26),0)+IFERROR(SEARCH("waste",D26),0)>0,"Energy & Environment", IF(IFERROR(SEARCH("hr",D26),0)+IFERROR(SEARCH("recruit",D26),0)+IFERROR(SEARCH("hiring",D26),0)+IFERROR(SEARCH("job",D26),0)>0,"HR & Recruitment", "Others")))))))))))))) -> Media & Entertainment | R26: =IF(ISNUMBER(SEARCH("bang",F26)),"Bangalore",IF(ISNUMBER(SEARCH("beng",F26)),"Bangalore",IF(ISNUMBER(SEARCH("mumbai",F26)),"Mumbai",IF(ISNUMBER(SEARCH("delhi",F26)),"Delhi-NCR",IF(ISNUMBER(SEARCH("gurgaon",F26)),"Delhi-NCR",IF(ISNUMBER(SEARCH("gurugram",F26)),"Delhi-NCR",IF(ISNUMBER(SEARCH("noida",F26)),"Delhi-NCR",IF(ISNUMBER(SEARCH("faridabad",F26)),"Delhi-NCR",IF(ISNUMBER(SEARCH("chennai",F26)),"Chennai",IF(ISNUMBER(SEARCH("hyderabad",F26)),"Hyderabad",IF(ISNUMBER(SEARCH("pune",F26)),"Pune",IF(ISNUMBER(SEARCH("kolkata",F26)),"Kolkata",IF(ISNUMBER(SEARCH("ahmedabad",F26)),"Ahmedabad",IF(ISNUMBER(SEARCH("jaipur",F26)),"Jaipur",IF(ISNUMBER(SEARCH("coimbatore",F26)),"Coimbatore",IF(ISNUMBER(SEARCH("kochi",F26)),"Kerala Cities",IF(ISNUMBER(SEARCH("cochin",F26)),"Kerala Cities",IF(ISNUMBER(SEARCH("francisco",F26)),"USA",IF(ISNUMBER(SEARCH("new york",F26)),"USA",IF(ISNUMBER(SEARCH("california",F26)),"USA",IF(ISNUMBER(SEARCH("palo alto",F26)),"USA",IF(ISNUMBER(SEARCH("santa",F26)),"USA",IF(ISNUMBER(SEARCH("singapore",F26)),"Singapore",IF(ISNUMBER(SEARCH("london",F26)),"London/UK",IF(F26="","Unknown","Other Cities"))))))))))))))))))))))))) -> Pune
A27: 26 | B27: 43789 | C27: Clumio | D27: SaaS | E27: Recovery software | F27: San Jose | G27: Altimeter Capital, Sutter Hill Ventures | H27: =IFERROR(TRIM(LEFT(G27,FIND(",",G27)-1)),TRIM(G27)) -> Altimeter Capital | I27: =IF(TRIM(G27)="",0,LEN(G27)-LEN(SUBSTITUTE(G27,",",""))+1) -> 2 | J27: =IF(Table1[[#This Row],[Investor Count]]>1,"Yes","No") -> Yes | K27: Series C | L27: 135000000 | M27: =YEAR(B27) -> 2019 | N27: =TEXT(B27,"mmmm") -> November | O27: 1295.6018 | P27: =IF(ISBLANK(K27),"Unknown",IF(OR(ISNUMBER(SEARCH("seed",K27)),ISNUMBER(SEARCH("Seed",K27))),"Seed",IF(ISNUMBER(SEARCH("Series A",K27)),"Series A",IF(ISNUMBER(SEARCH("Series B",K27)),"Series B",IF(ISNUMBER(SEARCH("Series C",K27)),"Series C",IF(ISNUMBER(SEARCH("Series D",K27)),"Series D",IF(ISNUMBER(SEARCH("Private Equity",K27)),"Private Equity","Other"))))))) -> Series C | Q27: =IF(IFERROR(SEARCH("ecom",D27),0)+IFERROR(SEARCH("commerce",D27),0)+IFERROR(SEARCH("retail",D27),0)>0,"E-Commerce", IF(IFERROR(SEARCH("fintech",D27),0)+IFERROR(SEARCH("finance",D27),0)+IFERROR(SEARCH("financial",D27),0)+IFERROR(SEARCH("lending",D27),0)+IFERROR(SEARCH("payment",D27),0)+IFERROR(SEARCH("banking",D27),0)+IFERROR(SEARCH("insurance",D27),0)>0,"FinTech", IF(IFERROR(SEARCH("tech",D27),0)+IFERROR(SEARCH("software",D27),0)+IFERROR(SEARCH("saas",D27),0)+IFERROR(SEARCH("ai",D27),0)+IFERROR(SEARCH("iot",D27),0)+IFERROR(SEARCH("cloud",D27),0)+IFERROR(SEARCH("data",D27),0)+IFERROR(SEARCH("analytics",D27),0)>0,"Technology", IF(IFERROR(SEARCH("food",D27),0)+IFERROR(SEARCH("restaurant",D27),0)+IFERROR(SEARCH("hospitality",D27),0)+IFERROR(SEARCH("beverage",D27),0)+IFERROR(SEARCH("delivery",D27),0)>0,"Food & Beverage", IF(IFERROR(SEARCH("health",D27),0)+IFERROR(SEARCH("medical",D27),0)+IFERROR(SEARCH("pharma",D27),0)+IFERROR(SEARCH("wellness",D27),0)+IFERROR(SEARCH("fitness",D27),0)>0,"Healthcare", IF(IFERROR(SEARCH("edu",D27),0)+IFERROR(SEARCH("learning",D27),0)+IFERROR(SEARCH("school",D27),0)+IFERROR(SEARCH("e-tech",D27),0)>0,"Education", IF(IFERROR(SEARCH("logistics",D27),0)+IFERROR(SEARCH("transport",D27),0)+IFERROR(SEARCH("delivery",D27),0)+IFERROR(SEARCH("mobility",D27),0)+IFERROR(SEARCH("automobile",D27),0)>0,"Logistics & Transport", IF(IFERROR(SEARCH("travel",D27),0)+IFERROR(SEARCH("hotel",D27),0)+IFERROR(SEARCH("booking",D27),0)+IFERROR(SEARCH("tourism",D27),0)>0,"Travel & Hospitality", IF(IFERROR(SEARCH("fashion",D27),0)+IFERROR(SEARCH("apparel",D27),0)+IFERROR(SEARCH("clothing",D27),0)+IFERROR(SEARCH("jewelry",D27),0)+IFERROR(SEARCH("beauty",D27),0)>0,"Fashion & Lifestyle", IF(IFERROR(SEARCH("media",D27),0)+IFERROR(SEARCH("entertainment",D27),0)+IFERROR(SEARCH("video",D27),0)+IFERROR(SEARCH("gaming",D27),0)+IFERROR(SEARCH("music",D27),0)+IFERROR(SEARCH("social",D27),0)>0,"Media & Entertainment", IF(IFERROR(SEARCH("agri",D27),0)+IFERROR(SEARCH("farm",D27),0)+IFERROR(SEARCH("agtech",D27),0)>0,"Agriculture", IF(IFERROR(SEARCH("real estate",D27),0)+IFERROR(SEARCH("property",D27),0)+IFERROR(SEARCH("housing",D27),0)>0,"Real Estate", IF(IFERROR(SEARCH("energy",D27),0)+IFERROR(SEARCH("solar",D27),0)+IFERROR(SEARCH("clean tech",D27),0)+IFERROR(SEARCH("waste",D27),0)>0,"Energy & Environment", IF(IFERROR(SEARCH("hr",D27),0)+IFERROR(SEARCH("recruit",D27),0)+IFERROR(SEARCH("hiring",D27),0)+IFERROR(SEARCH("job",D27),0)>0,"HR & Recruitment", "Others")))))))))))))) -> Technology | R27: =IF(ISNUMBER(SEARCH("bang",F27)),"Bangalore",IF(ISNUMBER(SEARCH("beng",F27)),"Bangalore",IF(ISNUMBER(SEARCH("mumbai",F27)),"Mumbai",IF(ISNUMBER(SEARCH("delhi",F27)),"Delhi-NCR",IF(ISNUMBER(SEARCH("gurgaon",F27)),"Delhi-NCR",IF(ISNUMBER(SEARCH("gurugram",F27)),"Delhi-NCR",IF(ISNUMBER(SEARCH("noida",F27)),"Delhi-NCR",IF(ISNUMBER(SEARCH("faridabad",F27)),"Delhi-NCR",IF(ISNUMBER(SEARCH("chennai",F27)),"Chennai",IF(ISNUMBER(SEARCH("hyderabad",F27)),"Hyderabad",IF(ISNUMBER(SEARCH("pune",F27)),"Pune",IF(ISNUMBER(SEARCH("kolkata",F27)),"Kolkata",IF(ISNUMBER(SEARCH("ahmedabad",F27)),"Ahmedabad",IF(ISNUMBER(SEARCH("jaipur",F27)),"Jaipur",IF(ISNUMBER(SEARCH("coimbatore",F27)),"Coimbatore",IF(ISNUMBER(SEARCH("kochi",F27)),"Kerala Cities",IF(ISNUMBER(SEARCH("cochin",F27)),"Kerala Cities",IF(ISNUMBER(SEARCH("francisco",F27)),"USA",IF(ISNUMBER(SEARCH("new york",F27)),"USA",IF(ISNUMBER(SEARCH("california",F27)),"USA",IF(ISNUMBER(SEARCH("palo alto",F27)),"USA",IF(ISNUMBER(SEARCH("santa",F27)),"USA",IF(ISNUMBER(SEARCH("singapore",F27)),"Singapore",IF(ISNUMBER(SEARCH("london",F27)),"London/UK",IF(F27="","Unknown","Other Cities"))))))))))))))))))))))))) -> Other Cities
A28: 27 | B28: 43780 | C28: eBikeGo | D28: Last Mile Transportation | E28: Electric bike rental | F28: Amritsar | G28: Startup Buddy | H28: =IFERROR(TRIM(LEFT(G28,FIND(",",G28)-1)),TRIM(G28)) -> Startup Buddy | I28: =IF(TRIM(G28)="",0,LEN(G28)-LEN(SUBSTITUTE(G28,",",""))+1) -> 1 | J28: =IF(Table1[[#This Row],[Investor Count]]>1,"Yes","No") -> No | K28: Seed | L28: 300000 | M28: =YEAR(B28) -> 2019 | N28: =TEXT(B28,"mmmm") -> November | O28: 2.879115 | P28: =IF(ISBLANK(K28),"Unknown",IF(OR(ISNUMBER(SEARCH("seed",K28)),ISNUMBER(SEARCH("Seed",K28))),"Seed",IF(ISNUMBER(SEARCH("Series A",K28)),"Series A",IF(ISNUMBER(SEARCH("Series B",K28)),"Series B",IF(ISNUMBER(SEARCH("Series C",K28)),"Series C",IF(ISNUMBER(SEARCH("Series D",K28)),"Series D",IF(ISNUMBER(SEARCH("Private Equity",K28)),"Private Equity","Other"))))))) -> Seed | Q28: =IF(IFERROR(SEARCH("ecom",D28),0)+IFERROR(SEARCH("commerce",D28),0)+IFERROR(SEARCH("retail",D28),0)>0,"E-Commerce", IF(IFERROR(SEARCH("fintech",D28),0)+IFERROR(SEARCH("finance",D28),0)+IFERROR(SEARCH("financial",D28),0)+IFERROR(SEARCH("lending",D28),0)+IFERROR(SEARCH("payment",D28),0)+IFERROR(SEARCH("banking",D28),0)+IFERROR(SEARCH("insurance",D28),0)>0,"FinTech", IF(IFERROR(SEARCH("tech",D28),0)+IFERROR(SEARCH("software",D28),0)+IFERROR(SEARCH("saas",D28),0)+IFERROR(SEARCH("ai",D28),0)+IFERROR(SEARCH("iot",D28),0)+IFERROR(SEARCH("cloud",D28),0)+IFERROR(SEARCH("data",D28),0)+IFERROR(SEARCH("analytics",D28),0)>0,"Technology", IF(IFERROR(SEARCH("food",D28),0)+IFERROR(SEARCH("restaurant",D28),0)+IFERROR(SEARCH("hospitality",D28),0)+IFERROR(SEARCH("beverage",D28),0)+IFERROR(SEARCH("delivery",D28),0)>0,"Food & Beverage", IF(IFERROR(SEARCH("health",D28),0)+IFERROR(SEARCH("medical",D28),0)+IFERROR(SEARCH("pharma",D28),0)+IFERROR(SEARCH("wellness",D28),0)+IFERROR(SEARCH("fitness",D28),0)>0,"Healthcare", IF(IFERROR(SEARCH("edu",D28),0)+IFERROR(SEARCH("learning",D28),0)+IFERROR(SEARCH("school",D28),0)+IFERROR(SEARCH("e-tech",D28),0)>0,"Education", IF(IFERROR(SEARCH("logistics",D28),0)+IFERROR(SEARCH("transport",D28),0)+IFERROR(SEARCH("delivery",D28),0)+IFERROR(SEARCH("mobility",D28),0)+IFERROR(SEARCH("automobile",D28),0)>0,"Logistics & Transport", IF(IFERROR(SEARCH("travel",D28),0)+IFERROR(SEARCH("hotel",D28),0)+IFERROR(SEARCH("booking",D28),0)+IFERROR(SEARCH("tourism",D28),0)>0,"Travel & Hospitality", IF(IFERROR(SEARCH("fashion",D28),0)+IFERROR(SEARCH("apparel",D28),0)+IFERROR(SEARCH("clothing",D28),0)+IFERROR(SEARCH("jewelry",D28),0)+IFERROR(SEARCH("beauty",D28),0)>0,"Fashion & Lifestyle", IF(IFERROR(SEARCH("media",D28),0)+IFERROR(SEARCH("entertainment",D28),0)+IFERROR(SEARCH("video",D28),0)+IFERROR(SEARCH("gaming",D28),0)+IFERROR(SEARCH("music",D28),0)+IFERROR(SEARCH("social",D28),0)>0,"Media & Entertainment", IF(IFERROR(SEARCH("agri",D28),0)+IFERROR(SEARCH("farm",D28),0)+IFERROR(SEARCH("agtech",D28),0)>0,"Agriculture", IF(IFERROR(SEARCH("real estate",D28),0)+IFERROR(SEARCH("property",D28),0)+IFERROR(SEARCH("housing",D28),0)>0,"Real Estate", IF(IFERROR(SEARCH("energy",D28),0)+IFERROR(SEARCH("solar",D28),0)+IFERROR(SEARCH("clean tech",D28),0)+IFERROR(SEARCH("waste",D28),0)>0,"Energy & Environment", IF(IFERROR(SEARCH("hr",D28),0)+IFERROR(SEARCH("recruit",D28),0)+IFERROR(SEARCH("hiring",D28),0)+IFERROR(SEARCH("job",D28),0)>0,"HR & Recruitment", "Others")))))))))))))) -> Logistics & Transport | R28: =IF(ISNUMBER(SEARCH("bang",F28)),"Bangalore",IF(ISNUMBER(SEARCH("beng",F28)),"Bangalore",IF(ISNUMBER(SEARCH("mumbai",F28)),"Mumbai",IF(ISNUMBER(SEARCH("delhi",F28)),"Delhi-NCR",IF(ISNUMBER(SEARCH("gurgaon",F28)),"Delhi-NCR",IF(ISNUMBER(SEARCH("gurugram",F28)),"Delhi-NCR",IF(ISNUMBER(SEARCH("noida",F28)),"Delhi-NCR",IF(ISNUMBER(SEARCH("faridabad",F28)),"Delhi-NCR",IF(ISNUMBER(SEARCH("chennai",F28)),"Chennai",IF(ISNUMBER(SEARCH("hyderabad",F28)),"Hyderabad",IF(ISNUMBER(SEARCH("pune",F28)),"Pune",IF(ISNUMBER(SEARCH("kolkata",F28)),"Kolkata",IF(ISNUMBER(SEARCH("ahmedabad",F28)),"Ahmedabad",IF(ISNUMBER(SEARCH("jaipur",F28)),"Jaipur",IF(ISNUMBER(SEARCH("coimbatore",F28)),"Coimbatore",IF(ISNUMBER(SEARCH("kochi",F28)),"Kerala Cities",IF(ISNUMBER(SEARCH("cochin",F28)),"Kerala Cities",IF(ISNUMBER(SEARCH("francisco",F28)),"USA",IF(ISNUMBER(SEARCH("new york",F28)),"USA",IF(ISNUMBER(SEARCH("california",F28)),"USA",IF(ISNUMBER(SEARCH("palo alto",F28)),"USA",IF(ISNUMBER(SEARCH("santa",F28)),"USA",IF(ISNUMBER(SEARCH("singapore",F28)),"Singapore",IF(ISNUMBER(SEARCH("london",F28)),"London/UK",IF(F28="","Unknown","Other Cities"))))))))))))))))))))))))) -> Other Cities
A29: 28 | B29: 43788 | C29: Digital Mall Asia | D29: Ecommerce | E29: Virtual e-commerce platform | F29: Delhi | G29: Amour Infrastructure | H29: =IFERROR(TRIM(LEFT(G29,FIND(",",G29)-1)),TRIM(G29)) -> Amour Infrastructure | I29: =IF(TRIM(G29)="",0,LEN(G29)-LEN(SUBSTITUTE(G29,",",""))+1) -> 1 | J29: =IF(Table1[[#This Row],[Investor Count]]>1,"Yes","No") -> No | K29: Seed Funding | L29: 220000000 | M29: =YEAR(B29) -> 2019 | N29: =TEXT(B29,"mmmm") -> November | O29: 2111.351 | P29: =IF(ISBLANK(K29),"Unknown",IF(OR(ISNUMBER(SEARCH("seed",K29)),ISNUMBER(SEARCH("Seed",K29))),"Seed",IF(ISNUMBER(SEARCH("Series A",K29)),"Series A",IF(ISNUMBER(SEARCH("Series B",K29)),"Series B",IF(ISNUMBER(SEARCH("Series C",K29)),"Series C",IF(ISNUMBER(SEARCH("Series D",K29)),"Series D",IF(ISNUMBER(SEARCH("Private Equity",K29)),"Private Equity","Other"))))))) -> Seed | Q29: =IF(IFERROR(SEARCH("ecom",D29),0)+IFERROR(SEARCH("commerce",D29),0)+IFERROR(SEARCH("retail",D29),0)>0,"E-Commerce", IF(IFERROR(SEARCH("fintech",D29),0)+IFERROR(SEARCH("finance",D29),0)+IFERROR(SEARCH("financial",D29),0)+IFERROR(SEARCH("lending",D29),0)+IFERROR(SEARCH("payment",D29),0)+IFERROR(SEARCH("banking",D29),0)+IFERROR(SEARCH("insurance",D29),0)>0,"FinTech", IF(IFERROR(SEARCH("tech",D29),0)+IFERROR(SEARCH("software",D29),0)+IFERROR(SEARCH("saas",D29),0)+IFERROR(SEARCH("ai",D29),0)+IFERROR(SEARCH("iot",D29),0)+IFERROR(SEARCH("cloud",D29),0)+IFERROR(SEARCH("data",D29),0)+IFERROR(SEARCH("analytics",D29),0)>0,"Technology", IF(IFERROR(SEARCH("food",D29),0)+IFERROR(SEARCH("restaurant",D29),0)+IFERROR(SEARCH("hospitality",D29),0)+IFERROR(SEARCH("beverage",D29),0)+IFERROR(SEARCH("delivery",D29),0)>0,"Food & Beverage", IF(IFERROR(SEARCH("health",D29),0)+IFERROR(SEARCH("medical",D29),0)+IFERROR(SEARCH("pharma",D29),0)+IFERROR(SEARCH("wellness",D29),0)+IFERROR(SEARCH("fitness",D29),0)>0,"Healthcare", IF(IFERROR(SEARCH("edu",D29),0)+IFERROR(SEARCH("learning",D29),0)+IFERROR(SEARCH("school",D29),0)+IFERROR(SEARCH("e-tech",D29),0)>0,"Education", IF(IFERROR(SEARCH("logistics",D29),0)+IFERROR(SEARCH("transport",D29),0)+IFERROR(SEARCH("delivery",D29),0)+IFERROR(SEARCH("mobility",D29),0)+IFERROR(SEARCH("automobile",D29),0)>0,"Logistics & Transport", IF(IFERROR(SEARCH("travel",D29),0)+IFERROR(SEARCH("hotel",D29),0)+IFERROR(SEARCH("booking",D29),0)+IFERROR(SEARCH("tourism",D29),0)>0,"Travel & Hospitality", IF(IFERROR(SEARCH("fashion",D29),0)+IFERROR(SEARCH("apparel",D29),0)+IFERROR(SEARCH("clothing",D29),0)+IFERROR(SEARCH("jewelry",D29),0)+IFERROR(SEARCH("beauty",D29),0)>0,"Fashion & Lifestyle", IF(IFERROR(SEARCH("media",D29),0)+IFERROR(SEARCH("entertainment",D29),0)+IFERROR(SEARCH("video",D29),0)+IFERROR(SEARCH("gaming",D29),0)+IFERROR(SEARCH("music",D29),0)+IFERROR(SEARCH("social",D29),0)>0,"Media & Entertainment", IF(IFERROR(SEARCH("agri",D29),0)+IFERROR(SEARCH("farm",D29),0)+IFERROR(SEARCH("agtech",D29),0)>0,"Agriculture", IF(IFERROR(SEARCH("real estate",D29),0)+IFERROR(SEARCH("property",D29),0)+IFERROR(SEARCH("housing",D29),0)>0,"Real Estate", IF(IFERROR(SEARCH("energy",D29),0)+IFERROR(SEARCH("solar",D29),0)+IFERROR(SEARCH("clean tech",D29),0)+IFERROR(SEARCH("waste",D29),0)>0,"Energy & Environment", IF(IFERROR(SEARCH("hr",D29),0)+IFERROR(SEARCH("recruit",D29),0)+IFERROR(SEARCH("hiring",D29),0)+IFERROR(SEARCH("job",D29),0)>0,"HR & Recruitment", "Others")))))))))))))) -> E-Commerce | R29: =IF(ISNUMBER(SEARCH("bang",F29)),"Bangalore",IF(ISNUMBER(SEARCH("beng",F29)),"Bangalore",IF(ISNUMBER(SEARCH("mumbai",F29)),"Mumbai",IF(ISNUMBER(SEARCH("delhi",F29)),"Delhi-NCR",IF(ISNUMBER(SEARCH("gurgaon",F29)),"Delhi-NCR",IF(ISNUMBER(SEARCH("gurugram",F29)),"Delhi-NCR",IF(ISNUMBER(SEARCH("noida",F29)),"Delhi-NCR",IF(ISNUMBER(SEARCH("faridabad",F29)),"Delhi-NCR",IF(ISNUMBER(SEARCH("chennai",F29)),"Chennai",IF(ISNUMBER(SEARCH("hyderabad",F29)),"Hyderabad",IF(ISNUMBER(SEARCH("pune",F29)),"Pune",IF(ISNUMBER(SEARCH("kolkata",F29)),"Kolkata",IF(ISNUMBER(SEARCH("ahmedabad",F29)),"Ahmedabad",IF(ISNUMBER(SEARCH("jaipur",F29)),"Jaipur",IF(ISNUMBER(SEARCH("coimbatore",F29)),"Coimbatore",IF(ISNUMBER(SEARCH("kochi",F29)),"Kerala Cities",IF(ISNUMBER(SEARCH("cochin",F29)),"Kerala Cities",IF(ISNUMBER(SEARCH("francisco",F29)),"USA",IF(ISNUMBER(SEARCH("new york",F29)),"USA",IF(ISNUMBER(SEARCH("california",F29)),"USA",IF(ISNUMBER(SEARCH("palo alto",F29)),"USA",IF(ISNUMBER(SEARCH("santa",F29)),"USA",IF(ISNUMBER(SEARCH("singapore",F29)),"Singapore",IF(ISNUMBER(SEARCH("london",F29)),"London/UK",IF(F29="","Unknown","Other Cities"))))))))))))))))))))))))) -> Delhi-NCR
A30: 29 | B30: 43787 | C30: Medikabazaar | D30: Healthcare | E30: B2B platform for medical supplies | F30: Mumbai | G30: Ackermans & Van Haaren, Healthquad, Rebright Partners, Toppan Printing | H30: =IFERROR(TRIM(LEFT(G30,FIND(",",G30)-1)),TRIM(G30)) -> Ackermans & Van Haaren | I30: =IF(TRIM(G30)="",0,LEN(G30)-LEN(SUBSTITUTE(G30,",",""))+1) -> 4 | J30: =IF(Table1[[#This Row],[Investor Count]]>1,"Yes","No") -> Yes | K30: Series B | L30: 15800000 | M30: =YEAR(B30) -> 2019 | N30: =TEXT(B30,"mmmm") -> November | O30: 151.63339 | P30: =IF(ISBLANK(K30),"Unknown",IF(OR(ISNUMBER(SEARCH("seed",K30)),ISNUMBER(SEARCH("Seed",K30))),"Seed",IF(ISNUMBER(SEARCH("Series A",K30)),"Series A",IF(ISNUMBER(SEARCH("Series B",K30)),"Series B",IF(ISNUMBER(SEARCH("Series C",K30)),"Series C",IF(ISNUMBER(SEARCH("Series D",K30)),"Series D",IF(ISNUMBER(SEARCH("Private Equity",K30)),"Private Equity","Other"))))))) -> Series B | Q30: =IF(IFERROR(SEARCH("ecom",D30),0)+IFERROR(SEARCH("commerce",D30),0)+IFERROR(SEARCH("retail",D30),0)>0,"E-Commerce", IF(IFERROR(SEARCH("fintech",D30),0)+IFERROR(SEARCH("finance",D30),0)+IFERROR(SEARCH("financial",D30),0)+IFERROR(SEARCH("lending",D30),0)+IFERROR(SEARCH("payment",D30),0)+IFERROR(SEARCH("banking",D30),0)+IFERROR(SEARCH("insurance",D30),0)>0,"FinTech", IF(IFERROR(SEARCH("tech",D30),0)+IFERROR(SEARCH("software",D30),0)+IFERROR(SEARCH("saas",D30),0)+IFERROR(SEARCH("ai",D30),0)+IFERROR(SEARCH("iot",D30),0)+IFERROR(SEARCH("cloud",D30),0)+IFERROR(SEARCH("data",D30),0)+IFERROR(SEARCH("analytics",D30),0)>0,"Technology", IF(IFERROR(SEARCH("food",D30),0)+IFERROR(SEARCH("restaurant",D30),0)+IFERROR(SEARCH("hospitality",D30),0)+IFERROR(SEARCH("beverage",D30),0)+IFERROR(SEARCH("delivery",D30),0)>0,"Food & Beverage", IF(IFERROR(SEARCH("health",D30),0)+IFERROR(SEARCH("medical",D30),0)+IFERROR(SEARCH("pharma",D30),0)+IFERROR(SEARCH("wellness",D30),0)+IFERROR(SEARCH("fitness",D30),0)>0,"Healthcare", IF(IFERROR(SEARCH("edu",D30),0)+IFERROR(SEARCH("learning",D30),0)+IFERROR(SEARCH("school",D30),0)+IFERROR(SEARCH("e-tech",D30),0)>0,"Education", IF(IFERROR(SEARCH("logistics",D30),0)+IFERROR(SEARCH("transport",D30),0)+IFERROR(SEARCH("delivery",D30),0)+IFERROR(SEARCH("mobility",D30),0)+IFERROR(SEARCH("automobile",D30),0)>0,"Logistics & Transport", IF(IFERROR(SEARCH("travel",D30),0)+IFERROR(SEARCH("hotel",D30),0)+IFERROR(SEARCH("booking",D30),0)+IFERROR(SEARCH("tourism",D30),0)>0,"Travel & Hospitality", IF(IFERROR(SEARCH("fashion",D30),0)+IFERROR(SEARCH("apparel",D30),0)+IFERROR(SEARCH("clothing",D30),0)+IFERROR(SEARCH("jewelry",D30),0)+IFERROR(SEARCH("beauty",D30),0)>0,"Fashion & Lifestyle", IF(IFERROR(SEARCH("media",D30),0)+IFERROR(SEARCH("entertainment",D30),0)+IFERROR(SEARCH("video",D30),0)+IFERROR(SEARCH("gaming",D30),0)+IFERROR(SEARCH("music",D30),0)+IFERROR(SEARCH("social",D30),0)>0,"Media & Entertainment", IF(IFERROR(SEARCH("agri",D30),0)+IFERROR(SEARCH("farm",D30),0)+IFERROR(SEARCH("agtech",D30),0)>0,"Agriculture", IF(IFERROR(SEARCH("real estate",D30),0)+IFERROR(SEARCH("property",D30),0)+IFERROR(SEARCH("housing",D30),0)>0,"Real Estate", IF(IFERROR(SEARCH("energy",D30),0)+IFERROR(SEARCH("solar",D30),0)+IFERROR(SEARCH("clean tech",D30),0)+IFERROR(SEARCH("waste",D30),0)>0,"Energy & Environment", IF(IFERROR(SEARCH("hr",D30),0)+IFERROR(SEARCH("recruit",D30),0)+IFERROR(SEARCH("hiring",D30),0)+IFERROR(SEARCH("job",D30),0)>0,"HR & Recruitment", "Others")))))))))))))) -> Healthcare | R30: =IF(ISNUMBER(SEARCH("bang",F30)),"Bangalore",IF(ISNUMBER(SEARCH("beng",F30)),"Bangalore",IF(ISNUMBER(SEARCH("mumbai",F30)),"Mumbai",IF(ISNUMBER(SEARCH("delhi",F30)),"Delhi-NCR",IF(ISNUMBER(SEARCH("gurgaon",F30)),"Delhi-NCR",IF(ISNUMBER(SEARCH("gurugram",F30)),"Delhi-NCR",IF(ISNUMBER(SEARCH("noida",F30)),"Delhi-NCR",IF(ISNUMBER(SEARCH("faridabad",F30)),"Delhi-NCR",IF(ISNUMBER(SEARCH("chennai",F30)),"Chennai",IF(ISNUMBER(SEARCH("hyderabad",F30)),"Hyderabad",IF(ISNUMBER(SEARCH("pune",F30)),"Pune",IF(ISNUMBER(SEARCH("kolkata",F30)),"Kolkata",IF(ISNUMBER(SEARCH("ahmedabad",F30)),"Ahmedabad",IF(ISNUMBER(SEARCH("jaipur",F30)),"Jaipur",IF(ISNUMBER(SEARCH("coimbatore",F30)),"Coimbatore",IF(ISNUMBER(SEARCH("kochi",F30)),"Kerala Cities",IF(ISNUMBER(SEARCH("cochin",F30)),"Kerala Cities",IF(ISNUMBER(SEARCH("francisco",F30)),"USA",IF(ISNUMBER(SEARCH("new york",F30)),"USA",IF(ISNUMBER(SEARCH("california",F30)),"USA",IF(ISNUMBER(SEARCH("palo alto",F30)),"USA",IF(ISNUMBER(SEARCH("santa",F30)),"USA",IF(ISNUMBER(SEARCH("singapore",F30)),"Singapore",IF(ISNUMBER(SEARCH("london",F30)),"London/UK",IF(F30="","Unknown","Other Cities"))))))))))))))))))))))))) -> Mumbai
A31: 30 | B31: 43784 | C31: Vogo Automotive | D31: Last Mile Transportation | E31: Scooter sharing app | F31: Kormangala | G31: Matrix Partners, Stellaris Venture Partners, Kalaari Capital | H31: =IFERROR(TRIM(LEFT(G31,FIND(",",G31)-1)),TRIM(G31)) -> Matrix Partners | I31: =IF(TRIM(G31)="",0,LEN(G31)-LEN(SUBSTITUTE(G31,",",""))+1) -> 3 | J31: =IF(Table1[[#This Row],[Investor Count]]>1,"Yes","No") -> Yes | K31: Series B | L31: 283000000 | M31: =YEAR(B31) -> 2019 | N31: =TEXT(B31,"mmmm") -> November | O31: 2715.9651 | P31: =IF(ISBLANK(K31),"Unknown",IF(OR(ISNUMBER(SEARCH("seed",K31)),ISNUMBER(SEARCH("Seed",K31))),"Seed",IF(ISNUMBER(SEARCH("Series A",K31)),"Series A",IF(ISNUMBER(SEARCH("Series B",K31)),"Series B",IF(ISNUMBER(SEARCH("Series C",K31)),"Series C",IF(ISNUMBER(SEARCH("Series D",K31)),"Series D",IF(ISNUMBER(SEARCH("Private Equity",K31)),"Private Equity","Other"))))))) -> Series B | Q31: =IF(IFERROR(SEARCH("ecom",D31),0)+IFERROR(SEARCH("commerce",D31),0)+IFERROR(SEARCH("retail",D31),0)>0,"E-Commerce", IF(IFERROR(SEARCH("fintech",D31),0)+IFERROR(SEARCH("finance",D31),0)+IFERROR(SEARCH("financial",D31),0)+IFERROR(SEARCH("lending",D31),0)+IFERROR(SEARCH("payment",D31),0)+IFERROR(SEARCH("banking",D31),0)+IFERROR(SEARCH("insurance",D31),0)>0,"FinTech", IF(IFERROR(SEARCH("tech",D31),0)+IFERROR(SEARCH("software",D31),0)+IFERROR(SEARCH("saas",D31),0)+IFERROR(SEARCH("ai",D31),0)+IFERROR(SEARCH("iot",D31),0)+IFERROR(SEARCH("cloud",D31),0)+IFERROR(SEARCH("data",D31),0)+IFERROR(SEARCH("analytics",D31),0)>0,"Technology", IF(IFERROR(SEARCH("food",D31),0)+IFERROR(SEARCH("restaurant",D31),0)+IFERROR(SEARCH("hospitality",D31),0)+IFERROR(SEARCH("beverage",D31),0)+IFERROR(SEARCH("delivery",D31),0)>0,"Food & Beverage", IF(IFERROR(SEARCH("health",D31),0)+IFERROR(SEARCH("medical",D31),0)+IFERROR(SEARCH("pharma",D31),0)+IFERROR(SEARCH("wellness",D31),0)+IFERROR(SEARCH("fitness",D31),0)>0,"Healthcare", IF(IFERROR(SEARCH("edu",D31),0)+IFERROR(SEARCH("learning",D31),0)+IFERROR(SEARCH("school",D31),0)+IFERROR(SEARCH("e-tech",D31),0)>0,"Education", IF(IFERROR(SEARCH("logistics",D31),0)+IFERROR(SEARCH("transport",D31),0)+IFERROR(SEARCH("delivery",D31),0)+IFERROR(SEARCH("mobility",D31),0)+IFERROR(SEARCH("automobile",D31),0)>0,"Logistics & Transport", IF(IFERROR(SEARCH("travel",D31),0)+IFERROR(SEARCH("hotel",D31),0)+IFERROR(SEARCH("booking",D31),0)+IFERROR(SEARCH("tourism",D31),0)>0,"Travel & Hospitality", IF(IFERROR(SEARCH("fashion",D31),0)+IFERROR(SEARCH("apparel",D31),0)+IFERROR(SEARCH("clothing",D31),0)+IFERROR(SEARCH("jewelry",D31),0)+IFERROR(SEARCH("beauty",D31),0)>0,"Fashion & Lifestyle", IF(IFERROR(SEARCH("media",D31),0)+IFERROR(SEARCH("entertainment",D31),0)+IFERROR(SEARCH("video",D31),0)+IFERROR(SEARCH("gaming",D31),0)+IFERROR(SEARCH("music",D31),0)+IFERROR(SEARCH("social",D31),0)>0,"Media & Entertainment", IF(IFERROR(SEARCH("agri",D31),0)+IFERROR(SEARCH("farm",D31),0)+IFERROR(SEARCH("agtech",D31),0)>0,"Agriculture", IF(IFERROR(SEARCH("real estate",D31),0)+IFERROR(SEARCH("property",D31),0)+IFERROR(SEARCH("housing",D31),0)>0,"Real Estate", IF(IFERROR(SEARCH("energy",D31),0)+IFERROR(SEARCH("solar",D31),0)+IFERROR(SEARCH("clean tech",D31),0)+IFERROR(SEARCH("waste",D31),0)>0,"Energy & Environment", IF(IFERROR(SEARCH("hr",D31),0)+IFERROR(SEARCH("recruit",D31),0)+IFERROR(SEARCH("hiring",D31),0)+IFERROR(SEARCH("job",D31),0)>0,"HR & Recruitment", "Others")))))))))))))) -> Logistics & Transport | R31: =IF(ISNUMBER(SEARCH("bang",F31)),"Bangalore",IF(ISNUMBER(SEARCH("beng",F31)),"Bangalore",IF(ISNUMBER(SEARCH("mumbai",F31)),"Mumbai",IF(ISNUMBER(SEARCH("delhi",F31)),"Delhi-NCR",IF(ISNUMBER(SEARCH("gurgaon",F31)),"Delhi-NCR",IF(ISNUMBER(SEARCH("gurugram",F31)),"Delhi-NCR",IF(ISNUMBER(SEARCH("noida",F31)),"Delhi-NCR",IF(ISNUMBER(SEARCH("faridabad",F31)),"Delhi-NCR",IF(ISNUMBER(SEARCH("chennai",F31)),"Chennai",IF(ISNUMBER(SEARCH("hyderabad",F31)),"Hyderabad",IF(ISNUMBER(SEARCH("pune",F31)),"Pune",IF(ISNUMBER(SEARCH("kolkata",F31)),"Kolkata",IF(ISNUMBER(SEARCH("ahmedabad",F31)),"Ahmedabad",IF(ISNUMBER(SEARCH("jaipur",F31)),"Jaipur",IF(ISNUMBER(SEARCH("coimbatore",F31)),"Coimbatore",IF(ISNUMBER(SEARCH("kochi",F31)),"Kerala Cities",IF(ISNUMBER(SEARCH("cochin",F31)),"Kerala Cities",IF(ISNUMBER(SEARCH("francisco",F31)),"USA",IF(ISNUMBER(SEARCH("new york",F31)),"USA",IF(ISNUMBER(SEARCH("california",F31)),"USA",IF(ISNUMBER(SEARCH("palo alto",F31)),"USA",IF(ISNUMBER(SEARCH("santa",F31)),"USA",IF(ISNUMBER(SEARCH("singapore",F31)),"Singapore",IF(ISNUMBER(SEARCH("london",F31)),"London/UK",IF(F31="","Unknown","Other Cities"))))))))))))))))))))))))) -> Other Cities
A32: 31 | B32: 43788 | C32: Furtados School of Music | D32: Education | E32: Music Education | F32: Tulangan | G32: Ian Fund , Dsg Consumer Partners | H32: =IFERROR(TRIM(LEFT(G32,FIND(",",G32)-1)),TRIM(G32)) -> Ian Fund | I32: =IF(TRIM(G32)="",0,LEN(G32)-LEN(SUBSTITUTE(G32,",",""))+1) -> 2 | J32: =IF(Table1[[#This Row],[Investor Count]]>1,"Yes","No") -> Yes | K32: Not Disclosed | L32: 200000000 | M32: =YEAR(B32) -> 2019 | N32: =TEXT(B32,"mmmm") -> November | O32: 1919.41 | P32: =IF(ISBLANK(K32),"Unknown",IF(OR(ISNUMBER(SEARCH("seed",K32)),ISNUMBER(SEARCH("Seed",K32))),"Seed",IF(ISNUMBER(SEARCH("Series A",K32)),"Series A",IF(ISNUMBER(SEARCH("Series B",K32)),"Series B",IF(ISNUMBER(SEARCH("Series C",K32)),"Series C",IF(ISNUMBER(SEARCH("Series D",K32)),"Series D",IF(ISNUMBER(SEARCH("Private Equity",K32)),"Private Equity","Other"))))))) -> Other | Q32: =IF(IFERROR(SEARCH("ecom",D32),0)+IFERROR(SEARCH("commerce",D32),0)+IFERROR(SEARCH("retail",D32),0)>0,"E-Commerce", IF(IFERROR(SEARCH("fintech",D32),0)+IFERROR(SEARCH("finance",D32),0)+IFERROR(SEARCH("financial",D32),0)+IFERROR(SEARCH("lending",D32),0)+IFERROR(SEARCH("payment",D32),0)+IFERROR(SEARCH("banking",D32),0)+IFERROR(SEARCH("insurance",D32),0)>0,"FinTech", IF(IFERROR(SEARCH("tech",D32),0)+IFERROR(SEARCH("software",D32),0)+IFERROR(SEARCH("saas",D32),0)+IFERROR(SEARCH("ai",D32),0)+IFERROR(SEARCH("iot",D32),0)+IFERROR(SEARCH("cloud",D32),0)+IFERROR(SEARCH("data",D32),0)+IFERROR(SEARCH("analytics",D32),0)>0,"Technology", IF(IFERROR(SEARCH("food",D32),0)+IFERROR(SEARCH("restaurant",D32),0)+IFERROR(SEARCH("hospitality",D32),0)+IFERROR(SEARCH("beverage",D32),0)+IFERROR(SEARCH("delivery",D32),0)>0,"Food & Beverage", IF(IFERROR(SEARCH("health",D32),0)+IFERROR(SEARCH("medical",D32),0)+IFERROR(SEARCH("pharma",D32),0)+IFERROR(SEARCH("wellness",D32),0)+IFERROR(SEARCH("fitness",D32),0)>0,"Healthcare", IF(IFERROR(SEARCH("edu",D32),0)+IFERROR(SEARCH("learning",D32),0)+IFERROR(SEARCH("school",D32),0)+IFERROR(SEARCH("e-tech",D32),0)>0,"Education", IF(IFERROR(SEARCH("logistics",D32),0)+IFERROR(SEARCH("transport",D32),0)+IFERROR(SEARCH("delivery",D32),0)+IFERROR(SEARCH("mobility",D32),0)+IFERROR(SEARCH("automobile",D32),0)>0,"Logistics & Transport", IF(IFERROR(SEARCH("travel",D32),0)+IFERROR(SEARCH("hotel",D32),0)+IFERROR(SEARCH("booking",D32),0)+IFERROR(SEARCH("tourism",D32),0)>0,"Travel & Hospitality", IF(IFERROR(SEARCH("fashion",D32),0)+IFERROR(SEARCH("apparel",D32),0)+IFERROR(SEARCH("clothing",D32),0)+IFERROR(SEARCH("jewelry",D32),0)+IFERROR(SEARCH("beauty",D32),0)>0,"Fashion & Lifestyle", IF(IFERROR(SEARCH("media",D32),0)+IFERROR(SEARCH("entertainment",D32),0)+IFERROR(SEARCH("video",D32),0)+IFERROR(SEARCH("gaming",D32),0)+IFERROR(SEARCH("music",D32),0)+IFERROR(SEARCH("social",D32),0)>0,"Media & Entertainment", IF(IFERROR(SEARCH("agri",D32),0)+IFERROR(SEARCH("farm",D32),0)+IFERROR(SEARCH("agtech",D32),0)>0,"Agriculture", IF(IFERROR(SEARCH("real estate",D32),0)+IFERROR(SEARCH("property",D32),0)+IFERROR(SEARCH("housing",D32),0)>0,"Real Estate", IF(IFERROR(SEARCH("energy",D32),0)+IFERROR(SEARCH("solar",D32),0)+IFERROR(SEARCH("clean tech",D32),0)+IFERROR(SEARCH("waste",D32),0)>0,"Energy & Environment", IF(IFERROR(SEARCH("hr",D32),0)+IFERROR(SEARCH("recruit",D32),0)+IFERROR(SEARCH("hiring",D32),0)+IFERROR(SEARCH("job",D32),0)>0,"HR & Recruitment", "Others")))))))))))))) -> Education | R32: =IF(ISNUMBER(SEARCH("bang",F32)),"Bangalore",IF(ISNUMBER(SEARCH("beng",F32)),"Bangalore",IF(ISNUMBER(SEARCH("mumbai",F32)),"Mumbai",IF(ISNUMBER(SEARCH("delhi",F32)),"Delhi-NCR",IF(ISNUMBER(SEARCH("gurgaon",F32)),"Delhi-NCR",IF(ISNUMBER(SEARCH("gurugram",F32)),"Delhi-NCR",IF(ISNUMBER(SEARCH("noida",F32)),"Delhi-NCR",IF(ISNUMBER(SEARCH("faridabad",F32)),"Delhi-NCR",IF(ISNUMBER(SEARCH("chennai",F32)),"Chennai",IF(ISNUMBER(SEARCH("hyderabad",F32)),"Hyderabad",IF(ISNUMBER(SEARCH("pune",F32)),"Pune",IF(ISNUMBER(SEARCH("kolkata",F32)),"Kolkata",IF(ISNUMBER(SEARCH("ahmedabad",F32)),"Ahmedabad",IF(ISNUMBER(SEARCH("jaipur",F32)),"Jaipur",IF(ISNUMBER(SEARCH("coimbatore",F32)),"Coimbatore",IF(ISNUMBER(SEARCH("kochi",F32)),"Kerala Cities",IF(ISNUMBER(SEARCH("cochin",F32)),"Kerala Cities",IF(ISNUMBER(SEARCH("francisco",F32)),"USA",IF(ISNUMBER(SEARCH("new york",F32)),"USA",IF(ISNUMBER(SEARCH("california",F32)),"USA",IF(ISNUMBER(SEARCH("palo alto",F32)),"USA",IF(ISNUMBER(SEARCH("santa",F32)),"USA",IF(ISNUMBER(SEARCH("singapore",F32)),"Singapore",IF(ISNUMBER(SEARCH("london",F32)),"London/UK",IF(F32="","Unknown","Other Cities"))))))))))))))))))))))))) -> Other Cities
A33: 32 | B33: 43794 | C33: Paytm | D33: FinTech | E33: Mobile Wallet | F33: Noida | G33: Vijay Shekhar Sharma | H33: =IFERROR(TRIM(LEFT(G33,FIND(",",G33)-1)),TRIM(G33)) -> Vijay Shekhar Sharma | I33: =IF(TRIM(G33)="",0,LEN(G33)-LEN(SUBSTITUTE(G33,",",""))+1) -> 1 | J33: =IF(Table1[[#This Row],[Investor Count]]>1,"Yes","No") -> No | K33: Funding Round | L33: 1000000000 | M33: =YEAR(B33) -> 2019 | N33: =TEXT(B33,"mmmm") -> November | O33: 9597.05 | P33: =IF(ISBLANK(K33),"Unknown",IF(OR(ISNUMBER(SEARCH("seed",K33)),ISNUMBER(SEARCH("Seed",K33))),"Seed",IF(ISNUMBER(SEARCH("Series A",K33)),"Series A",IF(ISNUMBER(SEARCH("Series B",K33)),"Series B",IF(ISNUMBER(SEARCH("Series C",K33)),"Series C",IF(ISNUMBER(SEARCH("Series D",K33)),"Series D",IF(ISNUMBER(SEARCH("Private Equity",K33)),"Private Equity","Other"))))))) -> Other | Q33: =IF(IFERROR(SEARCH("ecom",D33),0)+IFERROR(SEARCH("commerce",D33),0)+IFERROR(SEARCH("retail",D33),0)>0,"E-Commerce", IF(IFERROR(SEARCH("fintech",D33),0)+IFERROR(SEARCH("finance",D33),0)+IFERROR(SEARCH("financial",D33),0)+IFERROR(SEARCH("lending",D33),0)+IFERROR(SEARCH("payment",D33),0)+IFERROR(SEARCH("banking",D33),0)+IFERROR(SEARCH("insurance",D33),0)>0,"FinTech", IF(IFERROR(SEARCH("tech",D33),0)+IFERROR(SEARCH("software",D33),0)+IFERROR(SEARCH("saas",D33),0)+IFERROR(SEARCH("ai",D33),0)+IFERROR(SEARCH("iot",D33),0)+IFERROR(SEARCH("cloud",D33),0)+IFERROR(SEARCH("data",D33),0)+IFERROR(SEARCH("analytics",D33),0)>0,"Technology", IF(IFERROR(SEARCH("food",D33),0)+IFERROR(SEARCH("restaurant",D33),0)+IFERROR(SEARCH("hospitality",D33),0)+IFERROR(SEARCH("beverage",D33),0)+IFERROR(SEARCH("delivery",D33),0)>0,"Food & Beverage", IF(IFERROR(SEARCH("health",D33),0)+IFERROR(SEARCH("medical",D33),0)+IFERROR(SEARCH("pharma",D33),0)+IFERROR(SEARCH("wellness",D33),0)+IFERROR(SEARCH("fitness",D33),0)>0,"Healthcare", IF(IFERROR(SEARCH("edu",D33),0)+IFERROR(SEARCH("learning",D33),0)+IFERROR(SEARCH("school",D33),0)+IFERROR(SEARCH("e-tech",D33),0)>0,"Education", IF(IFERROR(SEARCH("logistics",D33),0)+IFERROR(SEARCH("transport",D33),0)+IFERROR(SEARCH("delivery",D33),0)+IFERROR(SEARCH("mobility",D33),0)+IFERROR(SEARCH("automobile",D33),0)>0,"Logistics & Transport", IF(IFERROR(SEARCH("travel",D33),0)+IFERROR(SEARCH("hotel",D33),0)+IFERROR(SEARCH("booking",D33),0)+IFERROR(SEARCH("tourism",D33),0)>0,"Travel & Hospitality", IF(IFERROR(SEARCH("fashion",D33),0)+IFERROR(SEARCH("apparel",D33),0)+IFERROR(SEARCH("clothing",D33),0)+IFERROR(SEARCH("jewelry",D33),0)+IFERROR(SEARCH("beauty",D33),0)>0,"Fashion & Lifestyle", IF(IFERROR(SEARCH("media",D33),0)+IFERROR(SEARCH("entertainment",D33),0)+IFERROR(SEARCH("video",D33),0)+IFERROR(SEARCH("gaming",D33),0)+IFERROR(SEARCH("music",D33),0)+IFERROR(SEARCH("social",D33),0)>0,"Media & Entertainment", IF(IFERROR(SEARCH("agri",D33),0)+IFERROR(SEARCH("farm",D33),0)+IFERROR(SEARCH("agtech",D33),0)>0,"Agriculture", IF(IFERROR(SEARCH("real estate",D33),0)+IFERROR(SEARCH("property",D33),0)+IFERROR(SEARCH("housing",D33),0)>0,"Real Estate", IF(IFERROR(SEARCH("energy",D33),0)+IFERROR(SEARCH("solar",D33),0)+IFERROR(SEARCH("clean tech",D33),0)+IFERROR(SEARCH("waste",D33),0)>0,"Energy & Environment", IF(IFERROR(SEARCH("hr",D33),0)+IFERROR(SEARCH("recruit",D33),0)+IFERROR(SEARCH("hiring",D33),0)+IFERROR(SEARCH("job",D33),0)>0,"HR & Recruitment", "Others")))))))))))))) -> FinTech | R33: =IF(ISNUMBER(SEARCH("bang",F33)),"Bangalore",IF(ISNUMBER(SEARCH("beng",F33)),"Bangalore",IF(ISNUMBER(SEARCH("mumbai",F33)),"Mumbai",IF(ISNUMBER(SEARCH("delhi",F33)),"Delhi-NCR",IF(ISNUMBER(SEARCH("gurgaon",F33)),"Delhi-NCR",IF(ISNUMBER(SEARCH("gurugram",F33)),"Delhi-NCR",IF(ISNUMBER(SEARCH("noida",F33)),"Delhi-NCR",IF(ISNUMBER(SEARCH("faridabad",F33)),"Delhi-NCR",IF(ISNUMBER(SEARCH("chennai",F33)),"Chennai",IF(ISNUMBER(SEARCH("hyderabad",F33)),"Hyderabad",IF(ISNUMBER(SEARCH("pune",F33)),"Pune",IF(ISNUMBER(SEARCH("kolkata",F33)),"Kolkata",IF(ISNUMBER(SEARCH("ahmedabad",F33)),"Ahmedabad",IF(ISNUMBER(SEARCH("jaipur",F33)),"Jaipur",IF(ISNUMBER(SEARCH("coimbatore",F33)),"Coimbatore",IF(ISNUMBER(SEARCH("kochi",F33)),"Kerala Cities",IF(ISNUMBER(SEARCH("cochin",F33)),"Kerala Cities",IF(ISNUMBER(SEARCH("francisco",F33)),"USA",IF(ISNUMBER(SEARCH("new york",F33)),"USA",IF(ISNUMBER(SEARCH("california",F33)),"USA",IF(ISNUMBER(SEARCH("palo alto",F33)),"USA",IF(ISNUMBER(SEARCH("santa",F33)),"USA",IF(ISNUMBER(SEARCH("singapore",F33)),"Singapore",IF(ISNUMBER(SEARCH("london",F33)),"London/UK",IF(F33="","Unknown","Other Cities"))))))))))))))))))))))))) -> Delhi-NCR
A34: 33 | B34: 43742 | C34: Dunzo | D34: Customer Service | E34: Delivery Service | F34: Bengaluru | G34: Lightbox | H34: =IFERROR(TRIM(LEFT(G34,FIND(",",G34)-1)),TRIM(G34)) -> Lightbox | I34: =IF(TRIM(G34)="",0,LEN(G34)-LEN(SUBSTITUTE(G34,",",""))+1) -> 1 | J34: =IF(Table1[[#This Row],[Investor Count]]>1,"Yes","No") -> No | K34: Series D | L34: 45000000 | M34: =YEAR(B34) -> 2019 | N34: =TEXT(B34,"mmmm") -> October | O34: 431.86725 | P34: =IF(ISBLANK(K34),"Unknown",IF(OR(ISNUMBER(SEARCH("seed",K34)),ISNUMBER(SEARCH("Seed",K34))),"Seed",IF(ISNUMBER(SEARCH("Series A",K34)),"Series A",IF(ISNUMBER(SEARCH("Series B",K34)),"Series B",IF(ISNUMBER(SEARCH("Series C",K34)),"Series C",IF(ISNUMBER(SEARCH("Series D",K34)),"Series D",IF(ISNUMBER(SEARCH("Private Equity",K34)),"Private Equity","Other"))))))) -> Series D | Q34: =IF(IFERROR(SEARCH("ecom",D34),0)+IFERROR(SEARCH("commerce",D34),0)+IFERROR(SEARCH("retail",D34),0)>0,"E-Commerce", IF(IFERROR(SEARCH("fintech",D34),0)+IFERROR(SEARCH("finance",D34),0)+IFERROR(SEARCH("financial",D34),0)+IFERROR(SEARCH("lending",D34),0)+IFERROR(SEARCH("payment",D34),0)+IFERROR(SEARCH("banking",D34),0)+IFERROR(SEARCH("insurance",D34),0)>0,"FinTech", IF(IFERROR(SEARCH("tech",D34),0)+IFERROR(SEARCH("software",D34),0)+IFERROR(SEARCH("saas",D34),0)+IFERROR(SEARCH("ai",D34),0)+IFERROR(SEARCH("iot",D34),0)+IFERROR(SEARCH("cloud",D34),0)+IFERROR(SEARCH("data",D34),0)+IFERROR(SEARCH("analytics",D34),0)>0,"Technology", IF(IFERROR(SEARCH("food",D34),0)+IFERROR(SEARCH("restaurant",D34),0)+IFERROR(SEARCH("hospitality",D34),0)+IFERROR(SEARCH("beverage",D34),0)+IFERROR(SEARCH("delivery",D34),0)>0,"Food & Beverage", IF(IFERROR(SEARCH("health",D34),0)+IFERROR(SEARCH("medical",D34),0)+IFERROR(SEARCH("pharma",D34),0)+IFERROR(SEARCH("wellness",D34),0)+IFERROR(SEARCH("fitness",D34),0)>0,"Healthcare", IF(IFERROR(SEARCH("edu",D34),0)+IFERROR(SEARCH("learning",D34),0)+IFERROR(SEARCH("school",D34),0)+IFERROR(SEARCH("e-tech",D34),0)>0,"Education", IF(IFERROR(SEARCH("logistics",D34),0)+IFERROR(SEARCH("transport",D34),0)+IFERROR(SEARCH("delivery",D34),0)+IFERROR(SEARCH("mobility",D34),0)+IFERROR(SEARCH("automobile",D34),0)>0,"Logistics & Transport", IF(IFERROR(SEARCH("travel",D34),0)+IFERROR(SEARCH("hotel",D34),0)+IFERROR(SEARCH("booking",D34),0)+IFERROR(SEARCH("tourism",D34),0)>0,"Travel & Hospitality", IF(IFERROR(SEARCH("fashion",D34),0)+IFERROR(SEARCH("apparel",D34),0)+IFERROR(SEARCH("clothing",D34),0)+IFERROR(SEARCH("jewelry",D34),0)+IFERROR(SEARCH("beauty",D34),0)>0,"Fashion & Lifestyle", IF(IFERROR(SEARCH("media",D34),0)+IFERROR(SEARCH("entertainment",D34),0)+IFERROR(SEARCH("video",D34),0)+IFERROR(SEARCH("gaming",D34),0)+IFERROR(SEARCH("music",D34),0)+IFERROR(SEARCH("social",D34),0)>0,"Media & Entertainment", IF(IFERROR(SEARCH("agri",D34),0)+IFERROR(SEARCH("farm",D34),0)+IFERROR(SEARCH("agtech",D34),0)>0,"Agriculture", IF(IFERROR(SEARCH("real estate",D34),0)+IFERROR(SEARCH("property",D34),0)+IFERROR(SEARCH("housing",D34),0)>0,"Real Estate", IF(IFERROR(SEARCH("energy",D34),0)+IFERROR(SEARCH("solar",D34),0)+IFERROR(SEARCH("clean tech",D34),0)+IFERROR(SEARCH("waste",D34),0)>0,"Energy & Environment", IF(IFERROR(SEARCH("hr",D34),0)+IFERROR(SEARCH("recruit",D34),0)+IFERROR(SEARCH("hiring",D34),0)+IFERROR(SEARCH("job",D34),0)>0,"HR & Recruitment", "Others")))))))))))))) -> Others | R34: =IF(ISNUMBER(SEARCH("bang",F34)),"Bangalore",IF(ISNUMBER(SEARCH("beng",F34)),"Bangalore",IF(ISNUMBER(SEARCH("mumbai",F34)),"Mumbai",IF(ISNUMBER(SEARCH("delhi",F34)),"Delhi-NCR",IF(ISNUMBER(SEARCH("gurgaon",F34)),"Delhi-NCR",IF(ISNUMBER(SEARCH("gurugram",F34)),"Delhi-NCR",IF(ISNUMBER(SEARCH("noida",F34)),"Delhi-NCR",IF(ISNUMBER(SEARCH("faridabad",F34)),"Delhi-NCR",IF(ISNUMBER(SEARCH("chennai",F34)),"Chennai",IF(ISNUMBER(SEARCH("hyderabad",F34)),"Hyderabad",IF(ISNUMBER(SEARCH("pune",F34)),"Pune",IF(ISNUMBER(SEARCH("kolkata",F34)),"Kolkata",IF(ISNUMBER(SEARCH("ahmedabad",F34)),"Ahmedabad",IF(ISNUMBER(SEARCH("jaipur",F34)),"Jaipur",IF(ISNUMBER(SEARCH("coimbatore",F34)),"Coimbatore",IF(ISNUMBER(SEARCH("kochi",F34)),"Kerala Cities",IF(ISNUMBER(SEARCH("cochin",F34)),"Kerala Cities",IF(ISNUMBER(SEARCH("francisco",F34)),"USA",IF(ISNUMBER(SEARCH("new york",F34)),"USA",IF(ISNUMBER(SEARCH("california",F34)),"USA",IF(ISNUMBER(SEARCH("palo alto",F34)),"USA",IF(ISNUMBER(SEARCH("santa",F34)),"USA",IF(ISNUMBER(SEARCH("singapore",F34)),"Singapore",IF(ISNUMBER(SEARCH("london",F34)),"London/UK",IF(F34="","Unknown","Other Cities"))))))))))))))))))))))))) -> Bangalore
A35: 34 | B35: 43740 | C35: Udaan | D35: B2B | E35: Business development | F35: Bengaluru | G35: Altimeter Capital, Dst Global | H35: =IFERROR(TRIM(LEFT(G35,FIND(",",G35)-1)),TRIM(G35)) -> Altimeter Capital | I35: =IF(TRIM(G35)="",0,LEN(G35)-LEN(SUBSTITUTE(G35,",",""))+1) -> 2 | J35: =IF(Table1[[#This Row],[Investor Count]]>1,"Yes","No") -> Yes | K35: Series D | L35: 585000000 | M35: =YEAR(B35) -> 2019 | N35: =TEXT(B35,"mmmm") -> October | O35: 5614.2743 | P35: =IF(ISBLANK(K35),"Unknown",IF(OR(ISNUMBER(SEARCH("seed",K35)),ISNUMBER(SEARCH("Seed",K35))),"Seed",IF(ISNUMBER(SEARCH("Series A",K35)),"Series A",IF(ISNUMBER(SEARCH("Series B",K35)),"Series B",IF(ISNUMBER(SEARCH("Series C",K35)),"Series C",IF(ISNUMBER(SEARCH("Series D",K35)),"Series D",IF(ISNUMBER(SEARCH("Private Equity",K35)),"Private Equity","Other"))))))) -> Series D | Q35: =IF(IFERROR(SEARCH("ecom",D35),0)+IFERROR(SEARCH("commerce",D35),0)+IFERROR(SEARCH("retail",D35),0)>0,"E-Commerce", IF(IFERROR(SEARCH("fintech",D35),0)+IFERROR(SEARCH("finance",D35),0)+IFERROR(SEARCH("financial",D35),0)+IFERROR(SEARCH("lending",D35),0)+IFERROR(SEARCH("payment",D35),0)+IFERROR(SEARCH("banking",D35),0)+IFERROR(SEARCH("insurance",D35),0)>0,"FinTech", IF(IFERROR(SEARCH("tech",D35),0)+IFERROR(SEARCH("software",D35),0)+IFERROR(SEARCH("saas",D35),0)+IFERROR(SEARCH("ai",D35),0)+IFERROR(SEARCH("iot",D35),0)+IFERROR(SEARCH("cloud",D35),0)+IFERROR(SEARCH("data",D35),0)+IFERROR(SEARCH("analytics",D35),0)>0,"Technology", IF(IFERROR(SEARCH("food",D35),0)+IFERROR(SEARCH("restaurant",D35),0)+IFERROR(SEARCH("hospitality",D35),0)+IFERROR(SEARCH("beverage",D35),0)+IFERROR(SEARCH("delivery",D35),0)>0,"Food & Beverage", IF(IFERROR(SEARCH("health",D35),0)+IFERROR(SEARCH("medical",D35),0)+IFERROR(SEARCH("pharma",D35),0)+IFERROR(SEARCH("wellness",D35),0)+IFERROR(SEARCH("fitness",D35),0)>0,"Healthcare", IF(IFERROR(SEARCH("edu",D35),0)+IFERROR(SEARCH("learning",D35),0)+IFERROR(SEARCH("school",D35),0)+IFERROR(SEARCH("e-tech",D35),0)>0,"Education", IF(IFERROR(SEARCH("logistics",D35),0)+IFERROR(SEARCH("transport",D35),0)+IFERROR(SEARCH("delivery",D35),0)+IFERROR(SEARCH("mobility",D35),0)+IFERROR(SEARCH("automobile",D35),0)>0,"Logistics & Transport", IF(IFERROR(SEARCH("travel",D35),0)+IFERROR(SEARCH("hotel",D35),0)+IFERROR(SEARCH("booking",D35),0)+IFERROR(SEARCH("tourism",D35),0)>0,"Travel & Hospitality", IF(IFERROR(SEARCH("fashion",D35),0)+IFERROR(SEARCH("apparel",D35),0)+IFERROR(SEARCH("clothing",D35),0)+IFERROR(SEARCH("jewelry",D35),0)+IFERROR(SEARCH("beauty",D35),0)>0,"Fashion & Lifestyle", IF(IFERROR(SEARCH("media",D35),0)+IFERROR(SEARCH("entertainment",D35),0)+IFERROR(SEARCH("video",D35),0)+IFERROR(SEARCH("gaming",D35),0)+IFERROR(SEARCH("music",D35),0)+IFERROR(SEARCH("social",D35),0)>0,"Media & Entertainment", IF(IFERROR(SEARCH("agri",D35),0)+IFERROR(SEARCH("farm",D35),0)+IFERROR(SEARCH("agtech",D35),0)>0,"Agriculture", IF(IFERROR(SEARCH("real estate",D35),0)+IFERROR(SEARCH("property",D35),0)+IFERROR(SEARCH("housing",D35),0)>0,"Real Estate", IF(IFERROR(SEARCH("energy",D35),0)+IFERROR(SEARCH("solar",D35),0)+IFERROR(SEARCH("clean tech",D35),0)+IFERROR(SEARCH("waste",D35),0)>0,"Energy & Environment", IF(IFERROR(SEARCH("hr",D35),0)+IFERROR(SEARCH("recruit",D35),0)+IFERROR(SEARCH("hiring",D35),0)+IFERROR(SEARCH("job",D35),0)>0,"HR & Recruitment", "Others")))))))))))))) -> Others | R35: =IF(ISNUMBER(SEARCH("bang",F35)),"Bangalore",IF(ISNUMBER(SEARCH("beng",F35)),"Bangalore",IF(ISNUMBER(SEARCH("mumbai",F35)),"Mumbai",IF(ISNUMBER(SEARCH("delhi",F35)),"Delhi-NCR",IF(ISNUMBER(SEARCH("gurgaon",F35)),"Delhi-NCR",IF(ISNUMBER(SEARCH("gurugram",F35)),"Delhi-NCR",IF(ISNUMBER(SEARCH("noida",F35)),"Delhi-NCR",IF(ISNUMBER(SEARCH("faridabad",F35)),"Delhi-NCR",IF(ISNUMBER(SEARCH("chennai",F35)),"Chennai",IF(ISNUMBER(SEARCH("hyderabad",F35)),"Hyderabad",IF(ISNUMBER(SEARCH("pune",F35)),"Pune",IF(ISNUMBER(SEARCH("kolkata",F35)),"Kolkata",IF(ISNUMBER(SEARCH("ahmedabad",F35)),"Ahmedabad",IF(ISNUMBER(SEARCH("jaipur",F35)),"Jaipur",IF(ISNUMBER(SEARCH("coimbatore",F35)),"Coimbatore",IF(ISNUMBER(SEARCH("kochi",F35)),"Kerala Cities",IF(ISNUMBER(SEARCH("cochin",F35)),"Kerala Cities",IF(ISNUMBER(SEARCH("francisco",F35)),"USA",IF(ISNUMBER(SEARCH("new york",F35)),"USA",IF(ISNUMBER(SEARCH("california",F35)),"USA",IF(ISNUMBER(SEARCH("palo alto",F35)),"USA",IF(ISNUMBER(SEARCH("santa",F35)),"USA",IF(ISNUMBER(SEARCH("singapore",F35)),"Singapore",IF(ISNUMBER(SEARCH("london",F35)),"London/UK",IF(F35="","Unknown","Other Cities"))))))))))))))))))))))))) -> Bangalore
A36: 35 | B36: 43759 | C36: The Man Company | D36: Consumer Goods | E36: Beauty , Grooming | F36: Gurgaon | G36: Ayushmann Khurana | H36: =IFERROR(TRIM(LEFT(G36,FIND(",",G36)-1)),TRIM(G36)) -> Ayushmann Khurana | I36: =IF(TRIM(G36)="",0,LEN(G36)-LEN(SUBSTITUTE(G36,",",""))+1) -> 1 | J36: =IF(Table1[[#This Row],[Investor Count]]>1,"Yes","No") -> No | K36: Corporate Round | M36: =YEAR(B36) -> 2019 | N36: =TEXT(B36,"mmmm") -> October | O36: 0 | P36: =IF(ISBLANK(K36),"Unknown",IF(OR(ISNUMBER(SEARCH("seed",K36)),ISNUMBER(SEARCH("Seed",K36))),"Seed",IF(ISNUMBER(SEARCH("Series A",K36)),"Series A",IF(ISNUMBER(SEARCH("Series B",K36)),"Series B",IF(ISNUMBER(SEARCH("Series C",K36)),"Series C",IF(ISNUMBER(SEARCH("Series D",K36)),"Series D",IF(ISNUMBER(SEARCH("Private Equity",K36)),"Private Equity","Other"))))))) -> Other | Q36: =IF(IFERROR(SEARCH("ecom",D36),0)+IFERROR(SEARCH("commerce",D36),0)+IFERROR(SEARCH("retail",D36),0)>0,"E-Commerce", IF(IFERROR(SEARCH("fintech",D36),0)+IFERROR(SEARCH("finance",D36),0)+IFERROR(SEARCH("financial",D36),0)+IFERROR(SEARCH("lending",D36),0)+IFERROR(SEARCH("payment",D36),0)+IFERROR(SEARCH("banking",D36),0)+IFERROR(SEARCH("insurance",D36),0)>0,"FinTech", IF(IFERROR(SEARCH("tech",D36),0)+IFERROR(SEARCH("software",D36),0)+IFERROR(SEARCH("saas",D36),0)+IFERROR(SEARCH("ai",D36),0)+IFERROR(SEARCH("iot",D36),0)+IFERROR(SEARCH("cloud",D36),0)+IFERROR(SEARCH("data",D36),0)+IFERROR(SEARCH("analytics",D36),0)>0,"Technology", IF(IFERROR(SEARCH("food",D36),0)+IFERROR(SEARCH("restaurant",D36),0)+IFERROR(SEARCH("hospitality",D36),0)+IFERROR(SEARCH("beverage",D36),0)+IFERROR(SEARCH("delivery",D36),0)>0,"Food & Beverage", IF(IFERROR(SEARCH("health",D36),0)+IFERROR(SEARCH("medical",D36),0)+IFERROR(SEARCH("pharma",D36),0)+IFERROR(SEARCH("wellness",D36),0)+IFERROR(SEARCH("fitness",D36),0)>0,"Healthcare", IF(IFERROR(SEARCH("edu",D36),0)+IFERROR(SEARCH("learning",D36),0)+IFERROR(SEARCH("school",D36),0)+IFERROR(SEARCH("e-tech",D36),0)>0,"Education", IF(IFERROR(SEARCH("logistics",D36),0)+IFERROR(SEARCH("transport",D36),0)+IFERROR(SEARCH("delivery",D36),0)+IFERROR(SEARCH("mobility",D36),0)+IFERROR(SEARCH("automobile",D36),0)>0,"Logistics & Transport", IF(IFERROR(SEARCH("travel",D36),0)+IFERROR(SEARCH("hotel",D36),0)+IFERROR(SEARCH("booking",D36),0)+IFERROR(SEARCH("tourism",D36),0)>0,"Travel & Hospitality", IF(IFERROR(SEARCH("fashion",D36),0)+IFERROR(SEARCH("apparel",D36),0)+IFERROR(SEARCH("clothing",D36),0)+IFERROR(SEARCH("jewelry",D36),0)+IFERROR(SEARCH("beauty",D36),0)>0,"Fashion & Lifestyle", IF(IFERROR(SEARCH("media",D36),0)+IFERROR(SEARCH("entertainment",D36),0)+IFERROR(SEARCH("video",D36),0)+IFERROR(SEARCH("gaming",D36),0)+IFERROR(SEARCH("music",D36),0)+IFERROR(SEARCH("social",D36),0)>0,"Media & Entertainment", IF(IFERROR(SEARCH("agri",D36),0)+IFERROR(SEARCH("farm",D36),0)+IFERROR(SEARCH("agtech",D36),0)>0,"Agriculture", IF(IFERROR(SEARCH("real estate",D36),0)+IFERROR(SEARCH("property",D36),0)+IFERROR(SEARCH("housing",D36),0)>0,"Real Estate", IF(IFERROR(SEARCH("energy",D36),0)+IFERROR(SEARCH("solar",D36),0)+IFERROR(SEARCH("clean tech",D36),0)+IFERROR(SEARCH("waste",D36),0)>0,"Energy & Environment", IF(IFERROR(SEARCH("hr",D36),0)+IFERROR(SEARCH("recruit",D36),0)+IFERROR(SEARCH("hiring",D36),0)+IFERROR(SEARCH("job",D36),0)>0,"HR & Recruitment", "Others")))))))))))))) -> Others | R36: =IF(ISNUMBER(SEARCH("bang",F36)),"Bangalore",IF(ISNUMBER(SEARCH("beng",F36)),"Bangalore",IF(ISNUMBER(SEARCH("mumbai",F36)),"Mumbai",IF(ISNUMBER(SEARCH("delhi",F36)),"Delhi-NCR",IF(ISNUMBER(SEARCH("gurgaon",F36)),"Delhi-NCR",IF(ISNUMBER(SEARCH("gurugram",F36)),"Delhi-NCR",IF(ISNUMBER(SEARCH("noida",F36)),"Delhi-NCR",IF(ISNUMBER(SEARCH("faridabad",F36)),"Delhi-NCR",IF(ISNUMBER(SEARCH("chennai",F36)),"Chennai",IF(ISNUMBER(SEARCH("hyderabad",F36)),"Hyderabad",IF(ISNUMBER(SEARCH("pune",F36)),"Pune",IF(ISNUMBER(SEARCH("kolkata",F36)),"Kolkata",IF(ISNUMBER(SEARCH("ahmedabad",F36)),"Ahmedabad",IF(ISNUMBER(SEARCH("jaipur",F36)),"Jaipur",IF(ISNUMBER(SEARCH("coimbatore",F36)),"Coimbatore",IF(ISNUMBER(SEARCH("kochi",F36)),"Kerala Cities",IF(ISNUMBER(SEARCH("cochin",F36)),"Kerala Cities",IF(ISNUMBER(SEARCH("francisco",F36)),"USA",IF(ISNUMBER(SEARCH("new york",F36)),"USA",IF(ISNUMBER(SEARCH("california",F36)),"USA",IF(ISNUMBER(SEARCH("palo alto",F36)),"USA",IF(ISNUMBER(SEARCH("santa",F36)),"USA",IF(ISNUMBER(SEARCH("singapore",F36)),"Singapore",IF(ISNUMBER(SEARCH("london",F36)),"London/UK",IF(F36="","Unknown","Other Cities"))))))))))))))))))))))))) -> Delhi-NCR
A37: 36 | B37: 43713 | C37: FPL Technologies | D37: FinTech | E37: Financial Services | F37: Pune | G37: Matrix Partners India, Sequoia India | H37: =IFERROR(TRIM(LEFT(G37,FIND(",",G37)-1)),TRIM(G37)) -> Matrix Partners India | I37: =IF(TRIM(G37)="",0,LEN(G37)-LEN(SUBSTITUTE(G37,",",""))+1) -> 2 | J37: =IF(Table1[[#This Row],[Investor Count]]>1,"Yes","No") -> Yes | K37: Maiden Round | L37: 4500000 | M37: =YEAR(B37) -> 2019 | N37: =TEXT(B37,"mmmm") -> September | O37: 43.186725 | P37: =IF(ISBLANK(K37),"Unknown",IF(OR(ISNUMBER(SEARCH("seed",K37)),ISNUMBER(SEARCH("Seed",K37))),"Seed",IF(ISNUMBER(SEARCH("Series A",K37)),"Series A",IF(ISNUMBER(SEARCH("Series B",K37)),"Series B",IF(ISNUMBER(SEARCH("Series C",K37)),"Series C",IF(ISNUMBER(SEARCH("Series D",K37)),"Series D",IF(ISNUMBER(SEARCH("Private Equity",K37)),"Private Equity","Other"))))))) -> Other | Q37: =IF(IFERROR(SEARCH("ecom",D37),0)+IFERROR(SEARCH("commerce",D37),0)+IFERROR(SEARCH("retail",D37),0)>0,"E-Commerce", IF(IFERROR(SEARCH("fintech",D37),0)+IFERROR(SEARCH("finance",D37),0)+IFERROR(SEARCH("financial",D37),0)+IFERROR(SEARCH("lending",D37),0)+IFERROR(SEARCH("payment",D37),0)+IFERROR(SEARCH("banking",D37),0)+IFERROR(SEARCH("insurance",D37),0)>0,"FinTech", IF(IFERROR(SEARCH("tech",D37),0)+IFERROR(SEARCH("software",D37),0)+IFERROR(SEARCH("saas",D37),0)+IFERROR(SEARCH("ai",D37),0)+IFERROR(SEARCH("iot",D37),0)+IFERROR(SEARCH("cloud",D37),0)+IFERROR(SEARCH("data",D37),0)+IFERROR(SEARCH("analytics",D37),0)>0,"Technology", IF(IFERROR(SEARCH("food",D37),0)+IFERROR(SEARCH("restaurant",D37),0)+IFERROR(SEARCH("hospitality",D37),0)+IFERROR(SEARCH("beverage",D37),0)+IFERROR(SEARCH("delivery",D37),0)>0,"Food & Beverage", IF(IFERROR(SEARCH("health",D37),0)+IFERROR(SEARCH("medical",D37),0)+IFERROR(SEARCH("pharma",D37),0)+IFERROR(SEARCH("wellness",D37),0)+IFERROR(SEARCH("fitness",D37),0)>0,"Healthcare", IF(IFERROR(SEARCH("edu",D37),0)+IFERROR(SEARCH("learning",D37),0)+IFERROR(SEARCH("school",D37),0)+IFERROR(SEARCH("e-tech",D37),0)>0,"Education", IF(IFERROR(SEARCH("logistics",D37),0)+IFERROR(SEARCH("transport",D37),0)+IFERROR(SEARCH("delivery",D37),0)+IFERROR(SEARCH("mobility",D37),0)+IFERROR(SEARCH("automobile",D37),0)>0,"Logistics & Transport", IF(IFERROR(SEARCH("travel",D37),0)+IFERROR(SEARCH("hotel",D37),0)+IFERROR(SEARCH("booking",D37),0)+IFERROR(SEARCH("tourism",D37),0)>0,"Travel & Hospitality", IF(IFERROR(SEARCH("fashion",D37),0)+IFERROR(SEARCH("apparel",D37),0)+IFERROR(SEARCH("clothing",D37),0)+IFERROR(SEARCH("jewelry",D37),0)+IFERROR(SEARCH("beauty",D37),0)>0,"Fashion & Lifestyle", IF(IFERROR(SEARCH("media",D37),0)+IFERROR(SEARCH("entertainment",D37),0)+IFERROR(SEARCH("video",D37),0)+IFERROR(SEARCH("gaming",D37),0)+IFERROR(SEARCH("music",D37),0)+IFERROR(SEARCH("social",D37),0)>0,"Media & Entertainment", IF(IFERROR(SEARCH("agri",D37),0)+IFERROR(SEARCH("farm",D37),0)+IFERROR(SEARCH("agtech",D37),0)>0,"Agriculture", IF(IFERROR(SEARCH("real estate",D37),0)+IFERROR(SEARCH("property",D37),0)+IFERROR(SEARCH("housing",D37),0)>0,"Real Estate", IF(IFERROR(SEARCH("energy",D37),0)+IFERROR(SEARCH("solar",D37),0)+IFERROR(SEARCH("clean tech",D37),0)+IFERROR(SEARCH("waste",D37),0)>0,"Energy & Environment", IF(IFERROR(SEARCH("hr",D37),0)+IFERROR(SEARCH("recruit",D37),0)+IFERROR(SEARCH("hiring",D37),0)+IFERROR(SEARCH("job",D37),0)>0,"HR & Recruitment", "Others")))))))))))))) -> FinTech | R37: =IF(ISNUMBER(SEARCH("bang",F37)),"Bangalore",IF(ISNUMBER(SEARCH("beng",F37)),"Bangalore",IF(ISNUMBER(SEARCH("mumbai",F37)),"Mumbai",IF(ISNUMBER(SEARCH("delhi",F37)),"Delhi-NCR",IF(ISNUMBER(SEARCH("gurgaon",F37)),"Delhi-NCR",IF(ISNUMBER(SEARCH("gurugram",F37)),"Delhi-NCR",IF(ISNUMBER(SEARCH("noida",F37)),"Delhi-NCR",IF(ISNUMBER(SEARCH("faridabad",F37)),"Delhi-NCR",IF(ISNUMBER(SEARCH("chennai",F37)),"Chennai",IF(ISNUMBER(SEARCH("hyderabad",F37)),"Hyderabad",IF(ISNUMBER(SEARCH("pune",F37)),"Pune",IF(ISNUMBER(SEARCH("kolkata",F37)),"Kolkata",IF(ISNUMBER(SEARCH("ahmedabad",F37)),"Ahmedabad",IF(ISNUMBER(SEARCH("jaipur",F37)),"Jaipur",IF(ISNUMBER(SEARCH("coimbatore",F37)),"Coimbatore",IF(ISNUMBER(SEARCH("kochi",F37)),"Kerala Cities",IF(ISNUMBER(SEARCH("cochin",F37)),"Kerala Cities",IF(ISNUMBER(SEARCH("francisco",F37)),"USA",IF(ISNUMBER(SEARCH("new york",F37)),"USA",IF(ISNUMBER(SEARCH("california",F37)),"USA",IF(ISNUMBER(SEARCH("palo alto",F37)),"USA",IF(ISNUMBER(SEARCH("santa",F37)),"USA",IF(ISNUMBER(SEARCH("singapore",F37)),"Singapore",IF(ISNUMBER(SEARCH("london",F37)),"London/UK",IF(F37="","Unknown","Other Cities"))))))))))))))))))))))))) -> Pune
A38: 37 | B38: 43712 | C38: Cashflo | D38: FinTech | E38: Invoice discounting platform , SME lending marketplace | F38: Mumbai | G38: Saif Partners | H38: =IFERROR(TRIM(LEFT(G38,FIND(",",G38)-1)),TRIM(G38)) -> Saif Partners | I38: =IF(TRIM(G38)="",0,LEN(G38)-LEN(SUBSTITUTE(G38,",",""))+1) -> 1 | J38: =IF(Table1[[#This Row],[Investor Count]]>1,"Yes","No") -> No | K38: Series A | L38: 3300000 | M38: =YEAR(B38) -> 2019 | N38: =TEXT(B38,"mmmm") -> September | O38: 31.670265 | P38: =IF(ISBLANK(K38),"Unknown",IF(OR(ISNUMBER(SEARCH("seed",K38)),ISNUMBER(SEARCH("Seed",K38))),"Seed",IF(ISNUMBER(SEARCH("Series A",K38)),"Series A",IF(ISNUMBER(SEARCH("Series B",K38)),"Series B",IF(ISNUMBER(SEARCH("Series C",K38)),"Series C",IF(ISNUMBER(SEARCH("Series D",K38)),"Series D",IF(ISNUMBER(SEARCH("Private Equity",K38)),"Private Equity","Other"))))))) -> Series A | Q38: =IF(IFERROR(SEARCH("ecom",D38),0)+IFERROR(SEARCH("commerce",D38),0)+IFERROR(SEARCH("retail",D38),0)>0,"E-Commerce", IF(IFERROR(SEARCH("fintech",D38),0)+IFERROR(SEARCH("finance",D38),0)+IFERROR(SEARCH("financial",D38),0)+IFERROR(SEARCH("lending",D38),0)+IFERROR(SEARCH("payment",D38),0)+IFERROR(SEARCH("banking",D38),0)+IFERROR(SEARCH("insurance",D38),0)>0,"FinTech", IF(IFERROR(SEARCH("tech",D38),0)+IFERROR(SEARCH("software",D38),0)+IFERROR(SEARCH("saas",D38),0)+IFERROR(SEARCH("ai",D38),0)+IFERROR(SEARCH("iot",D38),0)+IFERROR(SEARCH("cloud",D38),0)+IFERROR(SEARCH("data",D38),0)+IFERROR(SEARCH("analytics",D38),0)>0,"Technology", IF(IFERROR(SEARCH("food",D38),0)+IFERROR(SEARCH("restaurant",D38),0)+IFERROR(SEARCH("hospitality",D38),0)+IFERROR(SEARCH("beverage",D38),0)+IFERROR(SEARCH("delivery",D38),0)>0,"Food & Beverage", IF(IFERROR(SEARCH("health",D38),0)+IFERROR(SEARCH("medical",D38),0)+IFERROR(SEARCH("pharma",D38),0)+IFERROR(SEARCH("wellness",D38),0)+IFERROR(SEARCH("fitness",D38),0)>0,"Healthcare", IF(IFERROR(SEARCH("edu",D38),0)+IFERROR(SEARCH("learning",D38),0)+IFERROR(SEARCH("school",D38),0)+IFERROR(SEARCH("e-tech",D38),0)>0,"Education", IF(IFERROR(SEARCH("logistics",D38),0)+IFERROR(SEARCH("transport",D38),0)+IFERROR(SEARCH("delivery",D38),0)+IFERROR(SEARCH("mobility",D38),0)+IFERROR(SEARCH("automobile",D38),0)>0,"Logistics & Transport", IF(IFERROR(SEARCH("travel",D38),0)+IFERROR(SEARCH("hotel",D38),0)+IFERROR(SEARCH("booking",D38),0)+IFERROR(SEARCH("tourism",D38),0)>0,"Travel & Hospitality", IF(IFERROR(SEARCH("fashion",D38),0)+IFERROR(SEARCH("apparel",D38),0)+IFERROR(SEARCH("clothing",D38),0)+IFERROR(SEARCH("jewelry",D38),0)+IFERROR(SEARCH("beauty",D38),0)>0,"Fashion & Lifestyle", IF(IFERROR(SEARCH("media",D38),0)+IFERROR(SEARCH("entertainment",D38),0)+IFERROR(SEARCH("video",D38),0)+IFERROR(SEARCH("gaming",D38),0)+IFERROR(SEARCH("music",D38),0)+IFERROR(SEARCH("social",D38),0)>0,"Media & Entertainment", IF(IFERROR(SEARCH("agri",D38),0)+IFERROR(SEARCH("farm",D38),0)+IFERROR(SEARCH("agtech",D38),0)>0,"Agriculture", IF(IFERROR(SEARCH("real estate",D38),0)+IFERROR(SEARCH("property",D38),0)+IFERROR(SEARCH("housing",D38),0)>0,"Real Estate", IF(IFERROR(SEARCH("energy",D38),0)+IFERROR(SEARCH("solar",D38),0)+IFERROR(SEARCH("clean tech",D38),0)+IFERROR(SEARCH("waste",D38),0)>0,"Energy & Environment", IF(IFERROR(SEARCH("hr",D38),0)+IFERROR(SEARCH("recruit",D38),0)+IFERROR(SEARCH("hiring",D38),0)+IFERROR(SEARCH("job",D38),0)>0,"HR & Recruitment", "Others")))))))))))))) -> FinTech | R38: =IF(ISNUMBER(SEARCH("bang",F38)),"Bangalore",IF(ISNUMBER(SEARCH("beng",F38)),"Bangalore",IF(ISNUMBER(SEARCH("mumbai",F38)),"Mumbai",IF(ISNUMBER(SEARCH("delhi",F38)),"Delhi-NCR",IF(ISNUMBER(SEARCH("gurgaon",F38)),"Delhi-NCR",IF(ISNUMBER(SEARCH("gurugram",F38)),"Delhi-NCR",IF(ISNUMBER(SEARCH("noida",F38)),"Delhi-NCR",IF(ISNUMBER(SEARCH("faridabad",F38)),"Delhi-NCR",IF(ISNUMBER(SEARCH("chennai",F38)),"Chennai",IF(ISNUMBER(SEARCH("hyderabad",F38)),"Hyderabad",IF(ISNUMBER(SEARCH("pune",F38)),"Pune",IF(ISNUMBER(SEARCH("kolkata",F38)),"Kolkata",IF(ISNUMBER(SEARCH("ahmedabad",F38)),"Ahmedabad",IF(ISNUMBER(SEARCH("jaipur",F38)),"Jaipur",IF(ISNUMBER(SEARCH("coimbatore",F38)),"Coimbatore",IF(ISNUMBER(SEARCH("kochi",F38)),"Kerala Cities",IF(ISNUMBER(SEARCH("cochin",F38)),"Kerala Cities",IF(ISNUMBER(SEARCH("francisco",F38)),"USA",IF(ISNUMBER(SEARCH("new york",F38)),"USA",IF(ISNUMBER(SEARCH("california",F38)),"USA",IF(ISNUMBER(SEARCH("palo alto",F38)),"USA",IF(ISNUMBER(SEARCH("santa",F38)),"USA",IF(ISNUMBER(SEARCH("singapore",F38)),"Singapore",IF(ISNUMBER(SEARCH("london",F38)),"London/UK",IF(F38="","Unknown","Other Cities"))))))))))))))))))))))))) -> Mumbai
A39: 38 | B39: 43712 | C39: Digital F5 | D39: Advertising& Marketing | E39: Digital marketing firm | F39: Mumbai | G39: Tiw Private Equity | H39: =IFERROR(TRIM(LEFT(G39,FIND(",",G39)-1)),TRIM(G39)) -> Tiw Private Equity | I39: =IF(TRIM(G39)="",0,LEN(G39)-LEN(SUBSTITUTE(G39,",",""))+1) -> 1 | J39: =IF(Table1[[#This Row],[Investor Count]]>1,"Yes","No") -> No | K39: Private Equity Round | L39: 6000000 | M39: =YEAR(B39) -> 2019 | N39: =TEXT(B39,"mmmm") -> September | O39: 57.5823 | P39: =IF(ISBLANK(K39),"Unknown",IF(OR(ISNUMBER(SEARCH("seed",K39)),ISNUMBER(SEARCH("Seed",K39))),"Seed",IF(ISNUMBER(SEARCH("Series A",K39)),"Series A",IF(ISNUMBER(SEARCH("Series B",K39)),"Series B",IF(ISNUMBER(SEARCH("Series C",K39)),"Series C",IF(ISNUMBER(SEARCH("Series D",K39)),"Series D",IF(ISNUMBER(SEARCH("Private Equity",K39)),"Private Equity","Other"))))))) -> Private Equity | Q39: =IF(IFERROR(SEARCH("ecom",D39),0)+IFERROR(SEARCH("commerce",D39),0)+IFERROR(SEARCH("retail",D39),0)>0,"E-Commerce", IF(IFERROR(SEARCH("fintech",D39),0)+IFERROR(SEARCH("finance",D39),0)+IFERROR(SEARCH("financial",D39),0)+IFERROR(SEARCH("lending",D39),0)+IFERROR(SEARCH("payment",D39),0)+IFERROR(SEARCH("banking",D39),0)+IFERROR(SEARCH("insurance",D39),0)>0,"FinTech", IF(IFERROR(SEARCH("tech",D39),0)+IFERROR(SEARCH("software",D39),0)+IFERROR(SEARCH("saas",D39),0)+IFERROR(SEARCH("ai",D39),0)+IFERROR(SEARCH("iot",D39),0)+IFERROR(SEARCH("cloud",D39),0)+IFERROR(SEARCH("data",D39),0)+IFERROR(SEARCH("analytics",D39),0)>0,"Technology", IF(IFERROR(SEARCH("food",D39),0)+IFERROR(SEARCH("restaurant",D39),0)+IFERROR(SEARCH("hospitality",D39),0)+IFERROR(SEARCH("beverage",D39),0)+IFERROR(SEARCH("delivery",D39),0)>0,"Food & Beverage", IF(IFERROR(SEARCH("health",D39),0)+IFERROR(SEARCH("medical",D39),0)+IFERROR(SEARCH("pharma",D39),0)+IFERROR(SEARCH("wellness",D39),0)+IFERROR(SEARCH("fitness",D39),0)>0,"Healthcare", IF(IFERROR(SEARCH("edu",D39),0)+IFERROR(SEARCH("learning",D39),0)+IFERROR(SEARCH("school",D39),0)+IFERROR(SEARCH("e-tech",D39),0)>0,"Education", IF(IFERROR(SEARCH("logistics",D39),0)+IFERROR(SEARCH("transport",D39),0)+IFERROR(SEARCH("delivery",D39),0)+IFERROR(SEARCH("mobility",D39),0)+IFERROR(SEARCH("automobile",D39),0)>0,"Logistics & Transport", IF(IFERROR(SEARCH("travel",D39),0)+IFERROR(SEARCH("hotel",D39),0)+IFERROR(SEARCH("booking",D39),0)+IFERROR(SEARCH("tourism",D39),0)>0,"Travel & Hospitality", IF(IFERROR(SEARCH("fashion",D39),0)+IFERROR(SEARCH("apparel",D39),0)+IFERROR(SEARCH("clothing",D39),0)+IFERROR(SEARCH("jewelry",D39),0)+IFERROR(SEARCH("beauty",D39),0)>0,"Fashion & Lifestyle", IF(IFERROR(SEARCH("media",D39),0)+IFERROR(SEARCH("entertainment",D39),0)+IFERROR(SEARCH("video",D39),0)+IFERROR(SEARCH("gaming",D39),0)+IFERROR(SEARCH("music",D39),0)+IFERROR(SEARCH("social",D39),0)>0,"Media & Entertainment", IF(IFERROR(SEARCH("agri",D39),0)+IFERROR(SEARCH("farm",D39),0)+IFERROR(SEARCH("agtech",D39),0)>0,"Agriculture", IF(IFERROR(SEARCH("real estate",D39),0)+IFERROR(SEARCH("property",D39),0)+IFERROR(SEARCH("housing",D39),0)>0,"Real Estate", IF(IFERROR(SEARCH("energy",D39),0)+IFERROR(SEARCH("solar",D39),0)+IFERROR(SEARCH("clean tech",D39),0)+IFERROR(SEARCH("waste",D39),0)>0,"Energy & Environment", IF(IFERROR(SEARCH("hr",D39),0)+IFERROR(SEARCH("recruit",D39),0)+IFERROR(SEARCH("hiring",D39),0)+IFERROR(SEARCH("job",D39),0)>0,"HR & Recruitment", "Others")))))))))))))) -> Others | R39: =IF(ISNUMBER(SEARCH("bang",F39)),"Bangalore",IF(ISNUMBER(SEARCH("beng",F39)),"Bangalore",IF(ISNUMBER(SEARCH("mumbai",F39)),"Mumbai",IF(ISNUMBER(SEARCH("delhi",F39)),"Delhi-NCR",IF(ISNUMBER(SEARCH("gurgaon",F39)),"Delhi-NCR",IF(ISNUMBER(SEARCH("gurugram",F39)),"Delhi-NCR",IF(ISNUMBER(SEARCH("noida",F39)),"Delhi-NCR",IF(ISNUMBER(SEARCH("faridabad",F39)),"Delhi-NCR",IF(ISNUMBER(SEARCH("chennai",F39)),"Chennai",IF(ISNUMBER(SEARCH("hyderabad",F39)),"Hyderabad",IF(ISNUMBER(SEARCH("pune",F39)),"Pune",IF(ISNUMBER(SEARCH("kolkata",F39)),"Kolkata",IF(ISNUMBER(SEARCH("ahmedabad",F39)),"Ahmedabad",IF(ISNUMBER(SEARCH("jaipur",F39)),"Jaipur",IF(ISNUMBER(SEARCH("coimbatore",F39)),"Coimbatore",IF(ISNUMBER(SEARCH("kochi",F39)),"Kerala Cities",IF(ISNUMBER(SEARCH("cochin",F39)),"Kerala Cities",IF(ISNUMBER(SEARCH("francisco",F39)),"USA",IF(ISNUMBER(SEARCH("new york",F39)),"USA",IF(ISNUMBER(SEARCH("california",F39)),"USA",IF(ISNUMBER(SEARCH("palo alto",F39)),"USA",IF(ISNUMBER(SEARCH("santa",F39)),"USA",IF(ISNUMBER(SEARCH("singapore",F39)),"Singapore",IF(ISNUMBER(SEARCH("london",F39)),"London/UK",IF(F39="","Unknown","Other Cities"))))))))))))))))))))))))) -> Mumbai
A40: 39 | B40: 43712 | C40: 3rdFlix | D40: SaaS | E40: Education Technology | F40: Hyderabad | G40: Exfinity Venture Partners | H40: =IFERROR(TRIM(LEFT(G40,FIND(",",G40)-1)),TRIM(G40)) -> Exfinity Venture Partners | I40: =IF(TRIM(G40)="",0,LEN(G40)-LEN(SUBSTITUTE(G40,",",""))+1) -> 1 | J40: =IF(Table1[[#This Row],[Investor Count]]>1,"Yes","No") -> No | K40: pre-series A | L40: 5000000 | M40: =YEAR(B40) -> 2019 | N40: =TEXT(B40,"mmmm") -> September | O40: 47.98525 | P40: =IF(ISBLANK(K40),"Unknown",IF(OR(ISNUMBER(SEARCH("seed",K40)),ISNUMBER(SEARCH("Seed",K40))),"Seed",IF(ISNUMBER(SEARCH("Series A",K40)),"Series A",IF(ISNUMBER(SEARCH("Series B",K40)),"Series B",IF(ISNUMBER(SEARCH("Series C",K40)),"Series C",IF(ISNUMBER(SEARCH("Series D",K40)),"Series D",IF(ISNUMBER(SEARCH("Private Equity",K40)),"Private Equity","Other"))))))) -> Series A | Q40: =IF(IFERROR(SEARCH("ecom",D40),0)+IFERROR(SEARCH("commerce",D40),0)+IFERROR(SEARCH("retail",D40),0)>0,"E-Commerce", IF(IFERROR(SEARCH("fintech",D40),0)+IFERROR(SEARCH("finance",D40),0)+IFERROR(SEARCH("financial",D40),0)+IFERROR(SEARCH("lending",D40),0)+IFERROR(SEARCH("payment",D40),0)+IFERROR(SEARCH("banking",D40),0)+IFERROR(SEARCH("insurance",D40),0)>0,"FinTech", IF(IFERROR(SEARCH("tech",D40),0)+IFERROR(SEARCH("software",D40),0)+IFERROR(SEARCH("saas",D40),0)+IFERROR(SEARCH("ai",D40),0)+IFERROR(SEARCH("iot",D40),0)+IFERROR(SEARCH("cloud",D40),0)+IFERROR(SEARCH("data",D40),0)+IFERROR(SEARCH("analytics",D40),0)>0,"Technology", IF(IFERROR(SEARCH("food",D40),0)+IFERROR(SEARCH("restaurant",D40),0)+IFERROR(SEARCH("hospitality",D40),0)+IFERROR(SEARCH("beverage",D40),0)+IFERROR(SEARCH("delivery",D40),0)>0,"Food & Beverage", IF(IFERROR(SEARCH("health",D40),0)+IFERROR(SEARCH("medical",D40),0)+IFERROR(SEARCH("pharma",D40),0)+IFERROR(SEARCH("wellness",D40),0)+IFERROR(SEARCH("fitness",D40),0)>0,"Healthcare", IF(IFERROR(SEARCH("edu",D40),0)+IFERROR(SEARCH("learning",D40),0)+IFERROR(SEARCH("school",D40),0)+IFERROR(SEARCH("e-tech",D40),0)>0,"Education", IF(IFERROR(SEARCH("logistics",D40),0)+IFERROR(SEARCH("transport",D40),0)+IFERROR(SEARCH("delivery",D40),0)+IFERROR(SEARCH("mobility",D40),0)+IFERROR(SEARCH("automobile",D40),0)>0,"Logistics & Transport", IF(IFERROR(SEARCH("travel",D40),0)+IFERROR(SEARCH("hotel",D40),0)+IFERROR(SEARCH("booking",D40),0)+IFERROR(SEARCH("tourism",D40),0)>0,"Travel & Hospitality", IF(IFERROR(SEARCH("fashion",D40),0)+IFERROR(SEARCH("apparel",D40),0)+IFERROR(SEARCH("clothing",D40),0)+IFERROR(SEARCH("jewelry",D40),0)+IFERROR(SEARCH("beauty",D40),0)>0,"Fashion & Lifestyle", IF(IFERROR(SEARCH("media",D40),0)+IFERROR(SEARCH("entertainment",D40),0)+IFERROR(SEARCH("video",D40),0)+IFERROR(SEARCH("gaming",D40),0)+IFERROR(SEARCH("music",D40),0)+IFERROR(SEARCH("social",D40),0)>0,"Media & Entertainment", IF(IFERROR(SEARCH("agri",D40),0)+IFERROR(SEARCH("farm",D40),0)+IFERROR(SEARCH("agtech",D40),0)>0,"Agriculture", IF(IFERROR(SEARCH("real estate",D40),0)+IFERROR(SEARCH("property",D40),0)+IFERROR(SEARCH("housing",D40),0)>0,"Real Estate", IF(IFERROR(SEARCH("energy",D40),0)+IFERROR(SEARCH("solar",D40),0)+IFERROR(SEARCH("clean tech",D40),0)+IFERROR(SEARCH("waste",D40),0)>0,"Energy & Environment", IF(IFERROR(SEARCH("hr",D40),0)+IFERROR(SEARCH("recruit",D40),0)+IFERROR(SEARCH("hiring",D40),0)+IFERROR(SEARCH("job",D40),0)>0,"HR & Recruitment", "Others")))))))))))))) -> Technology | R40: =IF(ISNUMBER(SEARCH("bang",F40)),"Bangalore",IF(ISNUMBER(SEARCH("beng",F40)),"Bangalore",IF(ISNUMBER(SEARCH("mumbai",F40)),"Mumbai",IF(ISNUMBER(SEARCH("delhi",F40)),"Delhi-NCR",IF(ISNUMBER(SEARCH("gurgaon",F40)),"Delhi-NCR",IF(ISNUMBER(SEARCH("gurugram",F40)),"Delhi-NCR",IF(ISNUMBER(SEARCH("noida",F40)),"Delhi-NCR",IF(ISNUMBER(SEARCH("faridabad",F40)),"Delhi-NCR",IF(ISNUMBER(SEARCH("chennai",F40)),"Chennai",IF(ISNUMBER(SEARCH("hyderabad",F40)),"Hyderabad",IF(ISNUMBER(SEARCH("pune",F40)),"Pune",IF(ISNUMBER(SEARCH("kolkata",F40)),"Kolkata",IF(ISNUMBER(SEARCH("ahmedabad",F40)),"Ahmedabad",IF(ISNUMBER(SEARCH("jaipur",F40)),"Jaipur",IF(ISNUMBER(SEARCH("coimbatore",F40)),"Coimbatore",IF(ISNUMBER(SEARCH("kochi",F40)),"Kerala Cities",IF(ISNUMBER(SEARCH("cochin",F40)),"Kerala Cities",IF(ISNUMBER(SEARCH("francisco",F40)),"USA",IF(ISNUMBER(SEARCH("new york",F40)),"USA",IF(ISNUMBER(SEARCH("california",F40)),"USA",IF(ISNUMBER(SEARCH("palo alto",F40)),"USA",IF(ISNUMBER(SEARCH("santa",F40)),"USA",IF(ISNUMBER(SEARCH("singapore",F40)),"Singapore",IF(ISNUMBER(SEARCH("london",F40)),"London/UK",IF(F40="","Unknown","Other Cities"))))))))))))))))))))))))) -> Hyderabad
A41: 40 | B41: 43712 | C41: 75F | D41: IoT | E41: Building automation system | F41: Burnsville | G41: Breakthrough Energy Ventures | H41: =IFERROR(TRIM(LEFT(G41,FIND(",",G41)-1)),TRIM(G41)) -> Breakthrough Energy Ventures | I41: =IF(TRIM(G41)="",0,LEN(G41)-LEN(SUBSTITUTE(G41,",",""))+1) -> 1 | J41: =IF(Table1[[#This Row],[Investor Count]]>1,"Yes","No") -> No | K41: Series A | L41: 18000000 | M41: =YEAR(B41) -> 2019 | N41: =TEXT(B41,"mmmm") -> September | O41: 172.7469 | P41: =IF(ISBLANK(K41),"Unknown",IF(OR(ISNUMBER(SEARCH("seed",K41)),ISNUMBER(SEARCH("Seed",K41))),"Seed",IF(ISNUMBER(SEARCH("Series A",K41)),"Series A",IF(ISNUMBER(SEARCH("Series B",K41)),"Series B",IF(ISNUMBER(SEARCH("Series C",K41)),"Series C",IF(ISNUMBER(SEARCH("Series D",K41)),"Series D",IF(ISNUMBER(SEARCH("Private Equity",K41)),"Private Equity","Other"))))))) -> Series A | Q41: =IF(IFERROR(SEARCH("ecom",D41),0)+IFERROR(SEARCH("commerce",D41),0)+IFERROR(SEARCH("retail",D41),0)>0,"E-Commerce", IF(IFERROR(SEARCH("fintech",D41),0)+IFERROR(SEARCH("finance",D41),0)+IFERROR(SEARCH("financial",D41),0)+IFERROR(SEARCH("lending",D41),0)+IFERROR(SEARCH("payment",D41),0)+IFERROR(SEARCH("banking",D41),0)+IFERROR(SEARCH("insurance",D41),0)>0,"FinTech", IF(IFERROR(SEARCH("tech",D41),0)+IFERROR(SEARCH("software",D41),0)+IFERROR(SEARCH("saas",D41),0)+IFERROR(SEARCH("ai",D41),0)+IFERROR(SEARCH("iot",D41),0)+IFERROR(SEARCH("cloud",D41),0)+IFERROR(SEARCH("data",D41),0)+IFERROR(SEARCH("analytics",D41),0)>0,"Technology", IF(IFERROR(SEARCH("food",D41),0)+IFERROR(SEARCH("restaurant",D41),0)+IFERROR(SEARCH("hospitality",D41),0)+IFERROR(SEARCH("beverage",D41),0)+IFERROR(SEARCH("delivery",D41),0)>0,"Food & Beverage", IF(IFERROR(SEARCH("health",D41),0)+IFERROR(SEARCH("medical",D41),0)+IFERROR(SEARCH("pharma",D41),0)+IFERROR(SEARCH("wellness",D41),0)+IFERROR(SEARCH("fitness",D41),0)>0,"Healthcare", IF(IFERROR(SEARCH("edu",D41),0)+IFERROR(SEARCH("learning",D41),0)+IFERROR(SEARCH("school",D41),0)+IFERROR(SEARCH("e-tech",D41),0)>0,"Education", IF(IFERROR(SEARCH("logistics",D41),0)+IFERROR(SEARCH("transport",D41),0)+IFERROR(SEARCH("delivery",D41),0)+IFERROR(SEARCH("mobility",D41),0)+IFERROR(SEARCH("automobile",D41),0)>0,"Logistics & Transport", IF(IFERROR(SEARCH("travel",D41),0)+IFERROR(SEARCH("hotel",D41),0)+IFERROR(SEARCH("booking",D41),0)+IFERROR(SEARCH("tourism",D41),0)>0,"Travel & Hospitality", IF(IFERROR(SEARCH("fashion",D41),0)+IFERROR(SEARCH("apparel",D41),0)+IFERROR(SEARCH("clothing",D41),0)+IFERROR(SEARCH("jewelry",D41),0)+IFERROR(SEARCH("beauty",D41),0)>0,"Fashion & Lifestyle", IF(IFERROR(SEARCH("media",D41),0)+IFERROR(SEARCH("entertainment",D41),0)+IFERROR(SEARCH("video",D41),0)+IFERROR(SEARCH("gaming",D41),0)+IFERROR(SEARCH("music",D41),0)+IFERROR(SEARCH("social",D41),0)>0,"Media & Entertainment", IF(IFERROR(SEARCH("agri",D41),0)+IFERROR(SEARCH("farm",D41),0)+IFERROR(SEARCH("agtech",D41),0)>0,"Agriculture", IF(IFERROR(SEARCH("real estate",D41),0)+IFERROR(SEARCH("property",D41),0)+IFERROR(SEARCH("housing",D41),0)>0,"Real Estate", IF(IFERROR(SEARCH("energy",D41),0)+IFERROR(SEARCH("solar",D41),0)+IFERROR(SEARCH("clean tech",D41),0)+IFERROR(SEARCH("waste",D41),0)>0,"Energy & Environment", IF(IFERROR(SEARCH("hr",D41),0)+IFERROR(SEARCH("recruit",D41),0)+IFERROR(SEARCH("hiring",D41),0)+IFERROR(SEARCH("job",D41),0)>0,"HR & Recruitment", "Others")))))))))))))) -> Technology | R41: =IF(ISNUMBER(SEARCH("bang",F41)),"Bangalore",IF(ISNUMBER(SEARCH("beng",F41)),"Bangalore",IF(ISNUMBER(SEARCH("mumbai",F41)),"Mumbai",IF(ISNUMBER(SEARCH("delhi",F41)),"Delhi-NCR",IF(ISNUMBER(SEARCH("gurgaon",F41)),"Delhi-NCR",IF(ISNUMBER(SEARCH("gurugram",F41)),"Delhi-NCR",IF(ISNUMBER(SEARCH("noida",F41)),"Delhi-NCR",IF(ISNUMBER(SEARCH("faridabad",F41)),"Delhi-NCR",IF(ISNUMBER(SEARCH("chennai",F41)),"Chennai",IF(ISNUMBER(SEARCH("hyderabad",F41)),"Hyderabad",IF(ISNUMBER(SEARCH("pune",F41)),"Pune",IF(ISNUMBER(SEARCH("kolkata",F41)),"Kolkata",IF(ISNUMBER(SEARCH("ahmedabad",F41)),"Ahmedabad",IF(ISNUMBER(SEARCH("jaipur",F41)),"Jaipur",IF(ISNUMBER(SEARCH("coimbatore",F41)),"Coimbatore",IF(ISNUMBER(SEARCH("kochi",F41)),"Kerala Cities",IF(ISNUMBER(SEARCH("cochin",F41)),"Kerala Cities",IF(ISNUMBER(SEARCH("francisco",F41)),"USA",IF(ISNUMBER(SEARCH("new york",F41)),"USA",IF(ISNUMBER(SEARCH("california",F41)),"USA",IF(ISNUMBER(SEARCH("palo alto",F41)),"USA",IF(ISNUMBER(SEARCH("santa",F41)),"USA",IF(ISNUMBER(SEARCH("singapore",F41)),"Singapore",IF(ISNUMBER(SEARCH("london",F41)),"London/UK",IF(F41="","Unknown","Other Cities"))))))))))))))))))))))))) -> Other Cities
A42: 41 | B42: 43712 | C42: Myelin Foundry | D42: Information Technology | E42: Deep-technology | F42: Bengaluru | G42: Endiya Partners | H42: =IFERROR(TRIM(LEFT(G42,FIND(",",G42)-1)),TRIM(G42)) -> Endiya Partners | I42: =IF(TRIM(G42)="",0,LEN(G42)-LEN(SUBSTITUTE(G42,",",""))+1) -> 1 | J42: =IF(Table1[[#This Row],[Investor Count]]>1,"Yes","No") -> No | K42: Seed | L42: 1000000 | M42: =YEAR(B42) -> 2019 | N42: =TEXT(B42,"mmmm") -> September | O42: 9.59705 | P42: =IF(ISBLANK(K42),"Unknown",IF(OR(ISNUMBER(SEARCH("seed",K42)),ISNUMBER(SEARCH("Seed",K42))),"Seed",IF(ISNUMBER(SEARCH("Series A",K42)),"Series A",IF(ISNUMBER(SEARCH("Series B",K42)),"Series B",IF(ISNUMBER(SEARCH("Series C",K42)),"Series C",IF(ISNUMBER(SEARCH("Series D",K42)),"Series D",IF(ISNUMBER(SEARCH("Private Equity",K42)),"Private Equity","Other"))))))) -> Seed | Q42: =IF(IFERROR(SEARCH("ecom",D42),0)+IFERROR(SEARCH("commerce",D42),0)+IFERROR(SEARCH("retail",D42),0)>0,"E-Commerce", IF(IFERROR(SEARCH("fintech",D42),0)+IFERROR(SEARCH("finance",D42),0)+IFERROR(SEARCH("financial",D42),0)+IFERROR(SEARCH("lending",D42),0)+IFERROR(SEARCH("payment",D42),0)+IFERROR(SEARCH("banking",D42),0)+IFERROR(SEARCH("insurance",D42),0)>0,"FinTech", IF(IFERROR(SEARCH("tech",D42),0)+IFERROR(SEARCH("software",D42),0)+IFERROR(SEARCH("saas",D42),0)+IFERROR(SEARCH("ai",D42),0)+IFERROR(SEARCH("iot",D42),0)+IFERROR(SEARCH("cloud",D42),0)+IFERROR(SEARCH("data",D42),0)+IFERROR(SEARCH("analytics",D42),0)>0,"Technology", IF(IFERROR(SEARCH("food",D42),0)+IFERROR(SEARCH("restaurant",D42),0)+IFERROR(SEARCH("hospitality",D42),0)+IFERROR(SEARCH("beverage",D42),0)+IFERROR(SEARCH("delivery",D42),0)>0,"Food & Beverage", IF(IFERROR(SEARCH("health",D42),0)+IFERROR(SEARCH("medical",D42),0)+IFERROR(SEARCH("pharma",D42),0)+IFERROR(SEARCH("wellness",D42),0)+IFERROR(SEARCH("fitness",D42),0)>0,"Healthcare", IF(IFERROR(SEARCH("edu",D42),0)+IFERROR(SEARCH("learning",D42),0)+IFERROR(SEARCH("school",D42),0)+IFERROR(SEARCH("e-tech",D42),0)>0,"Education", IF(IFERROR(SEARCH("logistics",D42),0)+IFERROR(SEARCH("transport",D42),0)+IFERROR(SEARCH("delivery",D42),0)+IFERROR(SEARCH("mobility",D42),0)+IFERROR(SEARCH("automobile",D42),0)>0,"Logistics & Transport", IF(IFERROR(SEARCH("travel",D42),0)+IFERROR(SEARCH("hotel",D42),0)+IFERROR(SEARCH("booking",D42),0)+IFERROR(SEARCH("tourism",D42),0)>0,"Travel & Hospitality", IF(IFERROR(SEARCH("fashion",D42),0)+IFERROR(SEARCH("apparel",D42),0)+IFERROR(SEARCH("clothing",D42),0)+IFERROR(SEARCH("jewelry",D42),0)+IFERROR(SEARCH("beauty",D42),0)>0,"Fashion & Lifestyle", IF(IFERROR(SEARCH("media",D42),0)+IFERROR(SEARCH("entertainment",D42),0)+IFERROR(SEARCH("video",D42),0)+IFERROR(SEARCH("gaming",D42),0)+IFERROR(SEARCH("music",D42),0)+IFERROR(SEARCH("social",D42),0)>0,"Media & Entertainment", IF(IFERROR(SEARCH("agri",D42),0)+IFERROR(SEARCH("farm",D42),0)+IFERROR(SEARCH("agtech",D42),0)>0,"Agriculture", IF(IFERROR(SEARCH("real estate",D42),0)+IFERROR(SEARCH("property",D42),0)+IFERROR(SEARCH("housing",D42),0)>0,"Real Estate", IF(IFERROR(SEARCH("energy",D42),0)+IFERROR(SEARCH("solar",D42),0)+IFERROR(SEARCH("clean tech",D42),0)+IFERROR(SEARCH("waste",D42),0)>0,"Energy & Environment", IF(IFERROR(SEARCH("hr",D42),0)+IFERROR(SEARCH("recruit",D42),0)+IFERROR(SEARCH("hiring",D42),0)+IFERROR(SEARCH("job",D42),0)>0,"HR & Recruitment", "Others")))))))))))))) -> Technology | R42: =IF(ISNUMBER(SEARCH("bang",F42)),"Bangalore",IF(ISNUMBER(SEARCH("beng",F42)),"Bangalore",IF(ISNUMBER(SEARCH("mumbai",F42)),"Mumbai",IF(ISNUMBER(SEARCH("delhi",F42)),"Delhi-NCR",IF(ISNUMBER(SEARCH("gurgaon",F42)),"Delhi-NCR",IF(ISNUMBER(SEARCH("gurugram",F42)),"Delhi-NCR",IF(ISNUMBER(SEARCH("noida",F42)),"Delhi-NCR",IF(ISNUMBER(SEARCH("faridabad",F42)),"Delhi-NCR",IF(ISNUMBER(SEARCH("chennai",F42)),"Chennai",IF(ISNUMBER(SEARCH("hyderabad",F42)),"Hyderabad",IF(ISNUMBER(SEARCH("pune",F42)),"Pune",IF(ISNUMBER(SEARCH("kolkata",F42)),"Kolkata",IF(ISNUMBER(SEARCH("ahmedabad",F42)),"Ahmedabad",IF(ISNUMBER(SEARCH("jaipur",F42)),"Jaipur",IF(ISNUMBER(SEARCH("coimbatore",F42)),"Coimbatore",IF(ISNUMBER(SEARCH("kochi",F42)),"Kerala Cities",IF(ISNUMBER(SEARCH("cochin",F42)),"Kerala Cities",IF(ISNUMBER(SEARCH("francisco",F42)),"USA",IF(ISNUMBER(SEARCH("new york",F42)),"USA",IF(ISNUMBER(SEARCH("california",F42)),"USA",IF(ISNUMBER(SEARCH("palo alto",F42)),"USA",IF(ISNUMBER(SEARCH("santa",F42)),"USA",IF(ISNUMBER(SEARCH("singapore",F42)),"Singapore",IF(ISNUMBER(SEARCH("london",F42)),"London/UK",IF(F42="","Unknown","Other Cities"))))))))))))))))))))))))) -> Bangalore
A43: 42 | B43: 43712 | C43: Atomberg Technology | D43: Consumer Technology | E43: Consumer Electronics, Home Appliances | F43: Mumbai | G43: A91 Partners | H43: =IFERROR(TRIM(LEFT(G43,FIND(",",G43)-1)),TRIM(G43)) -> A91 Partners | I43: =IF(TRIM(G43)="",0,LEN(G43)-LEN(SUBSTITUTE(G43,",",""))+1) -> 1 | J43: =IF(Table1[[#This Row],[Investor Count]]>1,"Yes","No") -> No | K43: Series A | L43: 10000000 | M43: =YEAR(B43) -> 2019 | N43: =TEXT(B43,"mmmm") -> September | O43: 95.9705 | P43: =IF(ISBLANK(K43),"Unknown",IF(OR(ISNUMBER(SEARCH("seed",K43)),ISNUMBER(SEARCH("Seed",K43))),"Seed",IF(ISNUMBER(SEARCH("Series A",K43)),"Series A",IF(ISNUMBER(SEARCH("Series B",K43)),"Series B",IF(ISNUMBER(SEARCH("Series C",K43)),"Series C",IF(ISNUMBER(SEARCH("Series D",K43)),"Series D",IF(ISNUMBER(SEARCH("Private Equity",K43)),"Private Equity","Other"))))))) -> Series A | Q43: =IF(IFERROR(SEARCH("ecom",D43),0)+IFERROR(SEARCH("commerce",D43),0)+IFERROR(SEARCH("retail",D43),0)>0,"E-Commerce", IF(IFERROR(SEARCH("fintech",D43),0)+IFERROR(SEARCH("finance",D43),0)+IFERROR(SEARCH("financial",D43),0)+IFERROR(SEARCH("lending",D43),0)+IFERROR(SEARCH("payment",D43),0)+IFERROR(SEARCH("banking",D43),0)+IFERROR(SEARCH("insurance",D43),0)>0,"FinTech", IF(IFERROR(SEARCH("tech",D43),0)+IFERROR(SEARCH("software",D43),0)+IFERROR(SEARCH("saas",D43),0)+IFERROR(SEARCH("ai",D43),0)+IFERROR(SEARCH("iot",D43),0)+IFERROR(SEARCH("cloud",D43),0)+IFERROR(SEARCH("data",D43),0)+IFERROR(SEARCH("analytics",D43),0)>0,"Technology", IF(IFERROR(SEARCH("food",D43),0)+IFERROR(SEARCH("restaurant",D43),0)+IFERROR(SEARCH("hospitality",D43),0)+IFERROR(SEARCH("beverage",D43),0)+IFERROR(SEARCH("delivery",D43),0)>0,"Food & Beverage", IF(IFERROR(SEARCH("health",D43),0)+IFERROR(SEARCH("medical",D43),0)+IFERROR(SEARCH("pharma",D43),0)+IFERROR(SEARCH("wellness",D43),0)+IFERROR(SEARCH("fitness",D43),0)>0,"Healthcare", IF(IFERROR(SEARCH("edu",D43),0)+IFERROR(SEARCH("learning",D43),0)+IFERROR(SEARCH("school",D43),0)+IFERROR(SEARCH("e-tech",D43),0)>0,"Education", IF(IFERROR(SEARCH("logistics",D43),0)+IFERROR(SEARCH("transport",D43),0)+IFERROR(SEARCH("delivery",D43),0)+IFERROR(SEARCH("mobility",D43),0)+IFERROR(SEARCH("automobile",D43),0)>0,"Logistics & Transport", IF(IFERROR(SEARCH("travel",D43),0)+IFERROR(SEARCH("hotel",D43),0)+IFERROR(SEARCH("booking",D43),0)+IFERROR(SEARCH("tourism",D43),0)>0,"Travel & Hospitality", IF(IFERROR(SEARCH("fashion",D43),0)+IFERROR(SEARCH("apparel",D43),0)+IFERROR(SEARCH("clothing",D43),0)+IFERROR(SEARCH("jewelry",D43),0)+IFERROR(SEARCH("beauty",D43),0)>0,"Fashion & Lifestyle", IF(IFERROR(SEARCH("media",D43),0)+IFERROR(SEARCH("entertainment",D43),0)+IFERROR(SEARCH("video",D43),0)+IFERROR(SEARCH("gaming",D43),0)+IFERROR(SEARCH("music",D43),0)+IFERROR(SEARCH("social",D43),0)>0,"Media & Entertainment", IF(IFERROR(SEARCH("agri",D43),0)+IFERROR(SEARCH("farm",D43),0)+IFERROR(SEARCH("agtech",D43),0)>0,"Agriculture", IF(IFERROR(SEARCH("real estate",D43),0)+IFERROR(SEARCH("property",D43),0)+IFERROR(SEARCH("housing",D43),0)>0,"Real Estate", IF(IFERROR(SEARCH("energy",D43),0)+IFERROR(SEARCH("solar",D43),0)+IFERROR(SEARCH("clean tech",D43),0)+IFERROR(SEARCH("waste",D43),0)>0,"Energy & Environment", IF(IFERROR(SEARCH("hr",D43),0)+IFERROR(SEARCH("recruit",D43),0)+IFERROR(SEARCH("hiring",D43),0)+IFERROR(SEARCH("job",D43),0)>0,"HR & Recruitment", "Others")))))))))))))) -> Technology | R43: =IF(ISNUMBER(SEARCH("bang",F43)),"Bangalore",IF(ISNUMBER(SEARCH("beng",F43)),"Bangalore",IF(ISNUMBER(SEARCH("mumbai",F43)),"Mumbai",IF(ISNUMBER(SEARCH("delhi",F43)),"Delhi-NCR",IF(ISNUMBER(SEARCH("gurgaon",F43)),"Delhi-NCR",IF(ISNUMBER(SEARCH("gurugram",F43)),"Delhi-NCR",IF(ISNUMBER(SEARCH("noida",F43)),"Delhi-NCR",IF(ISNUMBER(SEARCH("faridabad",F43)),"Delhi-NCR",IF(ISNUMBER(SEARCH("chennai",F43)),"Chennai",IF(ISNUMBER(SEARCH("hyderabad",F43)),"Hyderabad",IF(ISNUMBER(SEARCH("pune",F43)),"Pune",IF(ISNUMBER(SEARCH("kolkata",F43)),"Kolkata",IF(ISNUMBER(SEARCH("ahmedabad",F43)),"Ahmedabad",IF(ISNUMBER(SEARCH("jaipur",F43)),"Jaipur",IF(ISNUMBER(SEARCH("coimbatore",F43)),"Coimbatore",IF(ISNUMBER(SEARCH("kochi",F43)),"Kerala Cities",IF(ISNUMBER(SEARCH("cochin",F43)),"Kerala Cities",IF(ISNUMBER(SEARCH("francisco",F43)),"USA",IF(ISNUMBER(SEARCH("new york",F43)),"USA",IF(ISNUMBER(SEARCH("california",F43)),"USA",IF(ISNUMBER(SEARCH("palo alto",F43)),"USA",IF(ISNUMBER(SEARCH("santa",F43)),"USA",IF(ISNUMBER(SEARCH("singapore",F43)),"Singapore",IF(ISNUMBER(SEARCH("london",F43)),"London/UK",IF(F43="","Unknown","Other Cities"))))))))))))))))))))))))) -> Mumbai
A44: 43 | B44: 43712 | C44: GOQii | D44: Healthcare | E44: Wearable Fitness B,s | F44: Menlo Park | G44: Bennett Coleman , Company Ltd | H44: =IFERROR(TRIM(LEFT(G44,FIND(",",G44)-1)),TRIM(G44)) -> Bennett Coleman | I44: =IF(TRIM(G44)="",0,LEN(G44)-LEN(SUBSTITUTE(G44,",",""))+1) -> 2 | J44: =IF(Table1[[#This Row],[Investor Count]]>1,"Yes","No") -> Yes | K44: Series C | L44: 450000000 | M44: =YEAR(B44) -> 2019 | N44: =TEXT(B44,"mmmm") -> September | O44: 4318.6725 | P44: =IF(ISBLANK(K44),"Unknown",IF(OR(ISNUMBER(SEARCH("seed",K44)),ISNUMBER(SEARCH("Seed",K44))),"Seed",IF(ISNUMBER(SEARCH("Series A",K44)),"Series A",IF(ISNUMBER(SEARCH("Series B",K44)),"Series B",IF(ISNUMBER(SEARCH("Series C",K44)),"Series C",IF(ISNUMBER(SEARCH("Series D",K44)),"Series D",IF(ISNUMBER(SEARCH("Private Equity",K44)),"Private Equity","Other"))))))) -> Series C | Q44: =IF(IFERROR(SEARCH("ecom",D44),0)+IFERROR(SEARCH("commerce",D44),0)+IFERROR(SEARCH("retail",D44),0)>0,"E-Commerce", IF(IFERROR(SEARCH("fintech",D44),0)+IFERROR(SEARCH("finance",D44),0)+IFERROR(SEARCH("financial",D44),0)+IFERROR(SEARCH("lending",D44),0)+IFERROR(SEARCH("payment",D44),0)+IFERROR(SEARCH("banking",D44),0)+IFERROR(SEARCH("insurance",D44),0)>0,"FinTech", IF(IFERROR(SEARCH("tech",D44),0)+IFERROR(SEARCH("software",D44),0)+IFERROR(SEARCH("saas",D44),0)+IFERROR(SEARCH("ai",D44),0)+IFERROR(SEARCH("iot",D44),0)+IFERROR(SEARCH("cloud",D44),0)+IFERROR(SEARCH("data",D44),0)+IFERROR(SEARCH("analytics",D44),0)>0,"Technology", IF(IFERROR(SEARCH("food",D44),0)+IFERROR(SEARCH("restaurant",D44),0)+IFERROR(SEARCH("hospitality",D44),0)+IFERROR(SEARCH("beverage",D44),0)+IFERROR(SEARCH("delivery",D44),0)>0,"Food & Beverage", IF(IFERROR(SEARCH("health",D44),0)+IFERROR(SEARCH("medical",D44),0)+IFERROR(SEARCH("pharma",D44),0)+IFERROR(SEARCH("wellness",D44),0)+IFERROR(SEARCH("fitness",D44),0)>0,"Healthcare", IF(IFERROR(SEARCH("edu",D44),0)+IFERROR(SEARCH("learning",D44),0)+IFERROR(SEARCH("school",D44),0)+IFERROR(SEARCH("e-tech",D44),0)>0,"Education", IF(IFERROR(SEARCH("logistics",D44),0)+IFERROR(SEARCH("transport",D44),0)+IFERROR(SEARCH("delivery",D44),0)+IFERROR(SEARCH("mobility",D44),0)+IFERROR(SEARCH("automobile",D44),0)>0,"Logistics & Transport", IF(IFERROR(SEARCH("travel",D44),0)+IFERROR(SEARCH("hotel",D44),0)+IFERROR(SEARCH("booking",D44),0)+IFERROR(SEARCH("tourism",D44),0)>0,"Travel & Hospitality", IF(IFERROR(SEARCH("fashion",D44),0)+IFERROR(SEARCH("apparel",D44),0)+IFERROR(SEARCH("clothing",D44),0)+IFERROR(SEARCH("jewelry",D44),0)+IFERROR(SEARCH("beauty",D44),0)>0,"Fashion & Lifestyle", IF(IFERROR(SEARCH("media",D44),0)+IFERROR(SEARCH("entertainment",D44),0)+IFERROR(SEARCH("video",D44),0)+IFERROR(SEARCH("gaming",D44),0)+IFERROR(SEARCH("music",D44),0)+IFERROR(SEARCH("social",D44),0)>0,"Media & Entertainment", IF(IFERROR(SEARCH("agri",D44),0)+IFERROR(SEARCH("farm",D44),0)+IFERROR(SEARCH("agtech",D44),0)>0,"Agriculture", IF(IFERROR(SEARCH("real estate",D44),0)+IFERROR(SEARCH("property",D44),0)+IFERROR(SEARCH("housing",D44),0)>0,"Real Estate", IF(IFERROR(SEARCH("energy",D44),0)+IFERROR(SEARCH("solar",D44),0)+IFERROR(SEARCH("clean tech",D44),0)+IFERROR(SEARCH("waste",D44),0)>0,"Energy & Environment", IF(IFERROR(SEARCH("hr",D44),0)+IFERROR(SEARCH("recruit",D44),0)+IFERROR(SEARCH("hiring",D44),0)+IFERROR(SEARCH("job",D44),0)>0,"HR & Recruitment", "Others")))))))))))))) -> Healthcare | R44: =IF(ISNUMBER(SEARCH("bang",F44)),"Bangalore",IF(ISNUMBER(SEARCH("beng",F44)),"Bangalore",IF(ISNUMBER(SEARCH("mumbai",F44)),"Mumbai",IF(ISNUMBER(SEARCH("delhi",F44)),"Delhi-NCR",IF(ISNUMBER(SEARCH("gurgaon",F44)),"Delhi-NCR",IF(ISNUMBER(SEARCH("gurugram",F44)),"Delhi-NCR",IF(ISNUMBER(SEARCH("noida",F44)),"Delhi-NCR",IF(ISNUMBER(SEARCH("faridabad",F44)),"Delhi-NCR",IF(ISNUMBER(SEARCH("chennai",F44)),"Chennai",IF(ISNUMBER(SEARCH("hyderabad",F44)),"Hyderabad",IF(ISNUMBER(SEARCH("pune",F44)),"Pune",IF(ISNUMBER(SEARCH("kolkata",F44)),"Kolkata",IF(ISNUMBER(SEARCH("ahmedabad",F44)),"Ahmedabad",IF(ISNUMBER(SEARCH("jaipur",F44)),"Jaipur",IF(ISNUMBER(SEARCH("coimbatore",F44)),"Coimbatore",IF(ISNUMBER(SEARCH("kochi",F44)),"Kerala Cities",IF(ISNUMBER(SEARCH("cochin",F44)),"Kerala Cities",IF(ISNUMBER(SEARCH("francisco",F44)),"USA",IF(ISNUMBER(SEARCH("new york",F44)),"USA",IF(ISNUMBER(SEARCH("california",F44)),"USA",IF(ISNUMBER(SEARCH("palo alto",F44)),"USA",IF(ISNUMBER(SEARCH("santa",F44)),"USA",IF(ISNUMBER(SEARCH("singapore",F44)),"Singapore",IF(ISNUMBER(SEARCH("london",F44)),"London/UK",IF(F44="","Unknown","Other Cities"))))))))))))))))))))))))) -> Other Cities
A45: 44 | B45: 43711 | C45: Vyapar App | D45: Accounting | E45: Mobile-based Accounting Software | F45: Bengaluru | G45: India Quotient, Axilor Ventures | H45: =IFERROR(TRIM(LEFT(G45,FIND(",",G45)-1)),TRIM(G45)) -> India Quotient | I45: =IF(TRIM(G45)="",0,LEN(G45)-LEN(SUBSTITUTE(G45,",",""))+1) -> 2 | J45: =IF(Table1[[#This Row],[Investor Count]]>1,"Yes","No") -> Yes | K45: Series A | L45: 5000000 | M45: =YEAR(B45) -> 2019 | N45: =TEXT(B45,"mmmm") -> September | O45: 47.98525 | P45: =IF(ISBLANK(K45),"Unknown",IF(OR(ISNUMBER(SEARCH("seed",K45)),ISNUMBER(SEARCH("Seed",K45))),"Seed",IF(ISNUMBER(SEARCH("Series A",K45)),"Series A",IF(ISNUMBER(SEARCH("Series B",K45)),"Series B",IF(ISNUMBER(SEARCH("Series C",K45)),"Series C",IF(ISNUMBER(SEARCH("Series D",K45)),"Series D",IF(ISNUMBER(SEARCH("Private Equity",K45)),"Private Equity","Other"))))))) -> Series A | Q45: =IF(IFERROR(SEARCH("ecom",D45),0)+IFERROR(SEARCH("commerce",D45),0)+IFERROR(SEARCH("retail",D45),0)>0,"E-Commerce", IF(IFERROR(SEARCH("fintech",D45),0)+IFERROR(SEARCH("finance",D45),0)+IFERROR(SEARCH("financial",D45),0)+IFERROR(SEARCH("lending",D45),0)+IFERROR(SEARCH("payment",D45),0)+IFERROR(SEARCH("banking",D45),0)+IFERROR(SEARCH("insurance",D45),0)>0,"FinTech", IF(IFERROR(SEARCH("tech",D45),0)+IFERROR(SEARCH("software",D45),0)+IFERROR(SEARCH("saas",D45),0)+IFERROR(SEARCH("ai",D45),0)+IFERROR(SEARCH("iot",D45),0)+IFERROR(SEARCH("cloud",D45),0)+IFERROR(SEARCH("data",D45),0)+IFERROR(SEARCH("analytics",D45),0)>0,"Technology", IF(IFERROR(SEARCH("food",D45),0)+IFERROR(SEARCH("restaurant",D45),0)+IFERROR(SEARCH("hospitality",D45),0)+IFERROR(SEARCH("beverage",D45),0)+IFERROR(SEARCH("delivery",D45),0)>0,"Food & Beverage", IF(IFERROR(SEARCH("health",D45),0)+IFERROR(SEARCH("medical",D45),0)+IFERROR(SEARCH("pharma",D45),0)+IFERROR(SEARCH("wellness",D45),0)+IFERROR(SEARCH("fitness",D45),0)>0,"Healthcare", IF(IFERROR(SEARCH("edu",D45),0)+IFERROR(SEARCH("learning",D45),0)+IFERROR(SEARCH("school",D45),0)+IFERROR(SEARCH("e-tech",D45),0)>0,"Education", IF(IFERROR(SEARCH("logistics",D45),0)+IFERROR(SEARCH("transport",D45),0)+IFERROR(SEARCH("delivery",D45),0)+IFERROR(SEARCH("mobility",D45),0)+IFERROR(SEARCH("automobile",D45),0)>0,"Logistics & Transport", IF(IFERROR(SEARCH("travel",D45),0)+IFERROR(SEARCH("hotel",D45),0)+IFERROR(SEARCH("booking",D45),0)+IFERROR(SEARCH("tourism",D45),0)>0,"Travel & Hospitality", IF(IFERROR(SEARCH("fashion",D45),0)+IFERROR(SEARCH("apparel",D45),0)+IFERROR(SEARCH("clothing",D45),0)+IFERROR(SEARCH("jewelry",D45),0)+IFERROR(SEARCH("beauty",D45),0)>0,"Fashion & Lifestyle", IF(IFERROR(SEARCH("media",D45),0)+IFERROR(SEARCH("entertainment",D45),0)+IFERROR(SEARCH("video",D45),0)+IFERROR(SEARCH("gaming",D45),0)+IFERROR(SEARCH("music",D45),0)+IFERROR(SEARCH("social",D45),0)>0,"Media & Entertainment", IF(IFERROR(SEARCH("agri",D45),0)+IFERROR(SEARCH("farm",D45),0)+IFERROR(SEARCH("agtech",D45),0)>0,"Agriculture", IF(IFERROR(SEARCH("real estate",D45),0)+IFERROR(SEARCH("property",D45),0)+IFERROR(SEARCH("housing",D45),0)>0,"Real Estate", IF(IFERROR(SEARCH("energy",D45),0)+IFERROR(SEARCH("solar",D45),0)+IFERROR(SEARCH("clean tech",D45),0)+IFERROR(SEARCH("waste",D45),0)>0,"Energy & Environment", IF(IFERROR(SEARCH("hr",D45),0)+IFERROR(SEARCH("recruit",D45),0)+IFERROR(SEARCH("hiring",D45),0)+IFERROR(SEARCH("job",D45),0)>0,"HR & Recruitment", "Others")))))))))))))) -> Others | R45: =IF(ISNUMBER(SEARCH("bang",F45)),"Bangalore",IF(ISNUMBER(SEARCH("beng",F45)),"Bangalore",IF(ISNUMBER(SEARCH("mumbai",F45)),"Mumbai",IF(ISNUMBER(SEARCH("delhi",F45)),"Delhi-NCR",IF(ISNUMBER(SEARCH("gurgaon",F45)),"Delhi-NCR",IF(ISNUMBER(SEARCH("gurugram",F45)),"Delhi-NCR",IF(ISNUMBER(SEARCH("noida",F45)),"Delhi-NCR",IF(ISNUMBER(SEARCH("faridabad",F45)),"Delhi-NCR",IF(ISNUMBER(SEARCH("chennai",F45)),"Chennai",IF(ISNUMBER(SEARCH("hyderabad",F45)),"Hyderabad",IF(ISNUMBER(SEARCH("pune",F45)),"Pune",IF(ISNUMBER(SEARCH("kolkata",F45)),"Kolkata",IF(ISNUMBER(SEARCH("ahmedabad",F45)),"Ahmedabad",IF(ISNUMBER(SEARCH("jaipur",F45)),"Jaipur",IF(ISNUMBER(SEARCH("coimbatore",F45)),"Coimbatore",IF(ISNUMBER(SEARCH("kochi",F45)),"Kerala Cities",IF(ISNUMBER(SEARCH("cochin",F45)),"Kerala Cities",IF(ISNUMBER(SEARCH("francisco",F45)),"USA",IF(ISNUMBER(SEARCH("new york",F45)),"USA",IF(ISNUMBER(SEARCH("california",F45)),"USA",IF(ISNUMBER(SEARCH("palo alto",F45)),"USA",IF(ISNUMBER(SEARCH("santa",F45)),"USA",IF(ISNUMBER(SEARCH("singapore",F45)),"Singapore",IF(ISNUMBER(SEARCH("london",F45)),"London/UK",IF(F45="","Unknown","Other Cities"))))))))))))))))))))))))) -> Bangalore
A46: 45 | B46: 43678 | C46: CarDekho | D46: Ecommerce | E46: Automotive | F46: Gurgaon | G46: Sc Gg India Mobility Holdings Llc | H46: =IFERROR(TRIM(LEFT(G46,FIND(",",G46)-1)),TRIM(G46)) -> Sc Gg India Mobility Holdings Llc | I46: =IF(TRIM(G46)="",0,LEN(G46)-LEN(SUBSTITUTE(G46,",",""))+1) -> 1 | J46: =IF(Table1[[#This Row],[Investor Count]]>1,"Yes","No") -> No | K46: Series C | L46: 20000000 | M46: =YEAR(B46) -> 2019 | N46: =TEXT(B46,"mmmm") -> August | O46: 191.941 | P46: =IF(ISBLANK(K46),"Unknown",IF(OR(ISNUMBER(SEARCH("seed",K46)),ISNUMBER(SEARCH("Seed",K46))),"Seed",IF(ISNUMBER(SEARCH("Series A",K46)),"Series A",IF(ISNUMBER(SEARCH("Series B",K46)),"Series B",IF(ISNUMBER(SEARCH("Series C",K46)),"Series C",IF(ISNUMBER(SEARCH("Series D",K46)),"Series D",IF(ISNUMBER(SEARCH("Private Equity",K46)),"Private Equity","Other"))))))) -> Series C | Q46: =IF(IFERROR(SEARCH("ecom",D46),0)+IFERROR(SEARCH("commerce",D46),0)+IFERROR(SEARCH("retail",D46),0)>0,"E-Commerce", IF(IFERROR(SEARCH("fintech",D46),0)+IFERROR(SEARCH("finance",D46),0)+IFERROR(SEARCH("financial",D46),0)+IFERROR(SEARCH("lending",D46),0)+IFERROR(SEARCH("payment",D46),0)+IFERROR(SEARCH("banking",D46),0)+IFERROR(SEARCH("insurance",D46),0)>0,"FinTech", IF(IFERROR(SEARCH("tech",D46),0)+IFERROR(SEARCH("software",D46),0)+IFERROR(SEARCH("saas",D46),0)+IFERROR(SEARCH("ai",D46),0)+IFERROR(SEARCH("iot",D46),0)+IFERROR(SEARCH("cloud",D46),0)+IFERROR(SEARCH("data",D46),0)+IFERROR(SEARCH("analytics",D46),0)>0,"Technology", IF(IFERROR(SEARCH("food",D46),0)+IFERROR(SEARCH("restaurant",D46),0)+IFERROR(SEARCH("hospitality",D46),0)+IFERROR(SEARCH("beverage",D46),0)+IFERROR(SEARCH("delivery",D46),0)>0,"Food & Beverage", IF(IFERROR(SEARCH("health",D46),0)+IFERROR(SEARCH("medical",D46),0)+IFERROR(SEARCH("pharma",D46),0)+IFERROR(SEARCH("wellness",D46),0)+IFERROR(SEARCH("fitness",D46),0)>0,"Healthcare", IF(IFERROR(SEARCH("edu",D46),0)+IFERROR(SEARCH("learning",D46),0)+IFERROR(SEARCH("school",D46),0)+IFERROR(SEARCH("e-tech",D46),0)>0,"Education", IF(IFERROR(SEARCH("logistics",D46),0)+IFERROR(SEARCH("transport",D46),0)+IFERROR(SEARCH("delivery",D46),0)+IFERROR(SEARCH("mobility",D46),0)+IFERROR(SEARCH("automobile",D46),0)>0,"Logistics & Transport", IF(IFERROR(SEARCH("travel",D46),0)+IFERROR(SEARCH("hotel",D46),0)+IFERROR(SEARCH("booking",D46),0)+IFERROR(SEARCH("tourism",D46),0)>0,"Travel & Hospitality", IF(IFERROR(SEARCH("fashion",D46),0)+IFERROR(SEARCH("apparel",D46),0)+IFERROR(SEARCH("clothing",D46),0)+IFERROR(SEARCH("jewelry",D46),0)+IFERROR(SEARCH("beauty",D46),0)>0,"Fashion & Lifestyle", IF(IFERROR(SEARCH("media",D46),0)+IFERROR(SEARCH("entertainment",D46),0)+IFERROR(SEARCH("video",D46),0)+IFERROR(SEARCH("gaming",D46),0)+IFERROR(SEARCH("music",D46),0)+IFERROR(SEARCH("social",D46),0)>0,"Media & Entertainment", IF(IFERROR(SEARCH("agri",D46),0)+IFERROR(SEARCH("farm",D46),0)+IFERROR(SEARCH("agtech",D46),0)>0,"Agriculture", IF(IFERROR(SEARCH("real estate",D46),0)+IFERROR(SEARCH("property",D46),0)+IFERROR(SEARCH("housing",D46),0)>0,"Real Estate", IF(IFERROR(SEARCH("energy",D46),0)+IFERROR(SEARCH("solar",D46),0)+IFERROR(SEARCH("clean tech",D46),0)+IFERROR(SEARCH("waste",D46),0)>0,"Energy & Environment", IF(IFERROR(SEARCH("hr",D46),0)+IFERROR(SEARCH("recruit",D46),0)+IFERROR(SEARCH("hiring",D46),0)+IFERROR(SEARCH("job",D46),0)>0,"HR & Recruitment", "Others")))))))))))))) -> E-Commerce | R46: =IF(ISNUMBER(SEARCH("bang",F46)),"Bangalore",IF(ISNUMBER(SEARCH("beng",F46)),"Bangalore",IF(ISNUMBER(SEARCH("mumbai",F46)),"Mumbai",IF(ISNUMBER(SEARCH("delhi",F46)),"Delhi-NCR",IF(ISNUMBER(SEARCH("gurgaon",F46)),"Delhi-NCR",IF(ISNUMBER(SEARCH("gurugram",F46)),"Delhi-NCR",IF(ISNUMBER(SEARCH("noida",F46)),"Delhi-NCR",IF(ISNUMBER(SEARCH("faridabad",F46)),"Delhi-NCR",IF(ISNUMBER(SEARCH("chennai",F46)),"Chennai",IF(ISNUMBER(SEARCH("hyderabad",F46)),"Hyderabad",IF(ISNUMBER(SEARCH("pune",F46)),"Pune",IF(ISNUMBER(SEARCH("kolkata",F46)),"Kolkata",IF(ISNUMBER(SEARCH("ahmedabad",F46)),"Ahmedabad",IF(ISNUMBER(SEARCH("jaipur",F46)),"Jaipur",IF(ISNUMBER(SEARCH("coimbatore",F46)),"Coimbatore",IF(ISNUMBER(SEARCH("kochi",F46)),"Kerala Cities",IF(ISNUMBER(SEARCH("cochin",F46)),"Kerala Cities",IF(ISNUMBER(SEARCH("francisco",F46)),"USA",IF(ISNUMBER(SEARCH("new york",F46)),"USA",IF(ISNUMBER(SEARCH("california",F46)),"USA",IF(ISNUMBER(SEARCH("palo alto",F46)),"USA",IF(ISNUMBER(SEARCH("santa",F46)),"USA",IF(ISNUMBER(SEARCH("singapore",F46)),"Singapore",IF(ISNUMBER(SEARCH("london",F46)),"London/UK",IF(F46="","Unknown","Other Cities"))))))))))))))))))))))))) -> Delhi-NCR
A47: 46 | B47: 43678 | C47: Progcap | D47: Finance | E47: Supply Chain Management | F47: New Delhi | G47: Sequoia India | H47: =IFERROR(TRIM(LEFT(G47,FIND(",",G47)-1)),TRIM(G47)) -> Sequoia India | I47: =IF(TRIM(G47)="",0,LEN(G47)-LEN(SUBSTITUTE(G47,",",""))+1) -> 1 | J47: =IF(Table1[[#This Row],[Investor Count]]>1,"Yes","No") -> No | K47: Series A | L47: 5000000 | M47: =YEAR(B47) -> 2019 | N47: =TEXT(B47,"mmmm") -> August | O47: 47.98525 | P47: =IF(ISBLANK(K47),"Unknown",IF(OR(ISNUMBER(SEARCH("seed",K47)),ISNUMBER(SEARCH("Seed",K47))),"Seed",IF(ISNUMBER(SEARCH("Series A",K47)),"Series A",IF(ISNUMBER(SEARCH("Series B",K47)),"Series B",IF(ISNUMBER(SEARCH("Series C",K47)),"Series C",IF(ISNUMBER(SEARCH("Series D",K47)),"Series D",IF(ISNUMBER(SEARCH("Private Equity",K47)),"Private Equity","Other"))))))) -> Series A | Q47: =IF(IFERROR(SEARCH("ecom",D47),0)+IFERROR(SEARCH("commerce",D47),0)+IFERROR(SEARCH("retail",D47),0)>0,"E-Commerce", IF(IFERROR(SEARCH("fintech",D47),0)+IFERROR(SEARCH("finance",D47),0)+IFERROR(SEARCH("financial",D47),0)+IFERROR(SEARCH("lending",D47),0)+IFERROR(SEARCH("payment",D47),0)+IFERROR(SEARCH("banking",D47),0)+IFERROR(SEARCH("insurance",D47),0)>0,"FinTech", IF(IFERROR(SEARCH("tech",D47),0)+IFERROR(SEARCH("software",D47),0)+IFERROR(SEARCH("saas",D47),0)+IFERROR(SEARCH("ai",D47),0)+IFERROR(SEARCH("iot",D47),0)+IFERROR(SEARCH("cloud",D47),0)+IFERROR(SEARCH("data",D47),0)+IFERROR(SEARCH("analytics",D47),0)>0,"Technology", IF(IFERROR(SEARCH("food",D47),0)+IFERROR(SEARCH("restaurant",D47),0)+IFERROR(SEARCH("hospitality",D47),0)+IFERROR(SEARCH("beverage",D47),0)+IFERROR(SEARCH("delivery",D47),0)>0,"Food & Beverage", IF(IFERROR(SEARCH("health",D47),0)+IFERROR(SEARCH("medical",D47),0)+IFERROR(SEARCH("pharma",D47),0)+IFERROR(SEARCH("wellness",D47),0)+IFERROR(SEARCH("fitness",D47),0)>0,"Healthcare", IF(IFERROR(SEARCH("edu",D47),0)+IFERROR(SEARCH("learning",D47),0)+IFERROR(SEARCH("school",D47),0)+IFERROR(SEARCH("e-tech",D47),0)>0,"Education", IF(IFERROR(SEARCH("logistics",D47),0)+IFERROR(SEARCH("transport",D47),0)+IFERROR(SEARCH("delivery",D47),0)+IFERROR(SEARCH("mobility",D47),0)+IFERROR(SEARCH("automobile",D47),0)>0,"Logistics & Transport", IF(IFERROR(SEARCH("travel",D47),0)+IFERROR(SEARCH("hotel",D47),0)+IFERROR(SEARCH("booking",D47),0)+IFERROR(SEARCH("tourism",D47),0)>0,"Travel & Hospitality", IF(IFERROR(SEARCH("fashion",D47),0)+IFERROR(SEARCH("apparel",D47),0)+IFERROR(SEARCH("clothing",D47),0)+IFERROR(SEARCH("jewelry",D47),0)+IFERROR(SEARCH("beauty",D47),0)>0,"Fashion & Lifestyle", IF(IFERROR(SEARCH("media",D47),0)+IFERROR(SEARCH("entertainment",D47),0)+IFERROR(SEARCH("video",D47),0)+IFERROR(SEARCH("gaming",D47),0)+IFERROR(SEARCH("music",D47),0)+IFERROR(SEARCH("social",D47),0)>0,"Media & Entertainment", IF(IFERROR(SEARCH("agri",D47),0)+IFERROR(SEARCH("farm",D47),0)+IFERROR(SEARCH("agtech",D47),0)>0,"Agriculture", IF(IFERROR(SEARCH("real estate",D47),0)+IFERROR(SEARCH("property",D47),0)+IFERROR(SEARCH("housing",D47),0)>0,"Real Estate", IF(IFERROR(SEARCH("energy",D47),0)+IFERROR(SEARCH("solar",D47),0)+IFERROR(SEARCH("clean tech",D47),0)+IFERROR(SEARCH("waste",D47),0)>0,"Energy & Environment", IF(IFERROR(SEARCH("hr",D47),0)+IFERROR(SEARCH("recruit",D47),0)+IFERROR(SEARCH("hiring",D47),0)+IFERROR(SEARCH("job",D47),0)>0,"HR & Recruitment", "Others")))))))))))))) -> FinTech | R47: =IF(ISNUMBER(SEARCH("bang",F47)),"Bangalore",IF(ISNUMBER(SEARCH("beng",F47)),"Bangalore",IF(ISNUMBER(SEARCH("mumbai",F47)),"Mumbai",IF(ISNUMBER(SEARCH("delhi",F47)),"Delhi-NCR",IF(ISNUMBER(SEARCH("gurgaon",F47)),"Delhi-NCR",IF(ISNUMBER(SEARCH("gurugram",F47)),"Delhi-NCR",IF(ISNUMBER(SEARCH("noida",F47)),"Delhi-NCR",IF(ISNUMBER(SEARCH("faridabad",F47)),"Delhi-NCR",IF(ISNUMBER(SEARCH("chennai",F47)),"Chennai",IF(ISNUMBER(SEARCH("hyderabad",F47)),"Hyderabad",IF(ISNUMBER(SEARCH("pune",F47)),"Pune",IF(ISNUMBER(SEARCH("kolkata",F47)),"Kolkata",IF(ISNUMBER(SEARCH("ahmedabad",F47)),"Ahmedabad",IF(ISNUMBER(SEARCH("jaipur",F47)),"Jaipur",IF(ISNUMBER(SEARCH("coimbatore",F47)),"Coimbatore",IF(ISNUMBER(SEARCH("kochi",F47)),"Kerala Cities",IF(ISNUMBER(SEARCH("cochin",F47)),"Kerala Cities",IF(ISNUMBER(SEARCH("francisco",F47)),"USA",IF(ISNUMBER(SEARCH("new york",F47)),"USA",IF(ISNUMBER(SEARCH("california",F47)),"USA",IF(ISNUMBER(SEARCH("palo alto",F47)),"USA",IF(ISNUMBER(SEARCH("santa",F47)),"USA",IF(ISNUMBER(SEARCH("singapore",F47)),"Singapore",IF(ISNUMBER(SEARCH("london",F47)),"London/UK",IF(F47="","Unknown","Other Cities"))))))))))))))))))))))))) -> Delhi-NCR
A48: 47 | B48: 43678 | C48: MyPetrolPump | D48: Retail | E48: Fuel Delivery | F48: Bengaluru | G48: Undisclosed | H48: =IFERROR(TRIM(LEFT(G48,FIND(",",G48)-1)),TRIM(G48)) -> Undisclosed | I48: =IF(TRIM(G48)="",0,LEN(G48)-LEN(SUBSTITUTE(G48,",",""))+1) -> 1 | J48: =IF(Table1[[#This Row],[Investor Count]]>1,"Yes","No") -> No | K48: Seed Funding Round | L48: 1600000 | M48: =YEAR(B48) -> 2019 | N48: =TEXT(B48,"mmmm") -> August | O48: 15.35528 | P48: =IF(ISBLANK(K48),"Unknown",IF(OR(ISNUMBER(SEARCH("seed",K48)),ISNUMBER(SEARCH("Seed",K48))),"Seed",IF(ISNUMBER(SEARCH("Series A",K48)),"Series A",IF(ISNUMBER(SEARCH("Series B",K48)),"Series B",IF(ISNUMBER(SEARCH("Series C",K48)),"Series C",IF(ISNUMBER(SEARCH("Series D",K48)),"Series D",IF(ISNUMBER(SEARCH("Private Equity",K48)),"Private Equity","Other"))))))) -> Seed | Q48: =IF(IFERROR(SEARCH("ecom",D48),0)+IFERROR(SEARCH("commerce",D48),0)+IFERROR(SEARCH("retail",D48),0)>0,"E-Commerce", IF(IFERROR(SEARCH("fintech",D48),0)+IFERROR(SEARCH("finance",D48),0)+IFERROR(SEARCH("financial",D48),0)+IFERROR(SEARCH("lending",D48),0)+IFERROR(SEARCH("payment",D48),0)+IFERROR(SEARCH("banking",D48),0)+IFERROR(SEARCH("insurance",D48),0)>0,"FinTech", IF(IFERROR(SEARCH("tech",D48),0)+IFERROR(SEARCH("software",D48),0)+IFERROR(SEARCH("saas",D48),0)+IFERROR(SEARCH("ai",D48),0)+IFERROR(SEARCH("iot",D48),0)+IFERROR(SEARCH("cloud",D48),0)+IFERROR(SEARCH("data",D48),0)+IFERROR(SEARCH("analytics",D48),0)>0,"Technology", IF(IFERROR(SEARCH("food",D48),0)+IFERROR(SEARCH("restaurant",D48),0)+IFERROR(SEARCH("hospitality",D48),0)+IFERROR(SEARCH("beverage",D48),0)+IFERROR(SEARCH("delivery",D48),0)>0,"Food & Beverage", IF(IFERROR(SEARCH("health",D48),0)+IFERROR(SEARCH("medical",D48),0)+IFERROR(SEARCH("pharma",D48),0)+IFERROR(SEARCH("wellness",D48),0)+IFERROR(SEARCH("fitness",D48),0)>0,"Healthcare", IF(IFERROR(SEARCH("edu",D48),0)+IFERROR(SEARCH("learning",D48),0)+IFERROR(SEARCH("school",D48),0)+IFERROR(SEARCH("e-tech",D48),0)>0,"Education", IF(IFERROR(SEARCH("logistics",D48),0)+IFERROR(SEARCH("transport",D48),0)+IFERROR(SEARCH("delivery",D48),0)+IFERROR(SEARCH("mobility",D48),0)+IFERROR(SEARCH("automobile",D48),0)>0,"Logistics & Transport", IF(IFERROR(SEARCH("travel",D48),0)+IFERROR(SEARCH("hotel",D48),0)+IFERROR(SEARCH("booking",D48),0)+IFERROR(SEARCH("tourism",D48),0)>0,"Travel & Hospitality", IF(IFERROR(SEARCH("fashion",D48),0)+IFERROR(SEARCH("apparel",D48),0)+IFERROR(SEARCH("clothing",D48),0)+IFERROR(SEARCH("jewelry",D48),0)+IFERROR(SEARCH("beauty",D48),0)>0,"Fashion & Lifestyle", IF(IFERROR(SEARCH("media",D48),0)+IFERROR(SEARCH("entertainment",D48),0)+IFERROR(SEARCH("video",D48),0)+IFERROR(SEARCH("gaming",D48),0)+IFERROR(SEARCH("music",D48),0)+IFERROR(SEARCH("social",D48),0)>0,"Media & Entertainment", IF(IFERROR(SEARCH("agri",D48),0)+IFERROR(SEARCH("farm",D48),0)+IFERROR(SEARCH("agtech",D48),0)>0,"Agriculture", IF(IFERROR(SEARCH("real estate",D48),0)+IFERROR(SEARCH("property",D48),0)+IFERROR(SEARCH("housing",D48),0)>0,"Real Estate", IF(IFERROR(SEARCH("energy",D48),0)+IFERROR(SEARCH("solar",D48),0)+IFERROR(SEARCH("clean tech",D48),0)+IFERROR(SEARCH("waste",D48),0)>0,"Energy & Environment", IF(IFERROR(SEARCH("hr",D48),0)+IFERROR(SEARCH("recruit",D48),0)+IFERROR(SEARCH("hiring",D48),0)+IFERROR(SEARCH("job",D48),0)>0,"HR & Recruitment", "Others")))))))))))))) -> E-Commerce | R48: =IF(ISNUMBER(SEARCH("bang",F48)),"Bangalore",IF(ISNUMBER(SEARCH("beng",F48)),"Bangalore",IF(ISNUMBER(SEARCH("mumbai",F48)),"Mumbai",IF(ISNUMBER(SEARCH("delhi",F48)),"Delhi-NCR",IF(ISNUMBER(SEARCH("gurgaon",F48)),"Delhi-NCR",IF(ISNUMBER(SEARCH("gurugram",F48)),"Delhi-NCR",IF(ISNUMBER(SEARCH("noida",F48)),"Delhi-NCR",IF(ISNUMBER(SEARCH("faridabad",F48)),"Delhi-NCR",IF(ISNUMBER(SEARCH("chennai",F48)),"Chennai",IF(ISNUMBER(SEARCH("hyderabad",F48)),"Hyderabad",IF(ISNUMBER(SEARCH("pune",F48)),"Pune",IF(ISNUMBER(SEARCH("kolkata",F48)),"Kolkata",IF(ISNUMBER(SEARCH("ahmedabad",F48)),"Ahmedabad",IF(ISNUMBER(SEARCH("jaipur",F48)),"Jaipur",IF(ISNUMBER(SEARCH("coimbatore",F48)),"Coimbatore",IF(ISNUMBER(SEARCH("kochi",F48)),"Kerala Cities",IF(ISNUMBER(SEARCH("cochin",F48)),"Kerala Cities",IF(ISNUMBER(SEARCH("francisco",F48)),"USA",IF(ISNUMBER(SEARCH("new york",F48)),"USA",IF(ISNUMBER(SEARCH("california",F48)),"USA",IF(ISNUMBER(SEARCH("palo alto",F48)),"USA",IF(ISNUMBER(SEARCH("santa",F48)),"USA",IF(ISNUMBER(SEARCH("singapore",F48)),"Singapore",IF(ISNUMBER(SEARCH("london",F48)),"London/UK",IF(F48="","Unknown","Other Cities"))))))))))))))))))))))))) -> Bangalore
